Workbook
Name SegmentaçãodeDados_Dias_de_viagem2: #N/A
Name SegmentaçãodeDados_dsh__dmh_ou_dlh: #N/A
Name SegmentaçãodeDados_Viagem_Urgente_sem_justificativa: #N/A
Name SegmentaçãodeDados_Vínculo_Institucional: #N/A

Sheet Entradas
A1: aux | B1: Identificador do processo de viagem | C1: Número da Proposta (PCDP) | D1: CPF viajante | E1: Nome | F1: Cargo | G1: Função | H1: Descrição Função | I1: Período - Data de início | J1: Período - Data de fim | K1: Motivo | L1: Origem - Data | M1: Destino - Data | N1: Origem - Cidade | O1: Destino - Cidade | P1: Cod Embarque | Q1: Cod Desembarque | R1: Cod Trecho | S1: Distância (km) | T1: Meio de transporte | U1: Missao? | V1: Situação | W1: Viagem Urgente | X1: Justificativa Urgência Viagem | Y1: Valor diárias | Z1: Valor outros gastos | AA1: Valor da passagem | AB1: Taxa de serviço | AC1: Data da emissão/compra | AD1: Classe | AE1: dsh, dmh ou dlh | AF1: EF | AG1: Emissões
A2: =COUNTIF($B$2:B2,B2) -> 1 | B2: 19001658 | C2: 000450/23 | D2: ***.518.375-** | E2: ANGELA DE OLIVEIRA CARNEIRO | F2: PROFESSOR DO MAGISTERIO SUPERIOR | G2: -1 | H2: Sem informação | I2: 45109 | J2: 45121 | K2: O PROPOSTO IRÁ PARTICIPAR COMO MEMBRO DE BANCA DE CONCURSO PÚBLICO DO DEPARTAMENTO DE ENFERMAGEM CLÍNICA | L2: 45109 | M2: 45121 | N2: Petrolina | O2: João Pessoa | P2: =VLOOKUP(N2,[1]ID_Cidades!$A$1:$E$5900,2,FALSE) -> 301428 | Q2: =VLOOKUP(O2,[1]ID_Cidades!$A$1:$E$5900,2,FALSE) -> 295765 | R2: =P2*Q2 -> 89151852420 | S2: =VLOOKUP(R2,'[1]GCD base'!$A$1:$M$200,7,FALSE) -> 665.73966 | T2: Aéreo | U2: Sim | V2: Realizada | W2: SIM | X2: justificativa em anexo. | Y2: 4058.65 | Z2: 0 | AA2: 2260.99 | AB2: 0 | AC2: 45097 | AD2: Econômica | AE2: {=_xlfn.IFS(S2<=Constantes!$G$2,"Muito Curta (evitável)",S2<=Constantes!$H$2,"Curta Distância",S2>Constantes!$H$2,"Longa Distância")} -> Curta Distância | AF2: =IFERROR(VLOOKUP(AE2,Constantes!$A$1:$E$5,MATCH(AD2,Constantes!$A$1:$E$1,0),0),"") -> 0.18286935 | AG2: =AF2*S2 -> 121.74338
A3: =COUNTIF($B$2:B3,B3) -> 2 | B3: 19001658 | C3: 000450/23 | D3: ***.518.375-** | E3: ANGELA DE OLIVEIRA CARNEIRO | F3: PROFESSOR DO MAGISTERIO SUPERIOR | G3: -1 | H3: Sem informação | I3: 45109 | J3: 45121 | K3: O PROPOSTO IRÁ PARTICIPAR COMO MEMBRO DE BANCA DE CONCURSO PÚBLICO DO DEPARTAMENTO DE ENFERMAGEM CLÍNICA | L3: 45121 | M3: 45121 | N3: João Pessoa | O3: Petrolina | P3: =VLOOKUP(N3,[1]ID_Cidades!$A$1:$E$5900,2,FALSE) -> 295765 | Q3: =VLOOKUP(O3,[1]ID_Cidades!$A$1:$E$5900,2,FALSE) -> 301428 | R3: =P3*Q3 -> 89151852420 | S3: =VLOOKUP(R3,'[1]GCD base'!$A$1:$M$200,7,FALSE) -> 665.73966 | T3: Aéreo | U3: Não | V3: Realizada | W3: SIM | X3: justificativa em anexo. | Y3: 0 | Z3: 0 | AA3: 2619.99 | AB3: 0 | AC3: 45097 | AD3: Econômica | AE3: {=_xlfn.IFS(S3<=Constantes!$G$2,"Muito Curta (evitável)",S3<=Constantes!$H$2,"Curta Distância",S3>Constantes!$H$2,"Longa Distância")} -> Curta Distância | AF3: =IFERROR(VLOOKUP(AE3,Constantes!$A$1:$E$5,MATCH(AD3,Constantes!$A$1:$E$1,0),0),"") -> 0.18286935 | AG3: =AF3*S3 -> 121.74338
A4: =COUNTIF($B$2:B4,B4) -> 1 | B4: 19016293 | C4: 000452/23 | D4: ***.187.354-** | E4: MARIA FATIMA DE SOUSA | F4: PROFESSOR DO MAGISTERIO SUPERIOR | G4: -1 | H4: Sem informação | I4: 45109 | J4: 45122 | K4: O PROPOSTO IRÁ PARTICIPAR COMO MEMBRO DE BANCA DE CONCURSO PÚBLICO DO DEPARTAMENTO DE ENFERMAGEM CLÍNICA | L4: 45122 | M4: 45122 | N4: João Pessoa | O4: Brasília | P4: =VLOOKUP(N4,[1]ID_Cidades!$A$1:$E$5900,2,FALSE) -> 295765 | Q4: =VLOOKUP(O4,[1]ID_Cidades!$A$1:$E$5900,2,FALSE) -> 295763 | R4: =P4*Q4 -> 87476343695 | S4: =VLOOKUP(R4,'[1]GCD base'!$A$1:$M$200,7,FALSE) -> 1713.42 | T4: Aéreo | U4: Não | V4: Realizada | W4: SIM | X4: justificativa em anexo. | Y4: 4399.67 | Z4: 0 | AA4: 1639.97 | AB4: 0 | AC4: 45097 | AD4: Econômica | AE4: {=_xlfn.IFS(S4<=Constantes!$G$2,"Muito Curta (evitável)",S4<=Constantes!$H$2,"Curta Distância",S4>Constantes!$H$2,"Longa Distância")} -> Curta Distância | AF4: =IFERROR(VLOOKUP(AE4,Constantes!$A$1:$E$5,MATCH(AD4,Constantes!$A$1:$E$1,0),0),"") -> 0.18286935 | AG4: =AF4*S4 -> 313.33201
A5: =COUNTIF($B$2:B5,B5) -> 2 | B5: 19016293 | C5: 000452/23 | D5: ***.187.354-** | E5: MARIA FATIMA DE SOUSA | F5: PROFESSOR DO MAGISTERIO SUPERIOR | G5: -1 | H5: Sem informação | I5: 45109 | J5: 45122 | K5: O PROPOSTO IRÁ PARTICIPAR COMO MEMBRO DE BANCA DE CONCURSO PÚBLICO DO DEPARTAMENTO DE ENFERMAGEM CLÍNICA | L5: 45109 | M5: 45122 | N5: Brasília | O5: João Pessoa | P5: =VLOOKUP(N5,[1]ID_Cidades!$A$1:$E$5900,2,FALSE) -> 295763 | Q5: =VLOOKUP(O5,[1]ID_Cidades!$A$1:$E$5900,2,FALSE) -> 295765 | R5: =P5*Q5 -> 87476343695 | S5: =VLOOKUP(R5,'[1]GCD base'!$A$1:$M$200,7,FALSE) -> 1713.42 | T5: Aéreo | U5: Sim | V5: Realizada | W5: SIM | X5: justificativa em anexo. | Y5: 0 | Z5: 0 | AA5: 950.99 | AB5: 0 | AC5: 45097 | AD5: Econômica | AE5: {=_xlfn.IFS(S5<=Constantes!$G$2,"Muito Curta (evitável)",S5<=Constantes!$H$2,"Curta Distância",S5>Constantes!$H$2,"Longa Distância")} -> Curta Distância | AF5: =IFERROR(VLOOKUP(AE5,Constantes!$A$1:$E$5,MATCH(AD5,Constantes!$A$1:$E$1,0),0),"") -> 0.18286935 | AG5: =AF5*S5 -> 313.33201
A6: =COUNTIF($B$2:B6,B6) -> 1 | B6: 19019910 | C6: 000457/23 | D6: ***.105.073-** | E6: ROBERTA MENESES OLIVEIRA | F6: PROFESSOR DO MAGISTERIO SUPERIOR | G6: -1 | H6: Sem informação | I6: 45109 | J6: 45122 | K6: O PROPOSTO IRÁ PARTICIPAR COMO MEMBRO DE BANCA DE CONCURSO PÚBLICO DO DEPARTAMENTO DE ENFERMAGEM CLÍNICA | L6: 45109 | M6: 45122 | N6: Fortaleza | O6: João Pessoa | P6: =VLOOKUP(N6,[1]ID_Cidades!$A$1:$E$5900,2,FALSE) -> 314439 | Q6: =VLOOKUP(O6,[1]ID_Cidades!$A$1:$E$5900,2,FALSE) -> 295765 | R6: =P6*Q6 -> 93000050835 | S6: =VLOOKUP(R6,'[1]GCD base'!$A$1:$M$200,7,FALSE) -> 546.23643 | T6: Aéreo | U6: Sim | V6: Realizada | W6: SIM | X6: justificativa em anexo. | Y6: 4399.67 | Z6: 0 | AA6: 1112.61 | AB6: 0 | AC6: 45098 | AD6: Econômica | AE6: {=_xlfn.IFS(S6<=Constantes!$G$2,"Muito Curta (evitável)",S6<=Constantes!$H$2,"Curta Distância",S6>Constantes!$H$2,"Longa Distância")} -> Muito Curta (evitável) | AF6: =IFERROR(VLOOKUP(AE6,Constantes!$A$1:$E$5,MATCH(AD6,Constantes!$A$1:$E$1,0),0),"") -> 0.27257679 | AG6: =AF6*S6 -> 148.89137 | AI6: =COUNTIF(AE:AE,"Muito Curta (evitável)") -> 53
A7: =COUNTIF($B$2:B7,B7) -> 2 | B7: 19019910 | C7: 000457/23 | D7: ***.105.073-** | E7: ROBERTA MENESES OLIVEIRA | F7: PROFESSOR DO MAGISTERIO SUPERIOR | G7: -1 | H7: Sem informação | I7: 45109 | J7: 45122 | K7: O PROPOSTO IRÁ PARTICIPAR COMO MEMBRO DE BANCA DE CONCURSO PÚBLICO DO DEPARTAMENTO DE ENFERMAGEM CLÍNICA | L7: 45122 | M7: 45122 | N7: João Pessoa | O7: Fortaleza | P7: =VLOOKUP(N7,[1]ID_Cidades!$A$1:$E$5900,2,FALSE) -> 295765 | Q7: =VLOOKUP(O7,[1]ID_Cidades!$A$1:$E$5900,2,FALSE) -> 314439 | R7: =P7*Q7 -> 93000050835 | S7: =VLOOKUP(R7,'[1]GCD base'!$A$1:$M$200,7,FALSE) -> 546.23643 | T7: Aéreo | U7: Não | V7: Realizada | W7: SIM | X7: justificativa em anexo. | Y7: 0 | Z7: 0 | AA7: 597.09 | AB7: 0 | AC7: 45098 | AD7: Econômica | AE7: {=_xlfn.IFS(S7<=Constantes!$G$2,"Muito Curta (evitável)",S7<=Constantes!$H$2,"Curta Distância",S7>Constantes!$H$2,"Longa Distância")} -> Muito Curta (evitável) | AF7: =IFERROR(VLOOKUP(AE7,Constantes!$A$1:$E$5,MATCH(AD7,Constantes!$A$1:$E$1,0),0),"") -> 0.27257679 | AG7: =AF7*S7 -> 148.89137
A8: =COUNTIF($B$2:B8,B8) -> 1 | B8: 19041737 | C8: 000481/23-3C | D8: ***.567.773-** | E8: BERLA MOREIRA DE MORAES | F8: PROFESSOR DO MAGISTERIO SUPERIOR | G8: CD-0002 | H8: Cargo Comissionado de Direção | I8: 45110 | J8: 45113 | K8: Participar do I ENCONTRO NACIONAL DE CULTURA & ARTE NAS UNIVERSIDADES FEDERAIS BRASILEIRAS, em Salvador/BA, no período de 03 a 05/07/2023 | L8: 45110 | M8: 45113 | N8: João Pessoa | O8: Salvador | P8: =VLOOKUP(N8,[1]ID_Cidades!$A$1:$E$5900,2,FALSE) -> 295765 | Q8: =VLOOKUP(O8,[1]ID_Cidades!$A$1:$E$5900,2,FALSE) -> 295770 | R8: =P8*Q8 -> 87478414050 | S8: =VLOOKUP(R8,'[1]GCD base'!$A$1:$M$200,7,FALSE) -> 741.11941 | T8: Aéreo | U8: Sim | V8: Realizada | W8: SIM | X8: 0 convite para participar do evento chegou fora do prazo, conforme justificativa no formulário de solicitação | Y8: 1720.73 | Z8: 0 | AA8: 2590.09 | AB8: 0 | AC8: 45104 | AD8: Econômica | AE8: {=_xlfn.IFS(S8<=Constantes!$G$2,"Muito Curta (evitável)",S8<=Constantes!$H$2,"Curta Distância",S8>Constantes!$H$2,"Longa Distância")} -> Curta Distância | AF8: =IFERROR(VLOOKUP(AE8,Constantes!$A$1:$E$5,MATCH(AD8,Constantes!$A$1:$E$1,0),0),"") -> 0.18286935 | AG8: =AF8*S8 -> 135.52803
A9: =COUNTIF($B$2:B9,B9) -> 2 | B9: 19041737 | C9: 000481/23-3C | D9: ***.567.773-** | E9: BERLA MOREIRA DE MORAES | F9: PROFESSOR DO MAGISTERIO SUPERIOR | G9: CD-0002 | H9: Cargo Comissionado de Direção | I9: 45110 | J9: 45113 | K9: Participar do I ENCONTRO NACIONAL DE CULTURA & ARTE NAS UNIVERSIDADES FEDERAIS BRASILEIRAS, em Salvador/BA, no período de 03 a 05/07/2023 | L9: 45113 | M9: 45113 | N9: Salvador | O9: João Pessoa | P9: =VLOOKUP(N9,[1]ID_Cidades!$A$1:$E$5900,2,FALSE) -> 295770 | Q9: =VLOOKUP(O9,[1]ID_Cidades!$A$1:$E$5900,2,FALSE) -> 295765 | R9: =P9*Q9 -> 87478414050 | S9: =VLOOKUP(R9,'[1]GCD base'!$A$1:$M$200,7,FALSE) -> 741.11941 | T9: Aéreo | U9: Não | V9: Realizada | W9: SIM | X9: 0 convite para participar do evento chegou fora do prazo, conforme justificativa no formulário de solicitação | Y9: 0 | Z9: 0 | AA9: 1104.36 | AB9: 0 | AC9: 45104 | AD9: Econômica | AE9: {=_xlfn.IFS(S9<=Constantes!$G$2,"Muito Curta (evitável)",S9<=Constantes!$H$2,"Curta Distância",S9>Constantes!$H$2,"Longa Distância")} -> Curta Distância | AF9: =IFERROR(VLOOKUP(AE9,Constantes!$A$1:$E$5,MATCH(AD9,Constantes!$A$1:$E$1,0),0),"") -> 0.18286935 | AG9: =AF9*S9 -> 135.52803
A10: =COUNTIF($B$2:B10,B10) -> 1 | B10: 19041166 | C10: 000484/23 | D10: ***.028.207-** | E10: MARCELO FERNANDES | G10: -1 | H10: Sem informação | I10: 45112 | J10: 45114 | K10: Ministrar um mini-curso e seminário acadêmico no PPGE/CCSA, nos dias 06 e 07 de julho de 2023. | L10: 45114 | M10: 45114 | N10: João Pessoa | O10: São Paulo | P10: =VLOOKUP(N10,[1]ID_Cidades!$A$1:$E$5900,2,FALSE) -> 295765 | Q10: =VLOOKUP(O10,[1]ID_Cidades!$A$1:$E$5900,2,FALSE) -> 295779 | R10: =P10*Q10 -> 87481075935 | S10: =VLOOKUP(R10,'[1]GCD base'!$A$1:$M$200,7,FALSE) -> 2189.9742 | T10: Aéreo | U10: Não | V10: Realizada | W10: SIM | X10: Aguardava-se a liberação dos recurso do PROAP, por essa razão, não foi solicitado antes. | Y10: 947.55 | Z10: 0 | AA10: 1265.73 | AB10: 0 | AC10: 45105 | AD10: Econômica | AE10: {=_xlfn.IFS(S10<=Constantes!$G$2,"Muito Curta (evitável)",S10<=Constantes!$H$2,"Curta Distância",S10>Constantes!$H$2,"Longa Distância")} -> Curta Distância | AF10: =IFERROR(VLOOKUP(AE10,Constantes!$A$1:$E$5,MATCH(AD10,Constantes!$A$1:$E$1,0),0),"") -> 0.18286935 | AG10: =AF10*S10 -> 400.47918
A11: =COUNTIF($B$2:B11,B11) -> 2 | B11: 19041166 | C11: 000484/23 | D11: ***.028.207-** | E11: MARCELO FERNANDES | G11: -1 | H11: Sem informação | I11: 45112 | J11: 45114 | K11: Ministrar um mini-curso e seminário acadêmico no PPGE/CCSA, nos dias 06 e 07 de julho de 2023. | L11: 45112 | M11: 45114 | N11: São Paulo | O11: João Pessoa | P11: =VLOOKUP(N11,[1]ID_Cidades!$A$1:$E$5900,2,FALSE) -> 295779 | Q11: =VLOOKUP(O11,[1]ID_Cidades!$A$1:$E$5900,2,FALSE) -> 295765 | R11: =P11*Q11 -> 87481075935 | S11: =VLOOKUP(R11,'[1]GCD base'!$A$1:$M$200,7,FALSE) -> 2189.9742 | T11: Aéreo | U11: Sim | V11: Realizada | W11: SIM | X11: Aguardava-se a liberação dos recurso do PROAP, por essa razão, não foi solicitado antes. | Y11: 0 | Z11: 0 | AA11: 1882.09 | AB11: 0 | AC11: 45105 | AD11: Econômica | AE11: {=_xlfn.IFS(S11<=Constantes!$G$2,"Muito Curta (evitável)",S11<=Constantes!$H$2,"Curta Distância",S11>Constantes!$H$2,"Longa Distância")} -> Curta Distância | AF11: =IFERROR(VLOOKUP(AE11,Constantes!$A$1:$E$5,MATCH(AD11,Constantes!$A$1:$E$1,0),0),"") -> 0.18286935 | AG11: =AF11*S11 -> 400.47918
A12: =COUNTIF($B$2:B12,B12) -> 1 | B12: 19062585 | C12: 000508/23 | D12: ***.731.370-** | E12: SERGIO BOTTON BARCELLOS | F12: PROFESSOR DO MAGISTERIO SUPERIOR | G12: FUC-0001 | H12: FUC-0001 | I12: 45117 | J12: 45122 | K12: Participação no 21º Congresso Brasileiro de Sociologia para mediação de um Comitê de Pesquisa e apresentação de um trabalho em GT. Ao mesmo tempo irei representando o PPGS-UFOB como coordenador na Plenária de Programas da área de Sociologia. | L12: 45117 | M12: 45122 | N12: João Pessoa | O12: Belém | P12: =VLOOKUP(N12,[1]ID_Cidades!$A$1:$E$5900,2,FALSE) -> 295765 | Q12: =VLOOKUP(O12,[1]ID_Cidades!$A$1:$E$5900,2,FALSE) -> 300439 | R12: =P12*Q12 -> 88859340835 | S12: =VLOOKUP(R12,'[1]GCD base'!$A$1:$M$200,7,FALSE) -> 1631.4561 | T12: Aéreo | U12: Sim | V12: Realizada | W12: SIM | X12: Recurso PROAP não foi disponibilizado com antecedência. | Y12: 1821.06 | Z12: 0 | AA12: 5292.78 | AB12: 0 | AC12: 45113 | AD12: Econômica | AE12: {=_xlfn.IFS(S12<=Constantes!$G$2,"Muito Curta (evitável)",S12<=Constantes!$H$2,"Curta Distância",S12>Constantes!$H$2,"Longa Distância")} -> Curta Distância | AF12: =IFERROR(VLOOKUP(AE12,Constantes!$A$1:$E$5,MATCH(AD12,Constantes!$A$1:$E$1,0),0),"") -> 0.18286935 | AG12: =AF12*S12 -> 298.34333
A13: =COUNTIF($B$2:B13,B13) -> 2 | B13: 19062585 | C13: 000508/23 | D13: ***.731.370-** | E13: SERGIO BOTTON BARCELLOS | F13: PROFESSOR DO MAGISTERIO SUPERIOR | G13: FUC-0001 | H13: FUC-0001 | I13: 45117 | J13: 45122 | K13: Participação no 21º Congresso Brasileiro de Sociologia para mediação de um Comitê de Pesquisa e apresentação de um trabalho em GT. Ao mesmo tempo irei representando o PPGS-UFOB como coordenador na Plenária de Programas da área de Sociologia. | L13: 45122 | M13: 45122 | N13: Belém | O13: João Pessoa | P13: =VLOOKUP(N13,[1]ID_Cidades!$A$1:$E$5900,2,FALSE) -> 300439 | Q13: =VLOOKUP(O13,[1]ID_Cidades!$A$1:$E$5900,2,FALSE) -> 295765 | R13: =P13*Q13 -> 88859340835 | S13: =VLOOKUP(R13,'[1]GCD base'!$A$1:$M$200,7,FALSE) -> 1631.4561 | T13: Aéreo | U13: Não | V13: Realizada | W13: SIM | X13: Recurso PROAP não foi disponibilizado com antecedência. | Y13: 0 | Z13: 0 | AA13: 0 | AB13: 0 | AC13: 0 | AD13: Econômica | AE13: {=_xlfn.IFS(S13<=Constantes!$G$2,"Muito Curta (evitável)",S13<=Constantes!$H$2,"Curta Distância",S13>Constantes!$H$2,"Longa Distância")} -> Curta Distância | AF13: =IFERROR(VLOOKUP(AE13,Constantes!$A$1:$E$5,MATCH(AD13,Constantes!$A$1:$E$1,0),0),"") -> 0.18286935 | AG13: =AF13*S13 -> 298.34333
A14: =COUNTIF($B$2:B14,B14) -> 1 | B14: 19065213 | C14: 000509/23 | D14: ***.585.343-** | E14: TERESA CRISTINA FURTADO MATOS | F14: PROFESSOR DO MAGISTERIO SUPERIOR | G14: -1 | H14: Sem informação | I14: 45117 | J14: 45122 | K14: Participação no 21º Congresso Brasileiro de Sociologia, com apresentação de trabalho no GT 10 do evento. | L14: 45117 | M14: 45122 | N14: João Pessoa | O14: Belém | P14: =VLOOKUP(N14,[1]ID_Cidades!$A$1:$E$5900,2,FALSE) -> 295765 | Q14: =VLOOKUP(O14,[1]ID_Cidades!$A$1:$E$5900,2,FALSE) -> 300439 | R14: =P14*Q14 -> 88859340835 | S14: =VLOOKUP(R14,'[1]GCD base'!$A$1:$M$200,7,FALSE) -> 1631.4561 | T14: Aéreo | U14: Sim | V14: Realizada | W14: SIM | X14: PROAP não foi liberado anteriormente. | Y14: 1821.06 | Z14: 0 | AA14: 5292.78 | AB14: 0 | AC14: 45114 | AD14: Econômica | AE14: {=_xlfn.IFS(S14<=Constantes!$G$2,"Muito Curta (evitável)",S14<=Constantes!$H$2,"Curta Distância",S14>Constantes!$H$2,"Longa Distância")} -> Curta Distância | AF14: =IFERROR(VLOOKUP(AE14,Constantes!$A$1:$E$5,MATCH(AD14,Constantes!$A$1:$E$1,0),0),"") -> 0.18286935 | AG14: =AF14*S14 -> 298.34333
A15: =COUNTIF($B$2:B15,B15) -> 2 | B15: 19065213 | C15: 000509/23 | D15: ***.585.343-** | E15: TERESA CRISTINA FURTADO MATOS | F15: PROFESSOR DO MAGISTERIO SUPERIOR | G15: -1 | H15: Sem informação | I15: 45117 | J15: 45122 | K15: Participação no 21º Congresso Brasileiro de Sociologia, com apresentação de trabalho no GT 10 do evento. | L15: 45122 | M15: 45122 | N15: Belém | O15: João Pessoa | P15: =VLOOKUP(N15,[1]ID_Cidades!$A$1:$E$5900,2,FALSE) -> 300439 | Q15: =VLOOKUP(O15,[1]ID_Cidades!$A$1:$E$5900,2,FALSE) -> 295765 | R15: =P15*Q15 -> 88859340835 | S15: =VLOOKUP(R15,'[1]GCD base'!$A$1:$M$200,7,FALSE) -> 1631.4561 | T15: Aéreo | U15: Não | V15: Realizada | W15: SIM | X15: PROAP não foi liberado anteriormente. | Y15: 0 | Z15: 0 | AA15: 0 | AB15: 0 | AC15: 0 | AD15: Econômica | AE15: {=_xlfn.IFS(S15<=Constantes!$G$2,"Muito Curta (evitável)",S15<=Constantes!$H$2,"Curta Distância",S15>Constantes!$H$2,"Longa Distância")} -> Curta Distância | AF15: =IFERROR(VLOOKUP(AE15,Constantes!$A$1:$E$5,MATCH(AD15,Constantes!$A$1:$E$1,0),0),"") -> 0.18286935 | AG15: =AF15*S15 -> 298.34333
A16: =COUNTIF($B$2:B16,B16) -> 1 | B16: 19012122 | C16: 000532/23 | D16: ***.103.474-** | E16: HIDELBRANDO JOSE FARKAT DIOGENES | F16: PROFESSOR DO MAGISTERIO SUPERIOR | G16: FUC-0001 | H16: FUC-0001 | I16: 45118 | J16: 45123 | K16: Trata-se da participação em evento científico internacional, a fim de divulgar resultados parciais do doutoramento de Lays Costa, aluna do PPGECAM sob orientação do Prof. Hidelbrando José Farkat Diógenes. | L16: 45122 | M16: 45123 | N16: Santiago | O16: João Pessoa | P16: =VLOOKUP(N16,[1]ID_Cidades!$A$1:$E$5900,2,FALSE) -> 305806 | Q16: =VLOOKUP(O16,[1]ID_Cidades!$A$1:$E$5900,2,FALSE) -> 295765 | R16: =P16*Q16 -> 90446711590 | S16: =VLOOKUP(R16,'[1]GCD base'!$A$1:$M$200,7,FALSE) -> 4701.6614 | T16: Aéreo | U16: Não | V16: Realizada | W16: SIM | X16: A viagem só pode ser cadastrada nesta data devido ao recurso do PROAP destinado ao pagamento da despesa só foi liberado dia 05/07 e estávamos aguardando, também, a realização do empenho específico. | Y16: 4252.24 | Z16: 0 | AA16: 6690.84 | AB16: 0 | AC16: 45113 | AD16: Econômica | AE16: {=_xlfn.IFS(S16<=Constantes!$G$2,"Muito Curta (evitável)",S16<=Constantes!$H$2,"Curta Distância",S16>Constantes!$H$2,"Longa Distância")} -> Longa Distância | AF16: =IFERROR(VLOOKUP(AE16,Constantes!$A$1:$E$5,MATCH(AD16,Constantes!$A$1:$E$1,0),0),"") -> 0.20010828 | AG16: =AF16*S16 -> 940.84139
A17: =COUNTIF($B$2:B17,B17) -> 2 | B17: 19012122 | C17: 000532/23 | D17: ***.103.474-** | E17: HIDELBRANDO JOSE FARKAT DIOGENES | F17: PROFESSOR DO MAGISTERIO SUPERIOR | G17: FUC-0001 | H17: FUC-0001 | I17: 45118 | J17: 45123 | K17: Trata-se da participação em evento científico internacional, a fim de divulgar resultados parciais do doutoramento de Lays Costa, aluna do PPGECAM sob orientação do Prof. Hidelbrando José Farkat Diógenes. | L17: 45118 | M17: 45122 | N17: João Pessoa | O17: Santiago | P17: =VLOOKUP(N17,[1]ID_Cidades!$A$1:$E$5900,2,FALSE) -> 295765 | Q17: =VLOOKUP(O17,[1]ID_Cidades!$A$1:$E$5900,2,FALSE) -> 305806 | R17: =P17*Q17 -> 90446711590 | S17: =VLOOKUP(R17,'[1]GCD base'!$A$1:$M$200,7,FALSE) -> 4701.6614 | T17: Aéreo | U17: Sim | V17: Realizada | W17: SIM | X17: A viagem só pode ser cadastrada nesta data devido ao recurso do PROAP destinado ao pagamento da despesa só foi liberado dia 05/07 e estávamos aguardando, também, a realização do empenho específico. | Y17: 0 | Z17: 0 | AA17: 0 | AB17: 0 | AC17: 0 | AD17: Econômica | AE17: {=_xlfn.IFS(S17<=Constantes!$G$2,"Muito Curta (evitável)",S17<=Constantes!$H$2,"Curta Distância",S17>Constantes!$H$2,"Longa Distância")} -> Longa Distância | AF17: =IFERROR(VLOOKUP(AE17,Constantes!$A$1:$E$5,MATCH(AD17,Constantes!$A$1:$E$1,0),0),"") -> 0.20010828 | AG17: =AF17*S17 -> 940.84139
A18: =COUNTIF($B$2:B18,B18) -> 1 | B18: 18932951 | C18: 000393/23 | D18: ***.778.616-** | E18: PRISCILLA GONTIJO LEITE | F18: PROFESSOR DO MAGISTERIO SUPERIOR | G18: -1 | H18: Sem informação | I18: 45120 | J18: 45128 | K18: Participação da Plenária de Coordenadores do ProfHistória que reúne duas vezes por ano. Esta será a primeira plenária que tem como finalidade de debater e deliberar sobre temas e questões pertinentes ao ProfHistória, propostos pela Comissão Acadêmica Nacional e ou pelas Comissões Acadêmicas Locais. Participação do 32º Simpósio Nacional de História da ANPUH com a comunicação 'Ensino de História Antiga e gamificação para a aprendizagem das formas de governo'. | L18: 45128 | M18: 45128 | N18: São Luís | O18: João Pessoa | P18: =VLOOKUP(N18,[1]ID_Cidades!$A$1:$E$5900,2,FALSE) -> 295771 | Q18: =VLOOKUP(O18,[1]ID_Cidades!$A$1:$E$5900,2,FALSE) -> 295765 | R18: =P18*Q18 -> 87478709815 | S18: =VLOOKUP(R18,'[1]GCD base'!$A$1:$M$200,7,FALSE) -> 1147.347 | T18: Aéreo | U18: Não | V18: Realizada | W18: NÃO | X18: Sem informação | Y18: 2784.3 | Z18: 0 | AA18: 1641.29 | AB18: 0 | AC18: 45083 | AD18: Econômica | AE18: {=_xlfn.IFS(S18<=Constantes!$G$2,"Muito Curta (evitável)",S18<=Constantes!$H$2,"Curta Distância",S18>Constantes!$H$2,"Longa Distância")} -> Curta Distância | AF18: =IFERROR(VLOOKUP(AE18,Constantes!$A$1:$E$5,MATCH(AD18,Constantes!$A$1:$E$1,0),0),"") -> 0.18286935 | AG18: =AF18*S18 -> 209.8146
A19: =COUNTIF($B$2:B19,B19) -> 2 | B19: 18932951 | C19: 000393/23 | D19: ***.778.616-** | E19: PRISCILLA GONTIJO LEITE | F19: PROFESSOR DO MAGISTERIO SUPERIOR | G19: -1 | H19: Sem informação | I19: 45120 | J19: 45128 | K19: Participação da Plenária de Coordenadores do ProfHistória que reúne duas vezes por ano. Esta será a primeira plenária que tem como finalidade de debater e deliberar sobre temas e questões pertinentes ao ProfHistória, propostos pela Comissão Acadêmica Nacional e ou pelas Comissões Acadêmicas Locais. Participação do 32º Simpósio Nacional de História da ANPUH com a comunicação 'Ensino de História Antiga e gamificação para a aprendizagem das formas de governo'. | L19: 45120 | M19: 45128 | N19: João Pessoa | O19: São Luís | P19: =VLOOKUP(N19,[1]ID_Cidades!$A$1:$E$5900,2,FALSE) -> 295765 | Q19: =VLOOKUP(O19,[1]ID_Cidades!$A$1:$E$5900,2,FALSE) -> 295771 | R19: =P19*Q19 -> 87478709815 | S19: =VLOOKUP(R19,'[1]GCD base'!$A$1:$M$200,7,FALSE) -> 1147.347 | T19: Aéreo | U19: Sim | V19: Realizada | W19: NÃO | X19: Sem informação | Y19: 0 | Z19: 0 | AA19: 1643.09 | AB19: 0 | AC19: 45083 | AD19: Econômica | AE19: {=_xlfn.IFS(S19<=Constantes!$G$2,"Muito Curta (evitável)",S19<=Constantes!$H$2,"Curta Distância",S19>Constantes!$H$2,"Longa Distância")} -> Curta Distância | AF19: =IFERROR(VLOOKUP(AE19,Constantes!$A$1:$E$5,MATCH(AD19,Constantes!$A$1:$E$1,0),0),"") -> 0.18286935 | AG19: =AF19*S19 -> 209.8146
A20: =COUNTIF($B$2:B20,B20) -> 1 | B20: 19032444 | C20: 000472/23 | D20: ***.888.244-** | E20: CARLOS ALBERTO OLIVEIRA BONIFACIO JUNIOR | G20: -1 | H20: Sem informação | I20: 45120 | J20: 45125 | K20: PROPOSTO APRESENTARÁ TRABALHO NO 25º FONEPE, QUE OCORRERÁ EM DOURADOS (MS), ENTRE OS DIAS 14,15 E 16 DE JULHO. | L20: 45124 | M20: 45125 | N20: Campo Grande | O20: João Pessoa | P20: =VLOOKUP(N20,[1]ID_Cidades!$A$1:$E$5900,2,FALSE) -> 301205 | Q20: =VLOOKUP(O20,[1]ID_Cidades!$A$1:$E$5900,2,FALSE) -> 295765 | R20: =P20*Q20 -> 89085896825 | S20: =VLOOKUP(R20,'[1]GCD base'!$A$1:$M$200,7,FALSE) -> 2588.8989 | T20: Aéreo | U20: Não | V20: Realizada | W20: SIM | X20: Tendo em vista problemas na emissão da passagem terrestre, a viagem entrou em período de urgência. | Y20: 0 | Z20: 0 | AA20: 932.37 | AB20: 0 | AC20: 45103 | AD20: Econômica | AE20: {=_xlfn.IFS(S20<=Constantes!$G$2,"Muito Curta (evitável)",S20<=Constantes!$H$2,"Curta Distância",S20>Constantes!$H$2,"Longa Distância")} -> Curta Distância | AF20: =IFERROR(VLOOKUP(AE20,Constantes!$A$1:$E$5,MATCH(AD20,Constantes!$A$1:$E$1,0),0),"") -> 0.18286935 | AG20: =AF20*S20 -> 473.43028
A21: =COUNTIF($B$2:B21,B21) -> 2 | B21: 19032444 | C21: 000472/23 | D21: ***.888.244-** | E21: CARLOS ALBERTO OLIVEIRA BONIFACIO JUNIOR | G21: -1 | H21: Sem informação | I21: 45120 | J21: 45125 | K21: PROPOSTO APRESENTARÁ TRABALHO NO 25º FONEPE, QUE OCORRERÁ EM DOURADOS (MS), ENTRE OS DIAS 14,15 E 16 DE JULHO. | L21: 45120 | M21: 45120 | N21: João Pessoa | O21: Campo Grande | P21: =VLOOKUP(N21,[1]ID_Cidades!$A$1:$E$5900,2,FALSE) -> 295765 | Q21: =VLOOKUP(O21,[1]ID_Cidades!$A$1:$E$5900,2,FALSE) -> 301205 | R21: =P21*Q21 -> 89085896825 | S21: =VLOOKUP(R21,'[1]GCD base'!$A$1:$M$200,7,FALSE) -> 2588.8989 | T21: Aéreo | U21: Não | V21: Realizada | W21: SIM | X21: Tendo em vista problemas na emissão da passagem terrestre, a viagem entrou em período de urgência. | Y21: 0 | Z21: 0 | AA21: 1080.09 | AB21: 0 | AC21: 45103 | AD21: Econômica | AE21: {=_xlfn.IFS(S21<=Constantes!$G$2,"Muito Curta (evitável)",S21<=Constantes!$H$2,"Curta Distância",S21>Constantes!$H$2,"Longa Distância")} -> Curta Distância | AF21: =IFERROR(VLOOKUP(AE21,Constantes!$A$1:$E$5,MATCH(AD21,Constantes!$A$1:$E$1,0),0),"") -> 0.18286935 | AG21: =AF21*S21 -> 473.43028
A22: =COUNTIF($B$2:B22,B22) -> 1 | B22: 19098667 | C22: 000601/23 | D22: ***.096.714-** | E22: FRANCISCO HUMBERTO XAVIER JUNIOR | F22: PROFESSOR DO MAGISTERIO SUPERIOR | G22: -1 | H22: Sem informação | I22: 45129 | J22: 45134 | K22: Recebimento do prêmio da 20ª edição do Destaque na Iniciação Científica e Tecnológica entregue pelo presidente do Conselho Nacional de Desenvolvimento Científico e Tecnológico (CNPq), o qual foi concedido a premiação na categoria Iniciação Tecnológica na área das Ciências da Vida para a aluna Ana Flávia Chaves Uchôa, sob minha orientação (anexo I), e será entregue na 75ª Reunião Anual da Sociedade Brasileira para o Progresso da Ciência (SBPC) entre os dias 23 a 29 de julho na Universidade Federal do Paraná (UFPR), em Curitiba | L22: 45134 | M22: 45134 | N22: Curitiba | O22: João Pessoa | P22: =VLOOKUP(N22,[1]ID_Cidades!$A$1:$E$5900,2,FALSE) -> 295780 | Q22: =VLOOKUP(O22,[1]ID_Cidades!$A$1:$E$5900,2,FALSE) -> 295765 | R22: =P22*Q22 -> 87481371700 | S22: =VLOOKUP(R22,'[1]GCD base'!$A$1:$M$200,7,FALSE) -> 2541.6476 | T22: Aéreo | U22: Não | V22: Realizada | W22: SIM | X22: Formulário em anexo | Y22: 1850.97 | Z22: 0 | AA22: 1193.59 | AB22: 0 | AC22: 45125 | AD22: Econômica | AE22: {=_xlfn.IFS(S22<=Constantes!$G$2,"Muito Curta (evitável)",S22<=Constantes!$H$2,"Curta Distância",S22>Constantes!$H$2,"Longa Distância")} -> Curta Distância | AF22: =IFERROR(VLOOKUP(AE22,Constantes!$A$1:$E$5,MATCH(AD22,Constantes!$A$1:$E$1,0),0),"") -> 0.18286935 | AG22: =AF22*S22 -> 464.78946
A23: =COUNTIF($B$2:B23,B23) -> 2 | B23: 19098667 | C23: 000601/23 | D23: ***.096.714-** | E23: FRANCISCO HUMBERTO XAVIER JUNIOR | F23: PROFESSOR DO MAGISTERIO SUPERIOR | G23: -1 | H23: Sem informação | I23: 45129 | J23: 45134 | K23: Recebimento do prêmio da 20ª edição do Destaque na Iniciação Científica e Tecnológica entregue pelo presidente do Conselho Nacional de Desenvolvimento Científico e Tecnológico (CNPq), o qual foi concedido a premiação na categoria Iniciação Tecnológica na área das Ciências da Vida para a aluna Ana Flávia Chaves Uchôa, sob minha orientação (anexo I), e será entregue na 75ª Reunião Anual da Sociedade Brasileira para o Progresso da Ciência (SBPC) entre os dias 23 a 29 de julho na Universidade Federal do Paraná (UFPR), em Curitiba | L23: 45129 | M23: 45134 | N23: João Pessoa | O23: Curitiba | P23: =VLOOKUP(N23,[1]ID_Cidades!$A$1:$E$5900,2,FALSE) -> 295765 | Q23: =VLOOKUP(O23,[1]ID_Cidades!$A$1:$E$5900,2,FALSE) -> 295780 | R23: =P23*Q23 -> 87481371700 | S23: =VLOOKUP(R23,'[1]GCD base'!$A$1:$M$200,7,FALSE) -> 2541.6476 | T23: Aéreo | U23: Sim | V23: Realizada | W23: SIM | X23: Formulário em anexo | Y23: 0 | Z23: 0 | AA23: 1466.89 | AB23: 0 | AC23: 45125 | AD23: Econômica | AE23: {=_xlfn.IFS(S23<=Constantes!$G$2,"Muito Curta (evitável)",S23<=Constantes!$H$2,"Curta Distância",S23>Constantes!$H$2,"Longa Distância")} -> Curta Distância | AF23: =IFERROR(VLOOKUP(AE23,Constantes!$A$1:$E$5,MATCH(AD23,Constantes!$A$1:$E$1,0),0),"") -> 0.18286935 | AG23: =AF23*S23 -> 464.78946
A24: =COUNTIF($B$2:B24,B24) -> 1 | B24: 18973156 | C24: 000407/23 | D24: ***.961.302-** | E24: MARCIA CRISTINA SILVA PAIXAO | F24: PROFESSOR DO MAGISTERIO SUPERIOR | G24: -1 | H24: Sem informação | I24: 45130 | J24: 45135 | K24: Participação do Congresso Nacional da SOBER - Sociedade Brasileira de Economia, Administração e Sociologia Rural como apresentadora de trabalhos, caso o primeiro autor não possa comparecer ao evento. ? Participação do evento como um todo na condição de congressista. Participação da Assembleia Geral da SOBER como componente do seu Conselho Fiscal. | L24: 45130 | M24: 45135 | N24: João Pessoa | O24: Piracicaba | P24: =VLOOKUP(N24,[1]ID_Cidades!$A$1:$E$5900,2,FALSE) -> 295765 | Q24: =VLOOKUP(O24,[1]ID_Cidades!$A$1:$E$5900,2,FALSE) -> 303909 | R24: =P24*Q24 -> 89885645385 | S24: =VLOOKUP(R24,'[1]GCD base'!$A$1:$M$200,7,FALSE) -> 2199.1675 | T24: Aéreo | U24: Sim | V24: Realizada | W24: NÃO | X24: Sem informação | Y24: 1600.4 | Z24: 0 | AA24: 1346.02 | AB24: 0 | AC24: 45083 | AD24: Econômica | AE24: {=_xlfn.IFS(S24<=Constantes!$G$2,"Muito Curta (evitável)",S24<=Constantes!$H$2,"Curta Distância",S24>Constantes!$H$2,"Longa Distância")} -> Curta Distância | AF24: =IFERROR(VLOOKUP(AE24,Constantes!$A$1:$E$5,MATCH(AD24,Constantes!$A$1:$E$1,0),0),"") -> 0.18286935 | AG24: =AF24*S24 -> 402.16035
A25: =COUNTIF($B$2:B25,B25) -> 2 | B25: 18973156 | C25: 000407/23 | D25: ***.961.302-** | E25: MARCIA CRISTINA SILVA PAIXAO | F25: PROFESSOR DO MAGISTERIO SUPERIOR | G25: -1 | H25: Sem informação | I25: 45130 | J25: 45135 | K25: Participação do Congresso Nacional da SOBER - Sociedade Brasileira de Economia, Administração e Sociologia Rural como apresentadora de trabalhos, caso o primeiro autor não possa comparecer ao evento. ? Participação do evento como um todo na condição de congressista. Participação da Assembleia Geral da SOBER como componente do seu Conselho Fiscal. | L25: 45135 | M25: 45135 | N25: Piracicaba | O25: João Pessoa | P25: =VLOOKUP(N25,[1]ID_Cidades!$A$1:$E$5900,2,FALSE) -> 303909 | Q25: =VLOOKUP(O25,[1]ID_Cidades!$A$1:$E$5900,2,FALSE) -> 295765 | R25: =P25*Q25 -> 89885645385 | S25: =VLOOKUP(R25,'[1]GCD base'!$A$1:$M$200,7,FALSE) -> 2199.1675 | T25: Aéreo | U25: Não | V25: Realizada | W25: NÃO | X25: Sem informação | Y25: 0 | Z25: 0 | AA25: 1485.59 | AB25: 0 | AC25: 45083 | AD25: Econômica | AE25: {=_xlfn.IFS(S25<=Constantes!$G$2,"Muito Curta (evitável)",S25<=Constantes!$H$2,"Curta Distância",S25>Constantes!$H$2,"Longa Distância")} -> Curta Distância | AF25: =IFERROR(VLOOKUP(AE25,Constantes!$A$1:$E$5,MATCH(AD25,Constantes!$A$1:$E$1,0),0),"") -> 0.18286935 | AG25: =AF25*S25 -> 402.16035
A26: =COUNTIF($B$2:B26,B26) -> 1 | B26: 19040494 | C26: 000477/23 | D26: ***.840.844-** | E26: HEMILIO FERNANDES CAMPOS COELHO | F26: PROFESSOR DO MAGISTERIO SUPERIOR | G26: FG-0001 | H26: FG-0001 | I26: 45130 | J26: 45136 | K26: Participação do evento científico 67ª Reunião Anual da Região Brasileira da Sociedade Internacional de Biometria (RBras) e 20º Simpósio de Estatística Aplicada à Experimentação Agronômica (SEAGRO) que serão realizados no Centro de Eventos e Convenções do Aurora Shopping na cidade de Londrina. | L26: 45130 | M26: 45136 | N26: João Pessoa | O26: Londrina | P26: =VLOOKUP(N26,[1]ID_Cidades!$A$1:$E$5900,2,FALSE) -> 295765 | Q26: =VLOOKUP(O26,[1]ID_Cidades!$A$1:$E$5900,2,FALSE) -> 304738 | R26: =P26*Q26 -> 90130834570 | S26: =VLOOKUP(R26,'[1]GCD base'!$A$1:$M$200,7,FALSE) -> 2496.4116 | T26: Aéreo | U26: Sim | V26: Realizada | W26: NÃO | X26: Sem informação | Y26: 1901.3 | Z26: 0 | AA26: 1788.29 | AB26: 0 | AC26: 45106 | AD26: Econômica | AE26: {=_xlfn.IFS(S26<=Constantes!$G$2,"Muito Curta (evitável)",S26<=Constantes!$H$2,"Curta Distância",S26>Constantes!$H$2,"Longa Distância")} -> Curta Distância | AF26: =IFERROR(VLOOKUP(AE26,Constantes!$A$1:$E$5,MATCH(AD26,Constantes!$A$1:$E$1,0),0),"") -> 0.18286935 | AG26: =AF26*S26 -> 456.51717
A27: =COUNTIF($B$2:B27,B27) -> 2 | B27: 19040494 | C27: 000477/23 | D27: ***.840.844-** | E27: HEMILIO FERNANDES CAMPOS COELHO | F27: PROFESSOR DO MAGISTERIO SUPERIOR | G27: FG-0001 | H27: FG-0001 | I27: 45130 | J27: 45136 | K27: Participação do evento científico 67ª Reunião Anual da Região Brasileira da Sociedade Internacional de Biometria (RBras) e 20º Simpósio de Estatística Aplicada à Experimentação Agronômica (SEAGRO) que serão realizados no Centro de Eventos e Convenções do Aurora Shopping na cidade de Londrina. | L27: 45136 | M27: 45136 | N27: Londrina | O27: João Pessoa | P27: =VLOOKUP(N27,[1]ID_Cidades!$A$1:$E$5900,2,FALSE) -> 304738 | Q27: =VLOOKUP(O27,[1]ID_Cidades!$A$1:$E$5900,2,FALSE) -> 295765 | R27: =P27*Q27 -> 90130834570 | S27: =VLOOKUP(R27,'[1]GCD base'!$A$1:$M$200,7,FALSE) -> 2496.4116 | T27: Aéreo | U27: Não | V27: Realizada | W27: NÃO | X27: Sem informação | Y27: 0 | Z27: 0 | AA27: 1232.58 | AB27: 0 | AC27: 45106 | AD27: Econômica | AE27: {=_xlfn.IFS(S27<=Constantes!$G$2,"Muito Curta (evitável)",S27<=Constantes!$H$2,"Curta Distância",S27>Constantes!$H$2,"Longa Distância")} -> Curta Distância | AF27: =IFERROR(VLOOKUP(AE27,Constantes!$A$1:$E$5,MATCH(AD27,Constantes!$A$1:$E$1,0),0),"") -> 0.18286935 | AG27: =AF27*S27 -> 456.51717
A28: =COUNTIF($B$2:B28,B28) -> 1 | B28: 19040802 | C28: 000480/23 | D28: ***.447.734-** | E28: ANA HERMINIA ANDRADE E SILVA | F28: PROFESSOR DO MAGISTERIO SUPERIOR | G28: -1 | H28: Sem informação | I28: 45130 | J28: 45136 | K28: Participação do evento científico 67ª Reunião Anual da Região Brasileira da Sociedade Internacional de Biometria (RBras) e 20º Simpósio de Estatística Aplicada à Experimentação Agronômica (SEAGRO) que serão realizados no Centro de Eventos e Convenções do Aurora Shopping na cidade de Londrina. | L28: 45130 | M28: 45136 | N28: João Pessoa | O28: Londrina | P28: =VLOOKUP(N28,[1]ID_Cidades!$A$1:$E$5900,2,FALSE) -> 295765 | Q28: =VLOOKUP(O28,[1]ID_Cidades!$A$1:$E$5900,2,FALSE) -> 304738 | R28: =P28*Q28 -> 90130834570 | S28: =VLOOKUP(R28,'[1]GCD base'!$A$1:$M$200,7,FALSE) -> 2496.4116 | T28: Aéreo | U28: Sim | V28: Realizada | W28: NÃO | X28: Sem informação | Y28: 1901.3 | Z28: 0 | AA28: 1787.18 | AB28: 0 | AC28: 45104 | AD28: Econômica | AE28: {=_xlfn.IFS(S28<=Constantes!$G$2,"Muito Curta (evitável)",S28<=Constantes!$H$2,"Curta Distância",S28>Constantes!$H$2,"Longa Distância")} -> Curta Distância | AF28: =IFERROR(VLOOKUP(AE28,Constantes!$A$1:$E$5,MATCH(AD28,Constantes!$A$1:$E$1,0),0),"") -> 0.18286935 | AG28: =AF28*S28 -> 456.51717
A29: =COUNTIF($B$2:B29,B29) -> 2 | B29: 19040802 | C29: 000480/23 | D29: ***.447.734-** | E29: ANA HERMINIA ANDRADE E SILVA | F29: PROFESSOR DO MAGISTERIO SUPERIOR | G29: -1 | H29: Sem informação | I29: 45130 | J29: 45136 | K29: Participação do evento científico 67ª Reunião Anual da Região Brasileira da Sociedade Internacional de Biometria (RBras) e 20º Simpósio de Estatística Aplicada à Experimentação Agronômica (SEAGRO) que serão realizados no Centro de Eventos e Convenções do Aurora Shopping na cidade de Londrina. | L29: 45136 | M29: 45136 | N29: Londrina | O29: João Pessoa | P29: =VLOOKUP(N29,[1]ID_Cidades!$A$1:$E$5900,2,FALSE) -> 304738 | Q29: =VLOOKUP(O29,[1]ID_Cidades!$A$1:$E$5900,2,FALSE) -> 295765 | R29: =P29*Q29 -> 90130834570 | S29: =VLOOKUP(R29,'[1]GCD base'!$A$1:$M$200,7,FALSE) -> 2496.4116 | T29: Aéreo | U29: Não | V29: Realizada | W29: NÃO | X29: Sem informação | Y29: 0 | Z29: 0 | AA29: 1955.79 | AB29: 0 | AC29: 45104 | AD29: Econômica | AE29: {=_xlfn.IFS(S29<=Constantes!$G$2,"Muito Curta (evitável)",S29<=Constantes!$H$2,"Curta Distância",S29>Constantes!$H$2,"Longa Distância")} -> Curta Distância | AF29: =IFERROR(VLOOKUP(AE29,Constantes!$A$1:$E$5,MATCH(AD29,Constantes!$A$1:$E$1,0),0),"") -> 0.18286935 | AG29: =AF29*S29 -> 456.51717
A30: =COUNTIF($B$2:B30,B30) -> 1 | B30: 19045645 | C30: 000488/23 | D30: ***.260.334-** | E30: EVERLANE SUANE DE ARAUJO DA SILVA | F30: PROFESSOR DO MAGISTERIO SUPERIOR | G30: -1 | H30: Sem informação | I30: 45130 | J30: 45136 | K30: Participação e apresentação em evento científico 67ª Reunião Anual da Região Brasileira da Sociedade Internacional de Biometria (RBras) e 20º Simpósio de Estatística Aplicada à Experimentação Agronômica (SEAGRO) que serão realizados no Centro de Eventos e Convenções do Aurora Shopping na cidade de Londrina. | L30: 45136 | M30: 45136 | N30: Londrina | O30: João Pessoa | P30: =VLOOKUP(N30,[1]ID_Cidades!$A$1:$E$5900,2,FALSE) -> 304738 | Q30: =VLOOKUP(O30,[1]ID_Cidades!$A$1:$E$5900,2,FALSE) -> 295765 | R30: =P30*Q30 -> 90130834570 | S30: =VLOOKUP(R30,'[1]GCD base'!$A$1:$M$200,7,FALSE) -> 2496.4116 | T30: Aéreo | U30: Não | V30: Realizada | W30: NÃO | X30: Sem informação | Y30: 1901.3 | Z30: 0 | AA30: 1232.58 | AB30: 0 | AC30: 45106 | AD30: Econômica | AE30: {=_xlfn.IFS(S30<=Constantes!$G$2,"Muito Curta (evitável)",S30<=Constantes!$H$2,"Curta Distância",S30>Constantes!$H$2,"Longa Distância")} -> Curta Distância | AF30: =IFERROR(VLOOKUP(AE30,Constantes!$A$1:$E$5,MATCH(AD30,Constantes!$A$1:$E$1,0),0),"") -> 0.18286935 | AG30: =AF30*S30 -> 456.51717
A31: =COUNTIF($B$2:B31,B31) -> 2 | B31: 19045645 | C31: 000488/23 | D31: ***.260.334-** | E31: EVERLANE SUANE DE ARAUJO DA SILVA | F31: PROFESSOR DO MAGISTERIO SUPERIOR | G31: -1 | H31: Sem informação | I31: 45130 | J31: 45136 | K31: Participação e apresentação em evento científico 67ª Reunião Anual da Região Brasileira da Sociedade Internacional de Biometria (RBras) e 20º Simpósio de Estatística Aplicada à Experimentação Agronômica (SEAGRO) que serão realizados no Centro de Eventos e Convenções do Aurora Shopping na cidade de Londrina. | L31: 45130 | M31: 45136 | N31: João Pessoa | O31: Londrina | P31: =VLOOKUP(N31,[1]ID_Cidades!$A$1:$E$5900,2,FALSE) -> 295765 | Q31: =VLOOKUP(O31,[1]ID_Cidades!$A$1:$E$5900,2,FALSE) -> 304738 | R31: =P31*Q31 -> 90130834570 | S31: =VLOOKUP(R31,'[1]GCD base'!$A$1:$M$200,7,FALSE) -> 2496.4116 | T31: Aéreo | U31: Sim | V31: Realizada | W31: NÃO | X31: Sem informação | Y31: 0 | Z31: 0 | AA31: 1788.29 | AB31: 0 | AC31: 45106 | AD31: Econômica | AE31: {=_xlfn.IFS(S31<=Constantes!$G$2,"Muito Curta (evitável)",S31<=Constantes!$H$2,"Curta Distância",S31>Constantes!$H$2,"Longa Distância")} -> Curta Distância | AF31: =IFERROR(VLOOKUP(AE31,Constantes!$A$1:$E$5,MATCH(AD31,Constantes!$A$1:$E$1,0),0),"") -> 0.18286935 | AG31: =AF31*S31 -> 456.51717
A32: =COUNTIF($B$2:B32,B32) -> 1 | B32: 19104129 | C32: 000627/23 | D32: ***.919.154-** | E32: SANDRA CRISTINA MORAES DE SOUZA | F32: PROFESSOR ENS BASICO TECN TECNOLOGICO | G32: -1 | H32: Sem informação | I32: 45130 | J32: 45135 | K32: Participar de Oficina na formação na Metodologia Acesso, Permanência e Êxito no Programa Mulheres Mil no período de 24 a 28 de julho de 2023 em Brasília-DF. | L32: 45130 | M32: 45135 | N32: João Pessoa | O32: Brasília | P32: =VLOOKUP(N32,[1]ID_Cidades!$A$1:$E$5900,2,FALSE) -> 295765 | Q32: =VLOOKUP(O32,[1]ID_Cidades!$A$1:$E$5900,2,FALSE) -> 295763 | R32: =P32*Q32 -> 87476343695 | S32: =VLOOKUP(R32,'[1]GCD base'!$A$1:$M$200,7,FALSE) -> 1713.42 | T32: Aéreo | U32: Sim | V32: Realizada | W32: SIM | X32: De acordo com a justificativa anexa. | Y32: 2041.72 | Z32: 0 | AA32: 2113.17 | AB32: 0 | AC32: 45126 | AD32: Econômica | AE32: {=_xlfn.IFS(S32<=Constantes!$G$2,"Muito Curta (evitável)",S32<=Constantes!$H$2,"Curta Distância",S32>Constantes!$H$2,"Longa Distância")} -> Curta Distância | AF32: =IFERROR(VLOOKUP(AE32,Constantes!$A$1:$E$5,MATCH(AD32,Constantes!$A$1:$E$1,0),0),"") -> 0.18286935 | AG32: =AF32*S32 -> 313.33201
A33: =COUNTIF($B$2:B33,B33) -> 2 | B33: 19104129 | C33: 000627/23 | D33: ***.919.154-** | E33: SANDRA CRISTINA MORAES DE SOUZA | F33: PROFESSOR ENS BASICO TECN TECNOLOGICO | G33: -1 | H33: Sem informação | I33: 45130 | J33: 45135 | K33: Participar de Oficina na formação na Metodologia Acesso, Permanência e Êxito no Programa Mulheres Mil no período de 24 a 28 de julho de 2023 em Brasília-DF. | L33: 45135 | M33: 45135 | N33: Brasília | O33: João Pessoa | P33: =VLOOKUP(N33,[1]ID_Cidades!$A$1:$E$5900,2,FALSE) -> 295763 | Q33: =VLOOKUP(O33,[1]ID_Cidades!$A$1:$E$5900,2,FALSE) -> 295765 | R33: =P33*Q33 -> 87476343695 | S33: =VLOOKUP(R33,'[1]GCD base'!$A$1:$M$200,7,FALSE) -> 1713.42 | T33: Aéreo | U33: Não | V33: Realizada | W33: SIM | X33: De acordo com a justificativa anexa. | Y33: 0 | Z33: 0 | AA33: 2569.89 | AB33: 0 | AC33: 45126 | AD33: Econômica | AE33: {=_xlfn.IFS(S33<=Constantes!$G$2,"Muito Curta (evitável)",S33<=Constantes!$H$2,"Curta Distância",S33>Constantes!$H$2,"Longa Distância")} -> Curta Distância | AF33: =IFERROR(VLOOKUP(AE33,Constantes!$A$1:$E$5,MATCH(AD33,Constantes!$A$1:$E$1,0),0),"") -> 0.18286935 | AG33: =AF33*S33 -> 313.33201
... A41: =COUNTIF($B$2:B41,B41) -> 2 | B41: 18924776 | C41: 000329/23 | D41: ***.687.994-** | E41: KARLA KATIUSCIA NOBREGA DE ALMEIDA | F41: PROFESSOR DO MAGISTERIO SUPERIOR | G41: -1 | H41: Sem informação | I41: 45132 | J41: 45135 | K41: Apresentação de 02 artigos científicos de minha co-autoria no 23° USP INTERNATIONAL CONFERENCE ON ACCOUNTING E 20° CONGRESSO USP DE INICIAÇÃO CIENTÍFICA EM CONTABILIDADE - PRESENCIAL | L41: 45135 | M41: 45135 | N41: São Paulo | O41: João Pessoa | P41: =VLOOKUP(N41,[1]ID_Cidades!$A$1:$E$5900,2,FALSE) -> 295779 | Q41: =VLOOKUP(O41,[1]ID_Cidades!$A$1:$E$5900,2,FALSE) -> 295765 | R41: =P41*Q41 -> 87481075935 | S41: =VLOOKUP(R41,'[1]GCD base'!$A$1:$M$200,7,FALSE) -> 2189.9742 | T41: Aéreo | U41: Não | V41: Realizada | W41: NÃO | X41: Sem informação | Y41: 0 | Z41: 0 | AA41: 854.29 | AB41: 0 | AC41: 45065 | AD41: Econômica | AE41: {=_xlfn.IFS(S41<=Constantes!$G$2,"Muito Curta (evitável)",S41<=Constantes!$H$2,"Curta Distância",S41>Constantes!$H$2,"Longa Distância")} -> Curta Distância | AF41: =IFERROR(VLOOKUP(AE41,Constantes!$A$1:$E$5,MATCH(AD41,Constantes!$A$1:$E$1,0),0),"") -> 0.18286935 | AG41: =AF41*S41 -> 400.47918
A42: =COUNTIF($B$2:B42,B42) -> 1 | B42: 18940972 | C42: 000348/23 | D42: ***.834.974-** | E42: EDSON FERREIRA DE ARAUJO | G42: -1 | H42: Sem informação | I42: 45132 | J42: 45136 | K42: PROPOSTO APRESENTARÁ TRABALHO NO 20º CONGRESSO USP DE INICIAÇÃO CIENTÍFICA EM CONTABILIDADE, QUE OCORRERÁ EM SÃO PAULO, ENTRE 26 E 28 DE JULHO DE 2023. | L42: 45136 | M42: 45136 | N42: São Paulo | O42: João Pessoa | P42: =VLOOKUP(N42,[1]ID_Cidades!$A$1:$E$5900,2,FALSE) -> 295779 | Q42: =VLOOKUP(O42,[1]ID_Cidades!$A$1:$E$5900,2,FALSE) -> 295765 | R42: =P42*Q42 -> 87481075935 | S42: =VLOOKUP(R42,'[1]GCD base'!$A$1:$M$200,7,FALSE) -> 2189.9742 | T42: Aéreo | U42: Não | V42: Realizada | W42: NÃO | X42: Sem informação | Y42: 0 | Z42: 0 | AA42: 747.39 | AB42: 0 | AC42: 45071 | AD42: Econômica | AE42: {=_xlfn.IFS(S42<=Constantes!$G$2,"Muito Curta (evitável)",S42<=Constantes!$H$2,"Curta Distância",S42>Constantes!$H$2,"Longa Distância")} -> Curta Distância | AF42: =IFERROR(VLOOKUP(AE42,Constantes!$A$1:$E$5,MATCH(AD42,Constantes!$A$1:$E$1,0),0),"") -> 0.18286935 | AG42: =AF42*S42 -> 400.47918
A43: =COUNTIF($B$2:B43,B43) -> 2 | B43: 18940972 | C43: 000348/23 | D43: ***.834.974-** | E43: EDSON FERREIRA DE ARAUJO | G43: -1 | H43: Sem informação | I43: 45132 | J43: 45136 | K43: PROPOSTO APRESENTARÁ TRABALHO NO 20º CONGRESSO USP DE INICIAÇÃO CIENTÍFICA EM CONTABILIDADE, QUE OCORRERÁ EM SÃO PAULO, ENTRE 26 E 28 DE JULHO DE 2023. | L43: 45132 | M43: 45136 | N43: João Pessoa | O43: São Paulo | P43: =VLOOKUP(N43,[1]ID_Cidades!$A$1:$E$5900,2,FALSE) -> 295765 | Q43: =VLOOKUP(O43,[1]ID_Cidades!$A$1:$E$5900,2,FALSE) -> 295779 | R43: =P43*Q43 -> 87481075935 | S43: =VLOOKUP(R43,'[1]GCD base'!$A$1:$M$200,7,FALSE) -> 2189.9742 | T43: Aéreo | U43: Sim | V43: Realizada | W43: NÃO | X43: Sem informação | Y43: 0 | Z43: 0 | AA43: 731.93 | AB43: 0 | AC43: 45071 | AD43: Econômica | AE43: {=_xlfn.IFS(S43<=Constantes!$G$2,"Muito Curta (evitável)",S43<=Constantes!$H$2,"Curta Distância",S43>Constantes!$H$2,"Longa Distância")} -> Curta Distância | AF43: =IFERROR(VLOOKUP(AE43,Constantes!$A$1:$E$5,MATCH(AD43,Constantes!$A$1:$E$1,0),0),"") -> 0.18286935 | AG43: =AF43*S43 -> 400.47918
A44: =COUNTIF($B$2:B44,B44) -> 1 | B44: 19006789 | C44: 000546/23 | D44: ***.219.784-** | E44: WENNER GLAUCIO LOPES LUCENA | F44: PROFESSOR DO MAGISTERIO SUPERIOR | G44: FUC-0001 | H44: FUC-0001 | I44: 45132 | J44: 45136 | K44: Participação com aprovação de artigo científico no USP Internacional Conference in Accounting da Universidade de São Paulo - USP que será realizado nos dias 26 a 28 de julho de 2023. | L44: 45132 | M44: 45135 | N44: João Pessoa | O44: São Paulo | P44: =VLOOKUP(N44,[1]ID_Cidades!$A$1:$E$5900,2,FALSE) -> 295765 | Q44: =VLOOKUP(O44,[1]ID_Cidades!$A$1:$E$5900,2,FALSE) -> 295779 | R44: =P44*Q44 -> 87481075935 | S44: =VLOOKUP(R44,'[1]GCD base'!$A$1:$M$200,7,FALSE) -> 2189.9742 | T44: Aéreo | U44: Sim | V44: Realizada | W44: NÃO | X44: Sem informação | Y44: 1690.49 | Z44: 0 | AA44: 1305.09 | AB44: 0 | AC44: 45117 | AD44: Econômica | AE44: {=_xlfn.IFS(S44<=Constantes!$G$2,"Muito Curta (evitável)",S44<=Constantes!$H$2,"Curta Distância",S44>Constantes!$H$2,"Longa Distância")} -> Curta Distância | AF44: =IFERROR(VLOOKUP(AE44,Constantes!$A$1:$E$5,MATCH(AD44,Constantes!$A$1:$E$1,0),0),"") -> 0.18286935 | AG44: =AF44*S44 -> 400.47918
A45: =COUNTIF($B$2:B45,B45) -> 2 | B45: 19006789 | C45: 000546/23 | D45: ***.219.784-** | E45: WENNER GLAUCIO LOPES LUCENA | F45: PROFESSOR DO MAGISTERIO SUPERIOR | G45: FUC-0001 | H45: FUC-0001 | I45: 45132 | J45: 45136 | K45: Participação com aprovação de artigo científico no USP Internacional Conference in Accounting da Universidade de São Paulo - USP que será realizado nos dias 26 a 28 de julho de 2023. | L45: 45135 | M45: 45136 | N45: São Paulo | O45: João Pessoa | P45: =VLOOKUP(N45,[1]ID_Cidades!$A$1:$E$5900,2,FALSE) -> 295779 | Q45: =VLOOKUP(O45,[1]ID_Cidades!$A$1:$E$5900,2,FALSE) -> 295765 | R45: =P45*Q45 -> 87481075935 | S45: =VLOOKUP(R45,'[1]GCD base'!$A$1:$M$200,7,FALSE) -> 2189.9742 | T45: Aéreo | U45: Não | V45: Realizada | W45: NÃO | X45: Sem informação | Y45: 0 | Z45: 0 | AA45: 798.83 | AB45: 0 | AC45: 45117 | AD45: Econômica | AE45: {=_xlfn.IFS(S45<=Constantes!$G$2,"Muito Curta (evitável)",S45<=Constantes!$H$2,"Curta Distância",S45>Constantes!$H$2,"Longa Distância")} -> Curta Distância | AF45: =IFERROR(VLOOKUP(AE45,Constantes!$A$1:$E$5,MATCH(AD45,Constantes!$A$1:$E$1,0),0),"") -> 0.18286935 | AG45: =AF45*S45 -> 400.47918
A46: =COUNTIF($B$2:B46,B46) -> 1 | B46: 19052755 | C46: 000545/23 | D46: ***.591.764-** | E46: ROBERIO DANTAS DE FRANCA | F46: PROFESSOR DO MAGISTERIO SUPERIOR | G46: FUC-0001 | H46: FUC-0001 | I46: 45132 | J46: 45136 | K46: Participação no evento USP Internacional Conference in Accounting da Universidade de São Paulo - USP que será realizado nos dias 26 a 28 de julho de 2023, em São Paulo-SP. | L46: 45132 | M46: 45135 | N46: João Pessoa | O46: São Paulo | P46: =VLOOKUP(N46,[1]ID_Cidades!$A$1:$E$5900,2,FALSE) -> 295765 | Q46: =VLOOKUP(O46,[1]ID_Cidades!$A$1:$E$5900,2,FALSE) -> 295779 | R46: =P46*Q46 -> 87481075935 | S46: =VLOOKUP(R46,'[1]GCD base'!$A$1:$M$200,7,FALSE) -> 2189.9742 | T46: Aéreo | U46: Sim | V46: Realizada | W46: NÃO | X46: Sem informação | Y46: 1690.49 | Z46: 0 | AA46: 1305.09 | AB46: 0 | AC46: 45117 | AD46: Econômica | AE46: {=_xlfn.IFS(S46<=Constantes!$G$2,"Muito Curta (evitável)",S46<=Constantes!$H$2,"Curta Distância",S46>Constantes!$H$2,"Longa Distância")} -> Curta Distância | AF46: =IFERROR(VLOOKUP(AE46,Constantes!$A$1:$E$5,MATCH(AD46,Constantes!$A$1:$E$1,0),0),"") -> 0.18286935 | AG46: =AF46*S46 -> 400.47918
A47: =COUNTIF($B$2:B47,B47) -> 2 | B47: 19052755 | C47: 000545/23 | D47: ***.591.764-** | E47: ROBERIO DANTAS DE FRANCA | F47: PROFESSOR DO MAGISTERIO SUPERIOR | G47: FUC-0001 | H47: FUC-0001 | I47: 45132 | J47: 45136 | K47: Participação no evento USP Internacional Conference in Accounting da Universidade de São Paulo - USP que será realizado nos dias 26 a 28 de julho de 2023, em São Paulo-SP. | L47: 45135 | M47: 45136 | N47: São Paulo | O47: João Pessoa | P47: =VLOOKUP(N47,[1]ID_Cidades!$A$1:$E$5900,2,FALSE) -> 295779 | Q47: =VLOOKUP(O47,[1]ID_Cidades!$A$1:$E$5900,2,FALSE) -> 295765 | R47: =P47*Q47 -> 87481075935 | S47: =VLOOKUP(R47,'[1]GCD base'!$A$1:$M$200,7,FALSE) -> 2189.9742 | T47: Aéreo | U47: Não | V47: Realizada | W47: NÃO | X47: Sem informação | Y47: 0 | Z47: 0 | AA47: 798.83 | AB47: 0 | AC47: 45117 | AD47: Econômica | AE47: {=_xlfn.IFS(S47<=Constantes!$G$2,"Muito Curta (evitável)",S47<=Constantes!$H$2,"Curta Distância",S47>Constantes!$H$2,"Longa Distância")} -> Curta Distância | AF47: =IFERROR(VLOOKUP(AE47,Constantes!$A$1:$E$5,MATCH(AD47,Constantes!$A$1:$E$1,0),0),"") -> 0.18286935 | AG47: =AF47*S47 -> 400.47918
A48: =COUNTIF($B$2:B48,B48) -> 1 | B48: 19052806 | C48: 000544/23 | D48: ***.079.524-** | E48: DIMAS BARRETO DE QUEIROZ | F48: PROFESSOR DO MAGISTERIO SUPERIOR | G48: -1 | H48: Sem informação | I48: 45132 | J48: 45136 | K48: Participação com aprovação de artigo científico no USP Internacional Conference in Accounting da Universidade de São Paulo - USP que será realizado nos dias 26 a 28 de julho de 2023. | L48: 45135 | M48: 45136 | N48: São Paulo | O48: João Pessoa | P48: =VLOOKUP(N48,[1]ID_Cidades!$A$1:$E$5900,2,FALSE) -> 295779 | Q48: =VLOOKUP(O48,[1]ID_Cidades!$A$1:$E$5900,2,FALSE) -> 295765 | R48: =P48*Q48 -> 87481075935 | S48: =VLOOKUP(R48,'[1]GCD base'!$A$1:$M$200,7,FALSE) -> 2189.9742 | T48: Aéreo | U48: Não | V48: Realizada | W48: NÃO | X48: Sem informação | Y48: 1690.49 | Z48: 0 | AA48: 1305.09 | AB48: 0 | AC48: 45117 | AD48: Econômica | AE48: {=_xlfn.IFS(S48<=Constantes!$G$2,"Muito Curta (evitável)",S48<=Constantes!$H$2,"Curta Distância",S48>Constantes!$H$2,"Longa Distância")} -> Curta Distância | AF48: =IFERROR(VLOOKUP(AE48,Constantes!$A$1:$E$5,MATCH(AD48,Constantes!$A$1:$E$1,0),0),"") -> 0.18286935 | AG48: =AF48*S48 -> 400.47918
A49: =COUNTIF($B$2:B49,B49) -> 2 | B49: 19052806 | C49: 000544/23 | D49: ***.079.524-** | E49: DIMAS BARRETO DE QUEIROZ | F49: PROFESSOR DO MAGISTERIO SUPERIOR | G49: -1 | H49: Sem informação | I49: 45132 | J49: 45136 | K49: Participação com aprovação de artigo científico no USP Internacional Conference in Accounting da Universidade de São Paulo - USP que será realizado nos dias 26 a 28 de julho de 2023. | L49: 45132 | M49: 45135 | N49: João Pessoa | O49: São Paulo | P49: =VLOOKUP(N49,[1]ID_Cidades!$A$1:$E$5900,2,FALSE) -> 295765 | Q49: =VLOOKUP(O49,[1]ID_Cidades!$A$1:$E$5900,2,FALSE) -> 295779 | R49: =P49*Q49 -> 87481075935 | S49: =VLOOKUP(R49,'[1]GCD base'!$A$1:$M$200,7,FALSE) -> 2189.9742 | T49: Aéreo | U49: Sim | V49: Realizada | W49: NÃO | X49: Sem informação | Y49: 0 | Z49: 0 | AA49: 798.83 | AB49: 0 | AC49: 45117 | AD49: Econômica | AE49: {=_xlfn.IFS(S49<=Constantes!$G$2,"Muito Curta (evitável)",S49<=Constantes!$H$2,"Curta Distância",S49>Constantes!$H$2,"Longa Distância")} -> Curta Distância | AF49: =IFERROR(VLOOKUP(AE49,Constantes!$A$1:$E$5,MATCH(AD49,Constantes!$A$1:$E$1,0),0),"") -> 0.18286935 | AG49: =AF49*S49 -> 400.47918
A50: =COUNTIF($B$2:B50,B50) -> 1 | B50: 19073413 | C50: 000547/23 | D50: ***.265.564-** | E50: CASSIO NUNES DOS ANJOS | G50: -1 | H50: Sem informação | I50: 45133 | J50: 45141 | K50: O proposto apresentará o artigo 'Oil proce forecast: a comparison between ARIMA, LSTM and ARI-MA-LSTM models' no XXIII Encontro Brasileiro de Finanças(EBFIN), que ocorrerá na cidade de São Paulo e também apresentará artigo na XX Escola de Séries Temporais e Econometria (ESTE), na cidade de Florianópolis-SC. | L50: 45141 | M50: 45141 | N50: Florianópolis | O50: João Pessoa | P50: =VLOOKUP(N50,[1]ID_Cidades!$A$1:$E$5900,2,FALSE) -> 295781 | Q50: =VLOOKUP(O50,[1]ID_Cidades!$A$1:$E$5900,2,FALSE) -> 295765 | R50: =P50*Q50 -> 87481667465 | S50: =VLOOKUP(R50,'[1]GCD base'!$A$1:$M$200,7,FALSE) -> 2695.5823 | T50: Aéreo | U50: Não | V50: Realizada | W50: SIM | X50: O pedido de viagem se deu no prazo correto, mas as intercorrências que têm atrasado o processamento da PCDP. | Y50: 0 | Z50: 0 | AA50: 450.63 | AB50: 0 | AC50: 45119 | AD50: Econômica | AE50: {=_xlfn.IFS(S50<=Constantes!$G$2,"Muito Curta (evitável)",S50<=Constantes!$H$2,"Curta Distância",S50>Constantes!$H$2,"Longa Distância")} -> Curta Distância | AF50: =IFERROR(VLOOKUP(AE50,Constantes!$A$1:$E$5,MATCH(AD50,Constantes!$A$1:$E$1,0),0),"") -> 0.18286935 | AG50: =AF50*S50 -> 492.9394
A51: =COUNTIF($B$2:B51,B51) -> 2 | B51: 19073413 | C51: 000547/23 | D51: ***.265.564-** | E51: CASSIO NUNES DOS ANJOS | G51: -1 | H51: Sem informação | I51: 45133 | J51: 45141 | K51: O proposto apresentará o artigo 'Oil proce forecast: a comparison between ARIMA, LSTM and ARI-MA-LSTM models' no XXIII Encontro Brasileiro de Finanças(EBFIN), que ocorrerá na cidade de São Paulo e também apresentará artigo na XX Escola de Séries Temporais e Econometria (ESTE), na cidade de Florianópolis-SC. | L51: 45133 | M51: 45136 | N51: João Pessoa | O51: São Paulo | P51: =VLOOKUP(N51,[1]ID_Cidades!$A$1:$E$5900,2,FALSE) -> 295765 | Q51: =VLOOKUP(O51,[1]ID_Cidades!$A$1:$E$5900,2,FALSE) -> 295779 | R51: =P51*Q51 -> 87481075935 | S51: =VLOOKUP(R51,'[1]GCD base'!$A$1:$M$200,7,FALSE) -> 2189.9742 | T51: Aéreo | U51: Sim | V51: Realizada | W51: SIM | X51: O pedido de viagem se deu no prazo correto, mas as intercorrências que têm atrasado o processamento da PCDP. | Y51: 0 | Z51: 0 | AA51: 1014.79 | AB51: 0 | AC51: 45119 | AD51: Econômica | AE51: {=_xlfn.IFS(S51<=Constantes!$G$2,"Muito Curta (evitável)",S51<=Constantes!$H$2,"Curta Distância",S51>Constantes!$H$2,"Longa Distância")} -> Curta Distância | AF51: =IFERROR(VLOOKUP(AE51,Constantes!$A$1:$E$5,MATCH(AD51,Constantes!$A$1:$E$1,0),0),"") -> 0.18286935 | AG51: =AF51*S51 -> 400.47918
A52: =COUNTIF($B$2:B52,B52) -> 3 | B52: 19073413 | C52: 000547/23 | D52: ***.265.564-** | E52: CASSIO NUNES DOS ANJOS | G52: -1 | H52: Sem informação | I52: 45133 | J52: 45141 | K52: O proposto apresentará o artigo 'Oil proce forecast: a comparison between ARIMA, LSTM and ARI-MA-LSTM models' no XXIII Encontro Brasileiro de Finanças(EBFIN), que ocorrerá na cidade de São Paulo e também apresentará artigo na XX Escola de Séries Temporais e Econometria (ESTE), na cidade de Florianópolis-SC. | L52: 45136 | M52: 45141 | N52: São Paulo | O52: Florianópolis | P52: =VLOOKUP(N52,[1]ID_Cidades!$A$1:$E$5900,2,FALSE) -> 295779 | Q52: =VLOOKUP(O52,[1]ID_Cidades!$A$1:$E$5900,2,FALSE) -> 295781 | R52: =P52*Q52 -> 87485808399 | S52: =VLOOKUP(R52,'[1]GCD base'!$A$1:$M$200,7,FALSE) -> 515.90735 | T52: Aéreo | U52: Sim | V52: Realizada | W52: SIM | X52: O pedido de viagem se deu no prazo correto, mas as intercorrências que têm atrasado o processamento da PCDP. | Y52: 0 | Z52: 0 | AA52: 1127.07 | AB52: 0 | AC52: 45119 | AD52: Econômica | AE52: {=_xlfn.IFS(S52<=Constantes!$G$2,"Muito Curta (evitável)",S52<=Constantes!$H$2,"Curta Distância",S52>Constantes!$H$2,"Longa Distância")} -> Muito Curta (evitável) | AF52: =IFERROR(VLOOKUP(AE52,Constantes!$A$1:$E$5,MATCH(AD52,Constantes!$A$1:$E$1,0),0),"") -> 0.27257679 | AG52: =AF52*S52 -> 140.62437
A53: =COUNTIF($B$2:B53,B53) -> 1 | B53: 19119044 | C53: 000677/23 | D53: ***.134.274-** | E53: FABRINA TAYANE GUEDES FARIAS | G53: -1 | H53: Sem informação | I53: 45141 | J53: 45145 | K53: PROPOSTO IRÁ PARTICIPAR DA II CONFERÊNCIA INTERNACIONAL DA CANNABIS MEDICINAL, NO CENTRO DE CONVENÇÕES FREI CANECA, NA CIDADE DE SÃO PAULO, NO PERÍODO DE 4 A 5 DE AGOSTO DO CORRENTE ANO, ONDE IRÁ APRESENTAR TRABALHO COMO ATIVIDADE ACADÊMICA DO SEU CURSO NA UFPB. | L53: 45144 | M53: 45145 | N53: São Paulo | O53: João Pessoa | P53: =VLOOKUP(N53,[1]ID_Cidades!$A$1:$E$5900,2,FALSE) -> 295779 | Q53: =VLOOKUP(O53,[1]ID_Cidades!$A$1:$E$5900,2,FALSE) -> 295765 | R53: =P53*Q53 -> 87481075935 | S53: =VLOOKUP(R53,'[1]GCD base'!$A$1:$M$200,7,FALSE) -> 2189.9742 | T53: Aéreo | U53: Não | V53: Realizada | W53: SIM | X53: O PROPOSTO APENAS CONSEGUIU A CARTA DE ACEITE DO EVENTO JÁ DENTRO DO PERÍODO DE VIAGEM URGENTE. | Y53: 0 | Z53: 0 | AA53: 1061.29 | AB53: 0 | AC53: 45134 | AD53: Econômica | AE53: {=_xlfn.IFS(S53<=Constantes!$G$2,"Muito Curta (evitável)",S53<=Constantes!$H$2,"Curta Distância",S53>Constantes!$H$2,"Longa Distância")} -> Curta Distância | AF53: =IFERROR(VLOOKUP(AE53,Constantes!$A$1:$E$5,MATCH(AD53,Constantes!$A$1:$E$1,0),0),"") -> 0.18286935 | AG53: =AF53*S53 -> 400.47918
A54: =COUNTIF($B$2:B54,B54) -> 2 | B54: 19119044 | C54: 000677/23 | D54: ***.134.274-** | E54: FABRINA TAYANE GUEDES FARIAS | G54: -1 | H54: Sem informação | I54: 45141 | J54: 45145 | K54: PROPOSTO IRÁ PARTICIPAR DA II CONFERÊNCIA INTERNACIONAL DA CANNABIS MEDICINAL, NO CENTRO DE CONVENÇÕES FREI CANECA, NA CIDADE DE SÃO PAULO, NO PERÍODO DE 4 A 5 DE AGOSTO DO CORRENTE ANO, ONDE IRÁ APRESENTAR TRABALHO COMO ATIVIDADE ACADÊMICA DO SEU CURSO NA UFPB. | L54: 45141 | M54: 45144 | N54: João Pessoa | O54: São Paulo | P54: =VLOOKUP(N54,[1]ID_Cidades!$A$1:$E$5900,2,FALSE) -> 295765 | Q54: =VLOOKUP(O54,[1]ID_Cidades!$A$1:$E$5900,2,FALSE) -> 295779 | R54: =P54*Q54 -> 87481075935 | S54: =VLOOKUP(R54,'[1]GCD base'!$A$1:$M$200,7,FALSE) -> 2189.9742 | T54: Aéreo | U54: Sim | V54: Realizada | W54: SIM | X54: O PROPOSTO APENAS CONSEGUIU A CARTA DE ACEITE DO EVENTO JÁ DENTRO DO PERÍODO DE VIAGEM URGENTE. | Y54: 0 | Z54: 0 | AA54: 947.93 | AB54: 0 | AC54: 45134 | AD54: Econômica | AE54: {=_xlfn.IFS(S54<=Constantes!$G$2,"Muito Curta (evitável)",S54<=Constantes!$H$2,"Curta Distância",S54>Constantes!$H$2,"Longa Distância")} -> Curta Distância | AF54: =IFERROR(VLOOKUP(AE54,Constantes!$A$1:$E$5,MATCH(AD54,Constantes!$A$1:$E$1,0),0),"") -> 0.18286935 | AG54: =AF54*S54 -> 400.47918
A55: =COUNTIF($B$2:B55,B55) -> 1 | B55: 19119322 | C55: 000676/23 | D55: ***.349.934-** | E55: JOAO AURILIO CARDOSO DE MORAES | G55: -1 | H55: Sem informação | I55: 45141 | J55: 45144 | K55: PROPOSTO IRÁ PARTICIPAR DA II CONFERÊNCIA INTERNACIONAL DA CANNABIS MEDICINAL, NO CENTRO DE CONVENÇÕES FREI CANECA, NA CIDADE DE SÃO PAULO, NO PERÍODO DE 4 A 5 DE AGOSTO DO CORRENTE ANO, ONDE IRÁ APRESENTAR TRABALHO COMO ATIVIDADE ACADÊMICA DO SEU CURSO NA UFPB. | L55: 45141 | M55: 45144 | N55: João Pessoa | O55: São Paulo | P55: =VLOOKUP(N55,[1]ID_Cidades!$A$1:$E$5900,2,FALSE) -> 295765 | Q55: =VLOOKUP(O55,[1]ID_Cidades!$A$1:$E$5900,2,FALSE) -> 295779 | R55: =P55*Q55 -> 87481075935 | S55: =VLOOKUP(R55,'[1]GCD base'!$A$1:$M$200,7,FALSE) -> 2189.9742 | T55: Aéreo | U55: Sim | V55: Realizada | W55: SIM | X55: O PROPOSTO APENAS CONSEGUIU A CARTA DE ACEITE DO EVENTO JÁ DENTRO DO PERÍODO DE VIAGEM URGENTE. | Y55: 0 | Z55: 0 | AA55: 1061.29 | AB55: 0 | AC55: 45134 | AD55: Econômica | AE55: {=_xlfn.IFS(S55<=Constantes!$G$2,"Muito Curta (evitável)",S55<=Constantes!$H$2,"Curta Distância",S55>Constantes!$H$2,"Longa Distância")} -> Curta Distância | AF55: =IFERROR(VLOOKUP(AE55,Constantes!$A$1:$E$5,MATCH(AD55,Constantes!$A$1:$E$1,0),0),"") -> 0.18286935 | AG55: =AF55*S55 -> 400.47918
A56: =COUNTIF($B$2:B56,B56) -> 2 | B56: 19119322 | C56: 000676/23 | D56: ***.349.934-** | E56: JOAO AURILIO CARDOSO DE MORAES | G56: -1 | H56: Sem informação | I56: 45141 | J56: 45144 | K56: PROPOSTO IRÁ PARTICIPAR DA II CONFERÊNCIA INTERNACIONAL DA CANNABIS MEDICINAL, NO CENTRO DE CONVENÇÕES FREI CANECA, NA CIDADE DE SÃO PAULO, NO PERÍODO DE 4 A 5 DE AGOSTO DO CORRENTE ANO, ONDE IRÁ APRESENTAR TRABALHO COMO ATIVIDADE ACADÊMICA DO SEU CURSO NA UFPB. | L56: 45144 | M56: 45144 | N56: São Paulo | O56: João Pessoa | P56: =VLOOKUP(N56,[1]ID_Cidades!$A$1:$E$5900,2,FALSE) -> 295779 | Q56: =VLOOKUP(O56,[1]ID_Cidades!$A$1:$E$5900,2,FALSE) -> 295765 | R56: =P56*Q56 -> 87481075935 | S56: =VLOOKUP(R56,'[1]GCD base'!$A$1:$M$200,7,FALSE) -> 2189.9742 | T56: Aéreo | U56: Não | V56: Realizada | W56: SIM | X56: O PROPOSTO APENAS CONSEGUIU A CARTA DE ACEITE DO EVENTO JÁ DENTRO DO PERÍODO DE VIAGEM URGENTE. | Y56: 0 | Z56: 0 | AA56: 947.93 | AB56: 0 | AC56: 45134 | AD56: Econômica | AE56: {=_xlfn.IFS(S56<=Constantes!$G$2,"Muito Curta (evitável)",S56<=Constantes!$H$2,"Curta Distância",S56>Constantes!$H$2,"Longa Distância")} -> Curta Distância | AF56: =IFERROR(VLOOKUP(AE56,Constantes!$A$1:$E$5,MATCH(AD56,Constantes!$A$1:$E$1,0),0),"") -> 0.18286935 | AG56: =AF56*S56 -> 400.47918
A57: =COUNTIF($B$2:B57,B57) -> 1 | B57: 19109815 | C57: 000660/23 | D57: ***.051.554-** | E57: VALDINEY VELOSO GOUVEIA | F57: PROFESSOR DO MAGISTERIO SUPERIOR | G57: CD-0001 | H57: Cargo Comissionado de Direção | I57: 45142 | J57: 45143 | K57: Participar da Cerimônia de Transmissão de Cargos de Reitor e Vice-Reitora da Universidade Federal do Rio de Janeiro, no Rio de Janeiro/RJ, no dia 04/08/2023. | L57: 45142 | M57: 45143 | N57: Rio de Janeiro | O57: João Pessoa | P57: =VLOOKUP(N57,[1]ID_Cidades!$A$1:$E$5900,2,FALSE) -> 295778 | Q57: =VLOOKUP(O57,[1]ID_Cidades!$A$1:$E$5900,2,FALSE) -> 295765 | R57: =P57*Q57 -> 87480780170 | S57: =VLOOKUP(R57,'[1]GCD base'!$A$1:$M$200,7,FALSE) -> 1961.5008 | T57: Aéreo | U57: Não | V57: Realizada | W57: SIM | X57: Em razão da agenda da Reitoria, somente na data de 20/07/2023, proposto confirmou a ida, conforme justificativa no item 7 do Formulário de Solicitação. | Y57: 715.32 | Z57: 0 | AA57: 736.69 | AB57: 0 | AC57: 45128 | AD57: Econômica | AE57: {=_xlfn.IFS(S57<=Constantes!$G$2,"Muito Curta (evitável)",S57<=Constantes!$H$2,"Curta Distância",S57>Constantes!$H$2,"Longa Distância")} -> Curta Distância | AF57: =IFERROR(VLOOKUP(AE57,Constantes!$A$1:$E$5,MATCH(AD57,Constantes!$A$1:$E$1,0),0),"") -> 0.18286935 | AG57: =AF57*S57 -> 358.69838
A58: =COUNTIF($B$2:B58,B58) -> 2 | B58: 19109815 | C58: 000660/23 | D58: ***.051.554-** | E58: VALDINEY VELOSO GOUVEIA | F58: PROFESSOR DO MAGISTERIO SUPERIOR | G58: CD-0001 | H58: Cargo Comissionado de Direção | I58: 45142 | J58: 45143 | K58: Participar da Cerimônia de Transmissão de Cargos de Reitor e Vice-Reitora da Universidade Federal do Rio de Janeiro, no Rio de Janeiro/RJ, no dia 04/08/2023. | L58: 45142 | M58: 45142 | N58: João Pessoa | O58: Rio de Janeiro | P58: =VLOOKUP(N58,[1]ID_Cidades!$A$1:$E$5900,2,FALSE) -> 295765 | Q58: =VLOOKUP(O58,[1]ID_Cidades!$A$1:$E$5900,2,FALSE) -> 295778 | R58: =P58*Q58 -> 87480780170 | S58: =VLOOKUP(R58,'[1]GCD base'!$A$1:$M$200,7,FALSE) -> 1961.5008 | T58: Aéreo | U58: Sim | V58: Realizada | W58: SIM | X58: Em razão da agenda da Reitoria, somente na data de 20/07/2023, proposto confirmou a ida, conforme justificativa no item 7 do Formulário de Solicitação. | Y58: 0 | Z58: 0 | AA58: 733.4 | AB58: 0 | AC58: 45128 | AD58: Econômica | AE58: {=_xlfn.IFS(S58<=Constantes!$G$2,"Muito Curta (evitável)",S58<=Constantes!$H$2,"Curta Distância",S58>Constantes!$H$2,"Longa Distância")} -> Curta Distância | AF58: =IFERROR(VLOOKUP(AE58,Constantes!$A$1:$E$5,MATCH(AD58,Constantes!$A$1:$E$1,0),0),"") -> 0.18286935 | AG58: =AF58*S58 -> 358.69838
A59: =COUNTIF($B$2:B59,B59) -> 1 | B59: 19076735 | C59: 000561/23 | D59: ***.427.978-** | E59: MARCELO DE SOUZA BISPO | F59: PROFESSOR DO MAGISTERIO SUPERIOR | G59: FUC-0001 | H59: FUC-0001 | I59: 45143 | J59: 45146 | K59: O Coordenador irá participar de uma reunião convidado pela Capes juntamente com todos os coordenadores de pós-graduação das Regiões Norte, Nordeste e Centro-Oeste da área de Administração Pública e de Empresas, Ciências Contábeis e Turismo (área 27). | L59: 45143 | M59: 45146 | N59: João Pessoa | O59: Salvador | P59: =VLOOKUP(N59,[1]ID_Cidades!$A$1:$E$5900,2,FALSE) -> 295765 | Q59: =VLOOKUP(O59,[1]ID_Cidades!$A$1:$E$5900,2,FALSE) -> 295770 | R59: =P59*Q59 -> 87478414050 | S59: =VLOOKUP(R59,'[1]GCD base'!$A$1:$M$200,7,FALSE) -> 741.11941 | T59: Aéreo | U59: Sim | V59: Realizada | W59: NÃO | X59: Sem informação | Y59: 1228.75 | Z59: 0 | AA59: 769.29 | AB59: 0 | AC59: 45117 | AD59: Econômica | AE59: {=_xlfn.IFS(S59<=Constantes!$G$2,"Muito Curta (evitável)",S59<=Constantes!$H$2,"Curta Distância",S59>Constantes!$H$2,"Longa Distância")} -> Curta Distância | AF59: =IFERROR(VLOOKUP(AE59,Constantes!$A$1:$E$5,MATCH(AD59,Constantes!$A$1:$E$1,0),0),"") -> 0.18286935 | AG59: =AF59*S59 -> 135.52803
A60: =COUNTIF($B$2:B60,B60) -> 2 | B60: 19076735 | C60: 000561/23 | D60: ***.427.978-** | E60: MARCELO DE SOUZA BISPO | F60: PROFESSOR DO MAGISTERIO SUPERIOR | G60: FUC-0001 | H60: FUC-0001 | I60: 45143 | J60: 45146 | K60: O Coordenador irá participar de uma reunião convidado pela Capes juntamente com todos os coordenadores de pós-graduação das Regiões Norte, Nordeste e Centro-Oeste da área de Administração Pública e de Empresas, Ciências Contábeis e Turismo (área 27). | L60: 45146 | M60: 45146 | N60: Salvador | O60: João Pessoa | P60: =VLOOKUP(N60,[1]ID_Cidades!$A$1:$E$5900,2,FALSE) -> 295770 | Q60: =VLOOKUP(O60,[1]ID_Cidades!$A$1:$E$5900,2,FALSE) -> 295765 | R60: =P60*Q60 -> 87478414050 | S60: =VLOOKUP(R60,'[1]GCD base'!$A$1:$M$200,7,FALSE) -> 741.11941 | T60: Aéreo | U60: Não | V60: Realizada | W60: NÃO | X60: Sem informação | Y60: 0 | Z60: 0 | AA60: 533.06 | AB60: 0 | AC60: 45117 | AD60: Econômica | AE60: {=_xlfn.IFS(S60<=Constantes!$G$2,"Muito Curta (evitável)",S60<=Constantes!$H$2,"Curta Distância",S60>Constantes!$H$2,"Longa Distância")} -> Curta Distância | AF60: =IFERROR(VLOOKUP(AE60,Constantes!$A$1:$E$5,MATCH(AD60,Constantes!$A$1:$E$1,0),0),"") -> 0.18286935 | AG60: =AF60*S60 -> 135.52803
A61: =COUNTIF($B$2:B61,B61) -> 1 | B61: 19041175 | C61: 000491/23 | D61: ***.514.605-** | E61: ILKA DIAS BICHARA | G61: -1 | H61: Sem informação | I61: 45144 | J61: 45159 | K61: Participar como membro efetivo em banca examinadora de Concurso Público na área de Psicologia do Desenvolvimento Infantil, Edital nº 57/2022/UFPB. | L61: 45144 | M61: 45159 | N61: Salvador | O61: João Pessoa | P61: =VLOOKUP(N61,[1]ID_Cidades!$A$1:$E$5900,2,FALSE) -> 295770 | Q61: =VLOOKUP(O61,[1]ID_Cidades!$A$1:$E$5900,2,FALSE) -> 295765 | R61: =P61*Q61 -> 87478414050 | S61: =VLOOKUP(R61,'[1]GCD base'!$A$1:$M$200,7,FALSE) -> 741.11941 | T61: Aéreo | U61: Sim | V61: Realizada | W61: NÃO | X61: Sem informação | Y61: 0 | Z61: 0 | AA61: 586.76 | AB61: 0 | AC61: 45111 | AD61: Econômica | AE61: {=_xlfn.IFS(S61<=Constantes!$G$2,"Muito Curta (evitável)",S61<=Constantes!$H$2,"Curta Distância",S61>Constantes!$H$2,"Longa Distância")} -> Curta Distância | AF61: =IFERROR(VLOOKUP(AE61,Constantes!$A$1:$E$5,MATCH(AD61,Constantes!$A$1:$E$1,0),0),"") -> 0.18286935 | AG61: =AF61*S61 -> 135.52803
A62: =COUNTIF($B$2:B62,B62) -> 2 | B62: 19041175 | C62: 000491/23 | D62: ***.514.605-** | E62: ILKA DIAS BICHARA | G62: -1 | H62: Sem informação | I62: 45144 | J62: 45159 | K62: Participar como membro efetivo em banca examinadora de Concurso Público na área de Psicologia do Desenvolvimento Infantil, Edital nº 57/2022/UFPB. | L62: 45159 | M62: 45159 | N62: João Pessoa | O62: Salvador | P62: =VLOOKUP(N62,[1]ID_Cidades!$A$1:$E$5900,2,FALSE) -> 295765 | Q62: =VLOOKUP(O62,[1]ID_Cidades!$A$1:$E$5900,2,FALSE) -> 295770 | R62: =P62*Q62 -> 87478414050 | S62: =VLOOKUP(R62,'[1]GCD base'!$A$1:$M$200,7,FALSE) -> 741.11941 | T62: Aéreo | U62: Não | V62: Realizada | W62: NÃO | X62: Sem informação | Y62: 0 | Z62: 0 | AA62: 591.39 | AB62: 0 | AC62: 45111 | AD62: Econômica | AE62: {=_xlfn.IFS(S62<=Constantes!$G$2,"Muito Curta (evitável)",S62<=Constantes!$H$2,"Curta Distância",S62>Constantes!$H$2,"Longa Distância")} -> Curta Distância | AF62: =IFERROR(VLOOKUP(AE62,Constantes!$A$1:$E$5,MATCH(AD62,Constantes!$A$1:$E$1,0),0),"") -> 0.18286935 | AG62: =AF62*S62 -> 135.52803
A63: =COUNTIF($B$2:B63,B63) -> 1 | B63: 19044799 | C63: 000507/23 | D63: ***.042.567-** | E63: VERA MARIA RAMOS DE VASCONCELLOS | G63: -1 | H63: Sem informação | I63: 45144 | J63: 45159 | K63: Participar como membro efetivo em banca examinadora de Concurso Público na área de Psicologia do Desenvolvimento Infantil, Edital nº 57/2022/UFPB. | L63: 45159 | M63: 45159 | N63: João Pessoa | O63: Rio de Janeiro | P63: =VLOOKUP(N63,[1]ID_Cidades!$A$1:$E$5900,2,FALSE) -> 295765 | Q63: =VLOOKUP(O63,[1]ID_Cidades!$A$1:$E$5900,2,FALSE) -> 295778 | R63: =P63*Q63 -> 87480780170 | S63: =VLOOKUP(R63,'[1]GCD base'!$A$1:$M$200,7,FALSE) -> 1961.5008 | T63: Aéreo | U63: Não | V63: Realizada | W63: NÃO | X63: Sem informação | Y63: 5380.81 | Z63: 0 | AA63: 910.8 | AB63: 0 | AC63: 45112 | AD63: Econômica | AE63: {=_xlfn.IFS(S63<=Constantes!$G$2,"Muito Curta (evitável)",S63<=Constantes!$H$2,"Curta Distância",S63>Constantes!$H$2,"Longa Distância")} -> Curta Distância | AF63: =IFERROR(VLOOKUP(AE63,Constantes!$A$1:$E$5,MATCH(AD63,Constantes!$A$1:$E$1,0),0),"") -> 0.18286935 | AG63: =AF63*S63 -> 358.69838
A64: =COUNTIF($B$2:B64,B64) -> 2 | B64: 19044799 | C64: 000507/23 | D64: ***.042.567-** | E64: VERA MARIA RAMOS DE VASCONCELLOS | G64: -1 | H64: Sem informação | I64: 45144 | J64: 45159 | K64: Participar como membro efetivo em banca examinadora de Concurso Público na área de Psicologia do Desenvolvimento Infantil, Edital nº 57/2022/UFPB. | L64: 45144 | M64: 45159 | N64: Rio de Janeiro | O64: João Pessoa | P64: =VLOOKUP(N64,[1]ID_Cidades!$A$1:$E$5900,2,FALSE) -> 295778 | Q64: =VLOOKUP(O64,[1]ID_Cidades!$A$1:$E$5900,2,FALSE) -> 295765 | R64: =P64*Q64 -> 87480780170 | S64: =VLOOKUP(R64,'[1]GCD base'!$A$1:$M$200,7,FALSE) -> 1961.5008 | T64: Aéreo | U64: Sim | V64: Realizada | W64: NÃO | X64: Sem informação | Y64: 0 | Z64: 0 | AA64: 805.69 | AB64: 0 | AC64: 45112 | AD64: Econômica | AE64: {=_xlfn.IFS(S64<=Constantes!$G$2,"Muito Curta (evitável)",S64<=Constantes!$H$2,"Curta Distância",S64>Constantes!$H$2,"Longa Distância")} -> Curta Distância | AF64: =IFERROR(VLOOKUP(AE64,Constantes!$A$1:$E$5,MATCH(AD64,Constantes!$A$1:$E$1,0),0),"") -> 0.18286935 | AG64: =AF64*S64 -> 358.69838
A65: =COUNTIF($B$2:B65,B65) -> 1 | B65: 19052875 | C65: 000565/23 | D65: ***.219.784-** | E65: WENNER GLAUCIO LOPES LUCENA | F65: PROFESSOR DO MAGISTERIO SUPERIOR | G65: FUC-0001 | H65: FUC-0001 | I65: 45144 | J65: 45146 | K65: Participação da reunião de coordenadores de programas de pós-graduação das Regiões Norte, Nordeste e Centro-Oeste da área de Administração Pública e de Empresas, Ciências Contábeis e Turismo (área 27). | L65: 45146 | M65: 45146 | N65: Salvador | O65: João Pessoa | P65: =VLOOKUP(N65,[1]ID_Cidades!$A$1:$E$5900,2,FALSE) -> 295770 | Q65: =VLOOKUP(O65,[1]ID_Cidades!$A$1:$E$5900,2,FALSE) -> 295765 | R65: =P65*Q65 -> 87478414050 | S65: =VLOOKUP(R65,'[1]GCD base'!$A$1:$M$200,7,FALSE) -> 741.11941 | T65: Aéreo | U65: Não | V65: Realizada | W65: NÃO | X65: Sem informação | Y65: 887.73 | Z65: 0 | AA65: 452.36 | AB65: 0 | AC65: 45118 | AD65: Econômica | AE65: {=_xlfn.IFS(S65<=Constantes!$G$2,"Muito Curta (evitável)",S65<=Constantes!$H$2,"Curta Distância",S65>Constantes!$H$2,"Longa Distância")} -> Curta Distância | AF65: =IFERROR(VLOOKUP(AE65,Constantes!$A$1:$E$5,MATCH(AD65,Constantes!$A$1:$E$1,0),0),"") -> 0.18286935 | AG65: =AF65*S65 -> 135.52803
A66: =COUNTIF($B$2:B66,B66) -> 2 | B66: 19052875 | C66: 000565/23 | D66: ***.219.784-** | E66: WENNER GLAUCIO LOPES LUCENA | F66: PROFESSOR DO MAGISTERIO SUPERIOR | G66: FUC-0001 | H66: FUC-0001 | I66: 45144 | J66: 45146 | K66: Participação da reunião de coordenadores de programas de pós-graduação das Regiões Norte, Nordeste e Centro-Oeste da área de Administração Pública e de Empresas, Ciências Contábeis e Turismo (área 27). | L66: 45144 | M66: 45146 | N66: João Pessoa | O66: Salvador | P66: =VLOOKUP(N66,[1]ID_Cidades!$A$1:$E$5900,2,FALSE) -> 295765 | Q66: =VLOOKUP(O66,[1]ID_Cidades!$A$1:$E$5900,2,FALSE) -> 295770 | R66: =P66*Q66 -> 87478414050 | S66: =VLOOKUP(R66,'[1]GCD base'!$A$1:$M$200,7,FALSE) -> 741.11941 | T66: Aéreo | U66: Sim | V66: Realizada | W66: NÃO | X66: Sem informação | Y66: 0 | Z66: 0 | AA66: 502.39 | AB66: 0 | AC66: 45118 | AD66: Econômica | AE66: {=_xlfn.IFS(S66<=Constantes!$G$2,"Muito Curta (evitável)",S66<=Constantes!$H$2,"Curta Distância",S66>Constantes!$H$2,"Longa Distância")} -> Curta Distância | AF66: =IFERROR(VLOOKUP(AE66,Constantes!$A$1:$E$5,MATCH(AD66,Constantes!$A$1:$E$1,0),0),"") -> 0.18286935 | AG66: =AF66*S66 -> 135.52803
A67: =COUNTIF($B$2:B67,B67) -> 1 | B67: 19086266 | C67: 000588/23 | D67: ***.932.194-** | E67: ANA CAROLINA KRUTA DE ARAUJO BISPO | F67: PROFESSOR DO MAGISTERIO SUPERIOR | G67: -1 | H67: Sem informação | I67: 45144 | J67: 45146 | K67: Trata-se de participação para a reunião de coordenadores de programas de pós-graduação das Regiões Norte, Nordeste e Centro-Oeste da área de Administração Pública e de Empresas, Ciências Contábeis e Turismo (área 27), que acontecerá no dia 07 de agosto de 2023, das 9h00 às 18h00, em Salvador/BA, na Escola de Administração da Universidade Federal da Bahia (EAUFBA). | L67: 45144 | M67: 45146 | N67: João Pessoa | O67: Salvador | P67: =VLOOKUP(N67,[1]ID_Cidades!$A$1:$E$5900,2,FALSE) -> 295765 | Q67: =VLOOKUP(O67,[1]ID_Cidades!$A$1:$E$5900,2,FALSE) -> 295770 | R67: =P67*Q67 -> 87478414050 | S67: =VLOOKUP(R67,'[1]GCD base'!$A$1:$M$200,7,FALSE) -> 741.11941 | T67: Aéreo | U67: Sim | V67: Realizada | W67: NÃO | X67: Sem informação | Y67: 887.73 | Z67: 0 | AA67: 764.66 | AB67: 0 | AC67: 45119 | AD67: Econômica | AE67: {=_xlfn.IFS(S67<=Constantes!$G$2,"Muito Curta (evitável)",S67<=Constantes!$H$2,"Curta Distância",S67>Constantes!$H$2,"Longa Distância")} -> Curta Distância | AF67: =IFERROR(VLOOKUP(AE67,Constantes!$A$1:$E$5,MATCH(AD67,Constantes!$A$1:$E$1,0),0),"") -> 0.18286935 | AG67: =AF67*S67 -> 135.52803
A68: =COUNTIF($B$2:B68,B68) -> 2 | B68: 19086266 | C68: 000588/23 | D68: ***.932.194-** | E68: ANA CAROLINA KRUTA DE ARAUJO BISPO | F68: PROFESSOR DO MAGISTERIO SUPERIOR | G68: -1 | H68: Sem informação | I68: 45144 | J68: 45146 | K68: Trata-se de participação para a reunião de coordenadores de programas de pós-graduação das Regiões Norte, Nordeste e Centro-Oeste da área de Administração Pública e de Empresas, Ciências Contábeis e Turismo (área 27), que acontecerá no dia 07 de agosto de 2023, das 9h00 às 18h00, em Salvador/BA, na Escola de Administração da Universidade Federal da Bahia (EAUFBA). | L68: 45146 | M68: 45146 | N68: Salvador | O68: João Pessoa | P68: =VLOOKUP(N68,[1]ID_Cidades!$A$1:$E$5900,2,FALSE) -> 295770 | Q68: =VLOOKUP(O68,[1]ID_Cidades!$A$1:$E$5900,2,FALSE) -> 295765 | R68: =P68*Q68 -> 87478414050 | S68: =VLOOKUP(R68,'[1]GCD base'!$A$1:$M$200,7,FALSE) -> 741.11941 | T68: Aéreo | U68: Não | V68: Realizada | W68: NÃO | X68: Sem informação | Y68: 0 | Z68: 0 | AA68: 769.29 | AB68: 0 | AC68: 45119 | AD68: Econômica | AE68: {=_xlfn.IFS(S68<=Constantes!$G$2,"Muito Curta (evitável)",S68<=Constantes!$H$2,"Curta Distância",S68>Constantes!$H$2,"Longa Distância")} -> Curta Distância | AF68: =IFERROR(VLOOKUP(AE68,Constantes!$A$1:$E$5,MATCH(AD68,Constantes!$A$1:$E$1,0),0),"") -> 0.18286935 | AG68: =AF68*S68 -> 135.52803
A69: =COUNTIF($B$2:B69,B69) -> 1 | B69: 19105380 | C69: 000667/23 | D69: ***.720.987-** | E69: NELSON MACULAN FILHO | G69: -1 | H69: Sem informação | I69: 45144 | J69: 45147 | K69: Reunião de pesquisa com o grupo de pesquisa em Otimização do PPGI, no período de 7 a 8 de agosto, dando continuidades às pesquisas em Programação Geométrica na sua parceria com o Professor Roberto Quirino | L69: 45147 | M69: 45147 | N69: João Pessoa | O69: Rio de Janeiro | P69: =VLOOKUP(N69,[1]ID_Cidades!$A$1:$E$5900,2,FALSE) -> 295765 | Q69: =VLOOKUP(O69,[1]ID_Cidades!$A$1:$E$5900,2,FALSE) -> 295778 | R69: =P69*Q69 -> 87480780170 | S69: =VLOOKUP(R69,'[1]GCD base'!$A$1:$M$200,7,FALSE) -> 1961.5008 | T69: Aéreo | U69: Não | V69: Realizada | W69: SIM | X69: Foi necessário solicitar o empenho de diárias, o que se deu na data de 24/07/2023. | Y69: 1288.57 | Z69: 0 | AA69: 782.79 | AB69: 0 | AC69: 45132 | AD69: Econômica | AE69: {=_xlfn.IFS(S69<=Constantes!$G$2,"Muito Curta (evitável)",S69<=Constantes!$H$2,"Curta Distância",S69>Constantes!$H$2,"Longa Distância")} -> Curta Distância | AF69: =IFERROR(VLOOKUP(AE69,Constantes!$A$1:$E$5,MATCH(AD69,Constantes!$A$1:$E$1,0),0),"") -> 0.18286935 | AG69: =AF69*S69 -> 358.69838
A70: =COUNTIF($B$2:B70,B70) -> 2 | B70: 19105380 | C70: 000667/23 | D70: ***.720.987-** | E70: NELSON MACULAN FILHO | G70: -1 | H70: Sem informação | I70: 45144 | J70: 45147 | K70: Reunião de pesquisa com o grupo de pesquisa em Otimização do PPGI, no período de 7 a 8 de agosto, dando continuidades às pesquisas em Programação Geométrica na sua parceria com o Professor Roberto Quirino | L70: 45144 | M70: 45147 | N70: Rio de Janeiro | O70: João Pessoa | P70: =VLOOKUP(N70,[1]ID_Cidades!$A$1:$E$5900,2,FALSE) -> 295778 | Q70: =VLOOKUP(O70,[1]ID_Cidades!$A$1:$E$5900,2,FALSE) -> 295765 | R70: =P70*Q70 -> 87480780170 | S70: =VLOOKUP(R70,'[1]GCD base'!$A$1:$M$200,7,FALSE) -> 1961.5008 | T70: Aéreo | U70: Sim | V70: Realizada | W70: SIM | X70: Foi necessário solicitar o empenho de diárias, o que se deu na data de 24/07/2023. | Y70: 0 | Z70: 0 | AA70: 930.99 | AB70: 0 | AC70: 45132 | AD70: Econômica | AE70: {=_xlfn.IFS(S70<=Constantes!$G$2,"Muito Curta (evitável)",S70<=Constantes!$H$2,"Curta Distância",S70>Constantes!$H$2,"Longa Distância")} -> Curta Distância | AF70: =IFERROR(VLOOKUP(AE70,Constantes!$A$1:$E$5,MATCH(AD70,Constantes!$A$1:$E$1,0),0),"") -> 0.18286935 | AG70: =AF70*S70 -> 358.69838
A71: =COUNTIF($B$2:B71,B71) -> 1 | B71: 19109127 | C71: 000696/23 | D71: ***.374.698-** | E71: REGINA STELA CORREA VIEIRA | F71: PROFESSOR DO MAGISTERIO SUPERIOR | G71: -1 | H71: Sem informação | I71: 45144 | J71: 45148 | K71: Participação, nos dias 7, 8 e 9 de agosto, como membro titular externo, na comissão examinadora da área de conhecimento 'Direito Público e Novos Direitos' do concurso público regido pelo Edital nº 57/2022, procedido pelo Departamento de Ciências Jurídicas da UFPB, no trabalho de avaliação da Prova Didática, segunda fase do referido concurso. Além disso, promoção, mas manhãs dos dias 8 e 9 de agosto, do minicurso 'Gênero, direito e neoliberalismo' junto aos estudantes do Curso de Bacharelado em Direito - Santa Rita. | L71: 45144 | M71: 45144 | N71: São Paulo | O71: Recife | P71: =VLOOKUP(N71,[1]ID_Cidades!$A$1:$E$5900,2,FALSE) -> 295779 | Q71: =VLOOKUP(O71,[1]ID_Cidades!$A$1:$E$5900,2,FALSE) -> 295766 | R71: =P71*Q71 -> 87481371714 | S71: =VLOOKUP(R71,'[1]GCD base'!$A$1:$M$200,7,FALSE) -> 2100.4987 | T71: Aéreo | U71: Não | V71: Realizada | W71: SIM | X71: Participação, nos dias 7, 8 e 9 de agosto, como membro titular externo, na comissão examinadora da área de conhecimento 'Direito Público e Novos Direitos' do concurso público regido pelo Edital nº 57/2022, procedido pelo Departamento de Ciências Jurídicas da UFPB, no trabalho de avaliação da Prova Didática, segunda fase do referido concurso. Além disso, promoção, mas manhãs dos dias 8 e 9 de agosto, do minicurso 'Gênero, direito e neoliberalismo' junto aos estudantes do Curso de Bacharelado em Direito - Santa Rita. | Y71: 1449.05 | Z71: 0 | AA71: 0 | AB71: 0 | AC71: 0 | AD71: Econômica | AE71: {=_xlfn.IFS(S71<=Constantes!$G$2,"Muito Curta (evitável)",S71<=Constantes!$H$2,"Curta Distância",S71>Constantes!$H$2,"Longa Distância")} -> Curta Distância | AF71: =IFERROR(VLOOKUP(AE71,Constantes!$A$1:$E$5,MATCH(AD71,Constantes!$A$1:$E$1,0),0),"") -> 0.18286935 | AG71: =AF71*S71 -> 384.11685
A72: =COUNTIF($B$2:B72,B72) -> 1 | B72: 19132757 | C72: 000719/23 | D72: ***.680.354-** | E72: SUELY AMORIM DE ARAUJO | F72: PROFESSOR DO MAGISTERIO SUPERIOR | G72: -1 | H72: Sem informação | I72: 45144 | J72: 45156 | K72: O proposto vira participar como membro de banca do concurso do departamento de enfermagem clínicas. | L72: 45156 | M72: 45156 | N72: João Pessoa | O72: Uberlândia | P72: =VLOOKUP(N72,[1]ID_Cidades!$A$1:$E$5900,2,FALSE) -> 295765 | Q72: =VLOOKUP(O72,[1]ID_Cidades!$A$1:$E$5900,2,FALSE) -> 303403 | R72: =P72*Q72 -> 89735988295 | S72: =VLOOKUP(R72,'[1]GCD base'!$A$1:$M$200,7,FALSE) -> 1941.3673 | T72: Aéreo | U72: Não | V72: Realizada | W72: SIM | X72: Conforme justificativa em anexo. | Y72: 4058.65 | Z72: 0 | AA72: 2507.42 | AB72: 0 | AC72: 45141 | AD72: Econômica | AE72: {=_xlfn.IFS(S72<=Constantes!$G$2,"Muito Curta (evitável)",S72<=Constantes!$H$2,"Curta Distância",S72>Constantes!$H$2,"Longa Distância")} -> Curta Distância | AF72: =IFERROR(VLOOKUP(AE72,Constantes!$A$1:$E$5,MATCH(AD72,Constantes!$A$1:$E$1,0),0),"") -> 0.18286935 | AG72: =AF72*S72 -> 355.01659
A73: =COUNTIF($B$2:B73,B73) -> 2 | B73: 19132757 | C73: 000719/23 | D73: ***.680.354-** | E73: SUELY AMORIM DE ARAUJO | F73: PROFESSOR DO MAGISTERIO SUPERIOR | G73: -1 | H73: Sem informação | I73: 45144 | J73: 45156 | K73: O proposto vira participar como membro de banca do concurso do departamento de enfermagem clínicas. | L73: 45144 | M73: 45156 | N73: Uberlândia | O73: João Pessoa | P73: =VLOOKUP(N73,[1]ID_Cidades!$A$1:$E$5900,2,FALSE) -> 303403 | Q73: =VLOOKUP(O73,[1]ID_Cidades!$A$1:$E$5900,2,FALSE) -> 295765 | R73: =P73*Q73 -> 89735988295 | S73: =VLOOKUP(R73,'[1]GCD base'!$A$1:$M$200,7,FALSE) -> 1941.3673 | T73: Aéreo | U73: Sim | V73: Realizada | W73: SIM | X73: Conforme justificativa em anexo. | Y73: 0 | Z73: 0 | AA73: 1810.59 | AB73: 0 | AC73: 45141 | AD73: Econômica | AE73: {=_xlfn.IFS(S73<=Constantes!$G$2,"Muito Curta (evitável)",S73<=Constantes!$H$2,"Curta Distância",S73>Constantes!$H$2,"Longa Distância")} -> Curta Distância | AF73: =IFERROR(VLOOKUP(AE73,Constantes!$A$1:$E$5,MATCH(AD73,Constantes!$A$1:$E$1,0),0),"") -> 0.18286935 | AG73: =AF73*S73 -> 355.01659
A74: =COUNTIF($B$2:B74,B74) -> 1 | B74: 18937420 | C74: 000422/23 | D74: ***.795.756-** | E74: LUIZ GUSTAVO AZEVEDO CARVALHO PIMENTEL | G74: -1 | H74: Sem informação | I74: 45146 | J74: 45158 | K74: Participar como um dos convidados especiais do PPGM/UFPB para participar do 6º Festival Internacional de Música de Câmara PPGM/UFPB, no período de 09 a 19/08/2023, em João Pessoa/PB | L74: 45146 | M74: 45158 | N74: Rio de Janeiro | O74: João Pessoa | P74: =VLOOKUP(N74,[1]ID_Cidades!$A$1:$E$5900,2,FALSE) -> 295778 | Q74: =VLOOKUP(O74,[1]ID_Cidades!$A$1:$E$5900,2,FALSE) -> 295765 | R74: =P74*Q74 -> 87480780170 | S74: =VLOOKUP(R74,'[1]GCD base'!$A$1:$M$200,7,FALSE) -> 1961.5008 | T74: Aéreo | U74: Sim | V74: Realizada | W74: NÃO | X74: Sem informação | Y74: 0 | Z74: 0 | AA74: 932.99 | AB74: 0 | AC74: 45089 | AD74: Econômica | AE74: {=_xlfn.IFS(S74<=Constantes!$G$2,"Muito Curta (evitável)",S74<=Constantes!$H$2,"Curta Distância",S74>Constantes!$H$2,"Longa Distância")} -> Curta Distância | AF74: =IFERROR(VLOOKUP(AE74,Constantes!$A$1:$E$5,MATCH(AD74,Constantes!$A$1:$E$1,0),0),"") -> 0.18286935 | AG74: =AF74*S74 -> 358.69838
A75: =COUNTIF($B$2:B75,B75) -> 2 | B75: 18937420 | C75: 000422/23 | D75: ***.795.756-** | E75: LUIZ GUSTAVO AZEVEDO CARVALHO PIMENTEL | G75: -1 | H75: Sem informação | I75: 45146 | J75: 45158 | K75: Participar como um dos convidados especiais do PPGM/UFPB para participar do 6º Festival Internacional de Música de Câmara PPGM/UFPB, no período de 09 a 19/08/2023, em João Pessoa/PB | L75: 45158 | M75: 45158 | N75: João Pessoa | O75: Rio de Janeiro | P75: =VLOOKUP(N75,[1]ID_Cidades!$A$1:$E$5900,2,FALSE) -> 295765 | Q75: =VLOOKUP(O75,[1]ID_Cidades!$A$1:$E$5900,2,FALSE) -> 295778 | R75: =P75*Q75 -> 87480780170 | S75: =VLOOKUP(R75,'[1]GCD base'!$A$1:$M$200,7,FALSE) -> 1961.5008 | T75: Aéreo | U75: Não | V75: Realizada | W75: NÃO | X75: Sem informação | Y75: 0 | Z75: 0 | AA75: 816.29 | AB75: 0 | AC75: 45089 | AD75: Econômica | AE75: {=_xlfn.IFS(S75<=Constantes!$G$2,"Muito Curta (evitável)",S75<=Constantes!$H$2,"Curta Distância",S75>Constantes!$H$2,"Longa Distância")} -> Curta Distância | AF75: =IFERROR(VLOOKUP(AE75,Constantes!$A$1:$E$5,MATCH(AD75,Constantes!$A$1:$E$1,0),0),"") -> 0.18286935 | AG75: =AF75*S75 -> 358.69838
A76: =COUNTIF($B$2:B76,B76) -> 1 | B76: 19092693 | C76: 000625/23 | D76: ***.837.834-** | E76: RENATA DA SILVA LEITE | F76: FARMACEUTICO | G76: FG-0003 | H76: FG-0003 | I76: 45146 | J76: 45149 | K76: O Congresso está relacionado com área de tecnologia e produção de medicamentos, sendo importante a participação da Diretoria de Pesquisas Tecnológicas do IPeFarM no referido evento, além disso, o IPeFarM faz parte da Associação dos Laboratórios Farmacêuticos Oficiais do Brasil (ALFOB) que está promovendo o I Congresso dos Laboratórios Farmacêuticos Oficiais do Brasil. | L76: 45146 | M76: 45149 | N76: João Pessoa | O76: Brasília | P76: =VLOOKUP(N76,[1]ID_Cidades!$A$1:$E$5900,2,FALSE) -> 295765 | Q76: =VLOOKUP(O76,[1]ID_Cidades!$A$1:$E$5900,2,FALSE) -> 295763 | R76: =P76*Q76 -> 87476343695 | S76: =VLOOKUP(R76,'[1]GCD base'!$A$1:$M$200,7,FALSE) -> 1713.42 | T76: Aéreo | U76: Sim | V76: Realizada | W76: NÃO | X76: Sem informação | Y76: 1214.35 | Z76: 0 | AA76: 2376.26 | AB76: 0 | AC76: 45131 | AD76: Econômica | AE76: {=_xlfn.IFS(S76<=Constantes!$G$2,"Muito Curta (evitável)",S76<=Constantes!$H$2,"Curta Distância",S76>Constantes!$H$2,"Longa Distância")} -> Curta Distância | AF76: =IFERROR(VLOOKUP(AE76,Constantes!$A$1:$E$5,MATCH(AD76,Constantes!$A$1:$E$1,0),0),"") -> 0.18286935 | AG76: =AF76*S76 -> 313.33201
A77: =COUNTIF($B$2:B77,B77) -> 2 | B77: 19092693 | C77: 000625/23 | D77: ***.837.834-** | E77: RENATA DA SILVA LEITE | F77: FARMACEUTICO | G77: FG-0003 | H77: FG-0003 | I77: 45146 | J77: 45149 | K77: O Congresso está relacionado com área de tecnologia e produção de medicamentos, sendo importante a participação da Diretoria de Pesquisas Tecnológicas do IPeFarM no referido evento, além disso, o IPeFarM faz parte da Associação dos Laboratórios Farmacêuticos Oficiais do Brasil (ALFOB) que está promovendo o I Congresso dos Laboratórios Farmacêuticos Oficiais do Brasil. | L77: 45149 | M77: 45149 | N77: Brasília | O77: João Pessoa | P77: =VLOOKUP(N77,[1]ID_Cidades!$A$1:$E$5900,2,FALSE) -> 295763 | Q77: =VLOOKUP(O77,[1]ID_Cidades!$A$1:$E$5900,2,FALSE) -> 295765 | R77: =P77*Q77 -> 87476343695 | S77: =VLOOKUP(R77,'[1]GCD base'!$A$1:$M$200,7,FALSE) -> 1713.42 | T77: Aéreo | U77: Não | V77: Realizada | W77: NÃO | X77: Sem informação | Y77: 0 | Z77: 0 | AA77: 0 | AB77: 0 | AC77: 0 | AD77: Econômica | AE77: {=_xlfn.IFS(S77<=Constantes!$G$2,"Muito Curta (evitável)",S77<=Constantes!$H$2,"Curta Distância",S77>Constantes!$H$2,"Longa Distância")} -> Curta Distância | AF77: =IFERROR(VLOOKUP(AE77,Constantes!$A$1:$E$5,MATCH(AD77,Constantes!$A$1:$E$1,0),0),"") -> 0.18286935 | AG77: =AF77*S77 -> 313.33201
A78: =COUNTIF($B$2:B78,B78) -> 1 | B78: 19127610 | C78: 000690/23 | D78: ***.270.137-** | E78: PALOMA RODRIGUES DUARTE DA NOBREGA | F78: AUDITOR | G78: CD-0004 | H78: Cargo Comissionado de Direção | I78: 45146 | J78: 45150 | K78: Participar do Congresso Brasileiro de Auditoria e Controle Interno COBACI/2023, que será realizado em Maceió/AL, no período de 09 a 11/08/2023 | L78: 45146 | M78: 45150 | N78: João Pessoa | O78: Maceió | P78: =VLOOKUP(N78,[1]ID_Cidades!$A$1:$E$5900,2,FALSE) -> 295765 | Q78: =VLOOKUP(O78,[1]ID_Cidades!$A$1:$E$5900,2,FALSE) -> 295768 | R78: =P78*Q78 -> 87477822520 | S78: =VLOOKUP(R78,'[1]GCD base'!$A$1:$M$200,7,FALSE) -> 279.06946 | T78: Aéreo | U78: Sim | V78: Realizada | W78: SIM | X78: Viagem Urgente para participação de evento de capacitação. Por questões administrativas o Processo teve seu trâmite prejudicado, mas o pedido foi realizado com 20 dias, conforme justificativa no formulário de solicitação | Y78: 1509.95 | Z78: 0 | AA78: 731.19 | AB78: 0 | AC78: 45134 | AD78: Econômica | AE78: {=_xlfn.IFS(S78<=Constantes!$G$2,"Muito Curta (evitável)",S78<=Constantes!$H$2,"Curta Distância",S78>Constantes!$H$2,"Longa Distância")} -> Muito Curta (evitável) | AF78: =IFERROR(VLOOKUP(AE78,Constantes!$A$1:$E$5,MATCH(AD78,Constantes!$A$1:$E$1,0),0),"") -> 0.27257679 | AG78: =AF78*S78 -> 76.067857
A79: =COUNTIF($B$2:B79,B79) -> 2 | B79: 19127610 | C79: 000690/23 | D79: ***.270.137-** | E79: PALOMA RODRIGUES DUARTE DA NOBREGA | F79: AUDITOR | G79: CD-0004 | H79: Cargo Comissionado de Direção | I79: 45146 | J79: 45150 | K79: Participar do Congresso Brasileiro de Auditoria e Controle Interno COBACI/2023, que será realizado em Maceió/AL, no período de 09 a 11/08/2023 | L79: 45150 | M79: 45150 | N79: Maceió | O79: João Pessoa | P79: =VLOOKUP(N79,[1]ID_Cidades!$A$1:$E$5900,2,FALSE) -> 295768 | Q79: =VLOOKUP(O79,[1]ID_Cidades!$A$1:$E$5900,2,FALSE) -> 295765 | R79: =P79*Q79 -> 87477822520 | S79: =VLOOKUP(R79,'[1]GCD base'!$A$1:$M$200,7,FALSE) -> 279.06946 | T79: Aéreo | U79: Não | V79: Realizada | W79: SIM | X79: Viagem Urgente para participação de evento de capacitação. Por questões administrativas o Processo teve seu trâmite prejudicado, mas o pedido foi realizado com 20 dias, conforme justificativa no formulário de solicitação | Y79: 0 | Z79: 0 | AA79: 635.29 | AB79: 0 | AC79: 45134 | AD79: Econômica | AE79: {=_xlfn.IFS(S79<=Constantes!$G$2,"Muito Curta (evitável)",S79<=Constantes!$H$2,"Curta Distância",S79>Constantes!$H$2,"Longa Distância")} -> Muito Curta (evitável) | AF79: =IFERROR(VLOOKUP(AE79,Constantes!$A$1:$E$5,MATCH(AD79,Constantes!$A$1:$E$1,0),0),"") -> 0.27257679 | AG79: =AF79*S79 -> 76.067857
A80: =COUNTIF($B$2:B80,B80) -> 1 | B80: 18942342 | C80: 000435/23 | D80: ***.000.000-** | E80: NEIL DAVID WITTEN | G80: -1 | H80: Sem informação | I80: 45149 | J80: 45158 | K80: Participação no 6º Festival Internacional de Música de Câmara PPGM-UFPB, em João Pessoa/PB, de 11 a 19/08/2023. | L80: 45149 | M80: 45158 | N80: Porto Alegre | O80: João Pessoa | P80: =VLOOKUP(N80,[1]ID_Cidades!$A$1:$E$5900,2,FALSE) -> 295786 | Q80: =VLOOKUP(O80,[1]ID_Cidades!$A$1:$E$5900,2,FALSE) -> 295765 | R80: =P80*Q80 -> 87483146290 | S80: =VLOOKUP(R80,'[1]GCD base'!$A$1:$M$200,7,FALSE) -> 3054.7955 | T80: Aéreo | U80: Sim | V80: Realizada | W80: NÃO | X80: Sem informação | Y80: 0 | Z80: 0 | AA80: 1217.09 | AB80: 0 | AC80: 45093 | AD80: Econômica | AE80: {=_xlfn.IFS(S80<=Constantes!$G$2,"Muito Curta (evitável)",S80<=Constantes!$H$2,"Curta Distância",S80>Constantes!$H$2,"Longa Distância")} -> Curta Distância | AF80: =IFERROR(VLOOKUP(AE80,Constantes!$A$1:$E$5,MATCH(AD80,Constantes!$A$1:$E$1,0),0),"") -> 0.18286935 | AG80: =AF80*S80 -> 558.62849
A81: =COUNTIF($B$2:B81,B81) -> 2 | B81: 18942342 | C81: 000435/23 | D81: ***.000.000-** | E81: NEIL DAVID WITTEN | G81: -1 | H81: Sem informação | I81: 45149 | J81: 45158 | K81: Participação no 6º Festival Internacional de Música de Câmara PPGM-UFPB, em João Pessoa/PB, de 11 a 19/08/2023. | L81: 45158 | M81: 45158 | N81: João Pessoa | O81: Porto Alegre | P81: =VLOOKUP(N81,[1]ID_Cidades!$A$1:$E$5900,2,FALSE) -> 295765 | Q81: =VLOOKUP(O81,[1]ID_Cidades!$A$1:$E$5900,2,FALSE) -> 295786 | R81: =P81*Q81 -> 87483146290 | S81: =VLOOKUP(R81,'[1]GCD base'!$A$1:$M$200,7,FALSE) -> 3054.7955 | T81: Aéreo | U81: Não | V81: Realizada | W81: NÃO | X81: Sem informação | Y81: 0 | Z81: 0 | AA81: 858.83 | AB81: 0 | AC81: 45093 | AD81: Econômica | AE81: {=_xlfn.IFS(S81<=Constantes!$G$2,"Muito Curta (evitável)",S81<=Constantes!$H$2,"Curta Distância",S81>Constantes!$H$2,"Longa Distância")} -> Curta Distância | AF81: =IFERROR(VLOOKUP(AE81,Constantes!$A$1:$E$5,MATCH(AD81,Constantes!$A$1:$E$1,0),0),"") -> 0.18286935 | AG81: =AF81*S81 -> 558.62849
A82: =COUNTIF($B$2:B82,B82) -> 1 | B82: 19070440 | C82: 000592/23 | D82: ***.508.956-** | E82: VITOR SOMMAVILLA DE SOUZA BARROS | F82: PROFESSOR DO MAGISTERIO SUPERIOR | G82: -1 | H82: Sem informação | I82: 45151 | J82: 45156 | K82: Participar como palestrante do evento 13th Principia International Symposium, em Florianópolis/SC. | L82: 45156 | M82: 45156 | N82: Florianópolis | O82: João Pessoa | P82: =VLOOKUP(N82,[1]ID_Cidades!$A$1:$E$5900,2,FALSE) -> 295781 | Q82: =VLOOKUP(O82,[1]ID_Cidades!$A$1:$E$5900,2,FALSE) -> 295765 | R82: =P82*Q82 -> 87481667465 | S82: =VLOOKUP(R82,'[1]GCD base'!$A$1:$M$200,7,FALSE) -> 2695.5823 | T82: Aéreo | U82: Não | V82: Realizada | W82: NÃO | X82: Sem informação | Y82: 1821.06 | Z82: 0 | AA82: 843.99 | AB82: 0 | AC82: 45120 | AD82: Econômica | AE82: {=_xlfn.IFS(S82<=Constantes!$G$2,"Muito Curta (evitável)",S82<=Constantes!$H$2,"Curta Distância",S82>Constantes!$H$2,"Longa Distância")} -> Curta Distância | AF82: =IFERROR(VLOOKUP(AE82,Constantes!$A$1:$E$5,MATCH(AD82,Constantes!$A$1:$E$1,0),0),"") -> 0.18286935 | AG82: =AF82*S82 -> 492.9394
A83: =COUNTIF($B$2:B83,B83) -> 2 | B83: 19070440 | C83: 000592/23 | D83: ***.508.956-** | E83: VITOR SOMMAVILLA DE SOUZA BARROS | F83: PROFESSOR DO MAGISTERIO SUPERIOR | G83: -1 | H83: Sem informação | I83: 45151 | J83: 45156 | K83: Participar como palestrante do evento 13th Principia International Symposium, em Florianópolis/SC. | L83: 45151 | M83: 45156 | N83: João Pessoa | O83: Florianópolis | P83: =VLOOKUP(N83,[1]ID_Cidades!$A$1:$E$5900,2,FALSE) -> 295765 | Q83: =VLOOKUP(O83,[1]ID_Cidades!$A$1:$E$5900,2,FALSE) -> 295781 | R83: =P83*Q83 -> 87481667465 | S83: =VLOOKUP(R83,'[1]GCD base'!$A$1:$M$200,7,FALSE) -> 2695.5823 | T83: Aéreo | U83: Sim | V83: Realizada | W83: NÃO | X83: Sem informação | Y83: 0 | Z83: 0 | AA83: 845.47 | AB83: 0 | AC83: 45120 | AD83: Econômica | AE83: {=_xlfn.IFS(S83<=Constantes!$G$2,"Muito Curta (evitável)",S83<=Constantes!$H$2,"Curta Distância",S83>Constantes!$H$2,"Longa Distância")} -> Curta Distância | AF83: =IFERROR(VLOOKUP(AE83,Constantes!$A$1:$E$5,MATCH(AD83,Constantes!$A$1:$E$1,0),0),"") -> 0.18286935 | AG83: =AF83*S83 -> 492.9394
A84: =COUNTIF($B$2:B84,B84) -> 1 | B84: 19164813 | C84: 000779/23 | D84: ***.676.784-** | E84: LETICIA MELO MOREIRA | F84: PROFESSOR ENS BASICO TECN TECNOLOGICO | G84: -1 | H84: Sem informação | I84: 45152 | J84: 45158 | K84: Participação em banca do concurso público Edital nº 30 de 03 de Maio de 2023 do Centro Profissional e Tecnológico da Universidade Federal da Paraíba. | L84: 45158 | M84: 45158 | N84: Recife | O84: Maceió | P84: =VLOOKUP(N84,[1]ID_Cidades!$A$1:$E$5900,2,FALSE) -> 295766 | Q84: =VLOOKUP(O84,[1]ID_Cidades!$A$1:$E$5900,2,FALSE) -> 295768 | R84: =P84*Q84 -> 87478118288 | S84: =VLOOKUP(R84,'[1]GCD base'!$A$1:$M$200,7,FALSE) -> 180.97985 | T84: Aéreo | U84: Não | V84: Realizada | W84: SIM | X84: Conforme justificativa anexa. | Y84: 2162.08 | Z84: 0 | AA84: 1241.79 | AB84: 0 | AC84: 45149 | AD84: Econômica | AE84: {=_xlfn.IFS(S84<=Constantes!$G$2,"Muito Curta (evitável)",S84<=Constantes!$H$2,"Curta Distância",S84>Constantes!$H$2,"Longa Distância")} -> Muito Curta (evitável) | AF84: =IFERROR(VLOOKUP(AE84,Constantes!$A$1:$E$5,MATCH(AD84,Constantes!$A$1:$E$1,0),0),"") -> 0.27257679 | AG84: =AF84*S84 -> 49.330905
A85: =COUNTIF($B$2:B85,B85) -> 2 | B85: 19164813 | C85: 000779/23 | D85: ***.676.784-** | E85: LETICIA MELO MOREIRA | F85: PROFESSOR ENS BASICO TECN TECNOLOGICO | G85: -1 | H85: Sem informação | I85: 45152 | J85: 45158 | K85: Participação em banca do concurso público Edital nº 30 de 03 de Maio de 2023 do Centro Profissional e Tecnológico da Universidade Federal da Paraíba. | L85: 45152 | M85: 45152 | N85: Maceió | O85: Recife | P85: =VLOOKUP(N85,[1]ID_Cidades!$A$1:$E$5900,2,FALSE) -> 295768 | Q85: =VLOOKUP(O85,[1]ID_Cidades!$A$1:$E$5900,2,FALSE) -> 295766 | R85: =P85*Q85 -> 87478118288 | S85: =VLOOKUP(R85,'[1]GCD base'!$A$1:$M$200,7,FALSE) -> 180.97985 | T85: Aéreo | U85: Não | V85: Realizada | W85: SIM | X85: Conforme justificativa anexa. | Y85: 0 | Z85: 0 | AA85: 804.14 | AB85: 0 | AC85: 45149 | AD85: Econômica | AE85: {=_xlfn.IFS(S85<=Constantes!$G$2,"Muito Curta (evitável)",S85<=Constantes!$H$2,"Curta Distância",S85>Constantes!$H$2,"Longa Distância")} -> Muito Curta (evitável) | AF85: =IFERROR(VLOOKUP(AE85,Constantes!$A$1:$E$5,MATCH(AD85,Constantes!$A$1:$E$1,0),0),"") -> 0.27257679 | AG85: =AF85*S85 -> 49.330905
A86: =COUNTIF($B$2:B86,B86) -> 1 | B86: 19165091 | C86: 000778/23 | D86: ***.119.154-** | E86: MARCELA DE OLIVEIRA FEITOSA | F86: PROFESSOR DO MAGISTERIO SUPERIOR | G86: -1 | H86: Sem informação | I86: 45152 | J86: 45159 | K86: Participação em banca do concurso público do Edital nº 30 de 03 de Maio de 2023 do Centro Profissional e Tecnológico da Universidade Federal da Paraíba. | L86: 45158 | M86: 45159 | N86: Recife | O86: Imperatriz | P86: =VLOOKUP(N86,[1]ID_Cidades!$A$1:$E$5900,2,FALSE) -> 295766 | Q86: =VLOOKUP(O86,[1]ID_Cidades!$A$1:$E$5900,2,FALSE) -> 301970 | R86: =P86*Q86 -> 89312459020 | S86: =VLOOKUP(R86,'[1]GCD base'!$A$1:$M$200,7,FALSE) -> 1413.4655 | T86: Aéreo | U86: Não | V86: Realizada | W86: SIM | X86: Conforme justificativa anexa. | Y86: 2454.23 | Z86: 0 | AA86: 2958.49 | AB86: 0 | AC86: 45149 | AD86: Econômica | AE86: {=_xlfn.IFS(S86<=Constantes!$G$2,"Muito Curta (evitável)",S86<=Constantes!$H$2,"Curta Distância",S86>Constantes!$H$2,"Longa Distância")} -> Curta Distância | AF86: =IFERROR(VLOOKUP(AE86,Constantes!$A$1:$E$5,MATCH(AD86,Constantes!$A$1:$E$1,0),0),"") -> 0.18286935 | AG86: =AF86*S86 -> 258.47953
A87: =COUNTIF($B$2:B87,B87) -> 2 | B87: 19165091 | C87: 000778/23 | D87: ***.119.154-** | E87: MARCELA DE OLIVEIRA FEITOSA | F87: PROFESSOR DO MAGISTERIO SUPERIOR | G87: -1 | H87: Sem informação | I87: 45152 | J87: 45159 | K87: Participação em banca do concurso público do Edital nº 30 de 03 de Maio de 2023 do Centro Profissional e Tecnológico da Universidade Federal da Paraíba. | L87: 45152 | M87: 45152 | N87: Imperatriz | O87: Recife | P87: =VLOOKUP(N87,[1]ID_Cidades!$A$1:$E$5900,2,FALSE) -> 301970 | Q87: =VLOOKUP(O87,[1]ID_Cidades!$A$1:$E$5900,2,FALSE) -> 295766 | R87: =P87*Q87 -> 89312459020 | S87: =VLOOKUP(R87,'[1]GCD base'!$A$1:$M$200,7,FALSE) -> 1413.4655 | T87: Aéreo | U87: Não | V87: Realizada | W87: SIM | X87: Conforme justificativa anexa. | Y87: 0 | Z87: 0 | AA87: 1764.54 | AB87: 0 | AC87: 45149 | AD87: Econômica | AE87: {=_xlfn.IFS(S87<=Constantes!$G$2,"Muito Curta (evitável)",S87<=Constantes!$H$2,"Curta Distância",S87>Constantes!$H$2,"Longa Distância")} -> Curta Distância | AF87: =IFERROR(VLOOKUP(AE87,Constantes!$A$1:$E$5,MATCH(AD87,Constantes!$A$1:$E$1,0),0),"") -> 0.18286935 | AG87: =AF87*S87 -> 258.47953
A88: =COUNTIF($B$2:B88,B88) -> 1 | B88: 19165330 | C88: 000780/23 | D88: ***.396.743-** | E88: FRANCISCO RICARDO MIRANDA PINTO | F88: PROFESSOR DO MAGISTERIO SUPERIOR | G88: FG-0001 | H88: FG-0001 | I88: 45152 | J88: 45158 | K88: Compor Banca de Concurso EDITAL Nº 30, 03 DE MAIO DE 2023 CONCURSO PÚBLICO DE PROVAS E TÍTULOS PARA PROFESSOR DO ENSINO BÁSICO, TÉCNICO E TECNOLÓGICO - EBTCPT-ETS-UFPB. | L88: 45152 | M88: 45158 | N88: Brasília | O88: João Pessoa | P88: =VLOOKUP(N88,[1]ID_Cidades!$A$1:$E$5900,2,FALSE) -> 295763 | Q88: =VLOOKUP(O88,[1]ID_Cidades!$A$1:$E$5900,2,FALSE) -> 295765 | R88: =P88*Q88 -> 87476343695 | S88: =VLOOKUP(R88,'[1]GCD base'!$A$1:$M$200,7,FALSE) -> 1713.42 | T88: Aéreo | U88: Sim | V88: Realizada | W88: SIM | X88: Conforme justificativa anexa. | Y88: 2162.08 | Z88: 0 | AA88: 2775.27 | AB88: 0 | AC88: 45149 | AD88: Econômica | AE88: {=_xlfn.IFS(S88<=Constantes!$G$2,"Muito Curta (evitável)",S88<=Constantes!$H$2,"Curta Distância",S88>Constantes!$H$2,"Longa Distância")} -> Curta Distância | AF88: =IFERROR(VLOOKUP(AE88,Constantes!$A$1:$E$5,MATCH(AD88,Constantes!$A$1:$E$1,0),0),"") -> 0.18286935 | AG88: =AF88*S88 -> 313.33201
A89: =COUNTIF($B$2:B89,B89) -> 2 | B89: 19165330 | C89: 000780/23 | D89: ***.396.743-** | E89: FRANCISCO RICARDO MIRANDA PINTO | F89: PROFESSOR DO MAGISTERIO SUPERIOR | G89: FG-0001 | H89: FG-0001 | I89: 45152 | J89: 45158 | K89: Compor Banca de Concurso EDITAL Nº 30, 03 DE MAIO DE 2023 CONCURSO PÚBLICO DE PROVAS E TÍTULOS PARA PROFESSOR DO ENSINO BÁSICO, TÉCNICO E TECNOLÓGICO - EBTCPT-ETS-UFPB. | L89: 45158 | M89: 45158 | N89: João Pessoa | O89: Brasília | P89: =VLOOKUP(N89,[1]ID_Cidades!$A$1:$E$5900,2,FALSE) -> 295765 | Q89: =VLOOKUP(O89,[1]ID_Cidades!$A$1:$E$5900,2,FALSE) -> 295763 | R89: =P89*Q89 -> 87476343695 | S89: =VLOOKUP(R89,'[1]GCD base'!$A$1:$M$200,7,FALSE) -> 1713.42 | T89: Aéreo | U89: Não | V89: Realizada | W89: SIM | X89: Conforme justificativa anexa. | Y89: 0 | Z89: 0 | AA89: 2216.99 | AB89: 0 | AC89: 45149 | AD89: Econômica | AE89: {=_xlfn.IFS(S89<=Constantes!$G$2,"Muito Curta (evitável)",S89<=Constantes!$H$2,"Curta Distância",S89>Constantes!$H$2,"Longa Distância")} -> Curta Distância | AF89: =IFERROR(VLOOKUP(AE89,Constantes!$A$1:$E$5,MATCH(AD89,Constantes!$A$1:$E$1,0),0),"") -> 0.18286935 | AG89: =AF89*S89 -> 313.33201
A90: =COUNTIF($B$2:B90,B90) -> 1 | B90: 19145555 | C90: 000730/23 | D90: ***.474.766-** | E90: EDNA GUSMAO DE GOES BRENNAND | F90: PROFESSOR DO MAGISTERIO SUPERIOR | G90: -1 | H90: Sem informação | I90: 45153 | J90: 45157 | K90: Trata-se de uma viagem que visa formalizar um convénio altamente relevante para o PPGE da UFPB, por se tratar de abertura de Turma Fora da Sede, na cidade de Vitória da Conquista/BA. Em parceria com a Secretaria Municipal de Educação, o Programa de Pós-Graduação em Educação busca através desta atividade aprofundar o processo de regionalização de suas atividades de ensino, pesquisa e extensão. | L90: 45153 | M90: 45157 | N90: João Pessoa | O90: Vitória da Conquista | P90: =VLOOKUP(N90,[1]ID_Cidades!$A$1:$E$5900,2,FALSE) -> 295765 | Q90: =VLOOKUP(O90,[1]ID_Cidades!$A$1:$E$5900,2,FALSE) -> 301606 | R90: =P90*Q90 -> 89204498590 | S90: =VLOOKUP(R90,'[1]GCD base'!$A$1:$M$200,7,FALSE) -> 1081.5366 | T90: Aéreo | U90: Sim | V90: Realizada | W90: SIM | X90: Não há solicitação de urgência. | Y90: 1329.41 | Z90: 0 | AA90: 1991.29 | AB90: 0 | AC90: 45147 | AD90: Econômica | AE90: {=_xlfn.IFS(S90<=Constantes!$G$2,"Muito Curta (evitável)",S90<=Constantes!$H$2,"Curta Distância",S90>Constantes!$H$2,"Longa Distância")} -> Curta Distância | AF90: =IFERROR(VLOOKUP(AE90,Constantes!$A$1:$E$5,MATCH(AD90,Constantes!$A$1:$E$1,0),0),"") -> 0.18286935 | AG90: =AF90*S90 -> 197.77991
A91: =COUNTIF($B$2:B91,B91) -> 2 | B91: 19145555 | C91: 000730/23 | D91: ***.474.766-** | E91: EDNA GUSMAO DE GOES BRENNAND | F91: PROFESSOR DO MAGISTERIO SUPERIOR | G91: -1 | H91: Sem informação | I91: 45153 | J91: 45157 | K91: Trata-se de uma viagem que visa formalizar um convénio altamente relevante para o PPGE da UFPB, por se tratar de abertura de Turma Fora da Sede, na cidade de Vitória da Conquista/BA. Em parceria com a Secretaria Municipal de Educação, o Programa de Pós-Graduação em Educação busca através desta atividade aprofundar o processo de regionalização de suas atividades de ensino, pesquisa e extensão. | L91: 45157 | M91: 45157 | N91: Vitória da Conquista | O91: João Pessoa | P91: =VLOOKUP(N91,[1]ID_Cidades!$A$1:$E$5900,2,FALSE) -> 301606 | Q91: =VLOOKUP(O91,[1]ID_Cidades!$A$1:$E$5900,2,FALSE) -> 295765 | R91: =P91*Q91 -> 89204498590 | S91: =VLOOKUP(R91,'[1]GCD base'!$A$1:$M$200,7,FALSE) -> 1081.5366 | T91: Aéreo | U91: Não | V91: Realizada | W91: SIM | X91: Não há solicitação de urgência. | Y91: 0 | Z91: 0 | AA91: 1777.81 | AB91: 0 | AC91: 45147 | AD91: Econômica | AE91: {=_xlfn.IFS(S91<=Constantes!$G$2,"Muito Curta (evitável)",S91<=Constantes!$H$2,"Curta Distância",S91>Constantes!$H$2,"Longa Distância")} -> Curta Distância | AF91: =IFERROR(VLOOKUP(AE91,Constantes!$A$1:$E$5,MATCH(AD91,Constantes!$A$1:$E$1,0),0),"") -> 0.18286935 | AG91: =AF91*S91 -> 197.77991
A92: =COUNTIF($B$2:B92,B92) -> 1 | B92: 19146238 | C92: 000731/23 | D92: ***.080.908-** | E92: JORGE FERNANDO HERMIDA AVEIRO | F92: PROFESSOR DO MAGISTERIO SUPERIOR | G92: FUC-0001 | H92: FUC-0001 | I92: 45153 | J92: 45157 | K92: Trata-se de uma viagem que visa formalizar um convénio altamente relevante para o PPGE da UFPB, por se tratar de abertura de Turma Fora da Sede, na cidade de Vitória da Conquista/BA. Em parceria com a Secretaria Municipal de Educação, o Programa de Pós-Graduação em Educação busca através desta atividade aprofundar o processo de regionalização de suas atividades de ensino, pesquisa e extensão. | L92: 45157 | M92: 45157 | N92: Vitória da Conquista | O92: João Pessoa | P92: =VLOOKUP(N92,[1]ID_Cidades!$A$1:$E$5900,2,FALSE) -> 301606 | Q92: =VLOOKUP(O92,[1]ID_Cidades!$A$1:$E$5900,2,FALSE) -> 295765 | R92: =P92*Q92 -> 89204498590 | S92: =VLOOKUP(R92,'[1]GCD base'!$A$1:$M$200,7,FALSE) -> 1081.5366 | T92: Aéreo | U92: Não | V92: Realizada | W92: SIM | X92: Não há urgência. | Y92: 1329.41 | Z92: 0 | AA92: 1777.81 | AB92: 0 | AC92: 45147 | AD92: Econômica | AE92: {=_xlfn.IFS(S92<=Constantes!$G$2,"Muito Curta (evitável)",S92<=Constantes!$H$2,"Curta Distância",S92>Constantes!$H$2,"Longa Distância")} -> Curta Distância | AF92: =IFERROR(VLOOKUP(AE92,Constantes!$A$1:$E$5,MATCH(AD92,Constantes!$A$1:$E$1,0),0),"") -> 0.18286935 | AG92: =AF92*S92 -> 197.77991
A93: =COUNTIF($B$2:B93,B93) -> 2 | B93: 19146238 | C93: 000731/23 | D93: ***.080.908-** | E93: JORGE FERNANDO HERMIDA AVEIRO | F93: PROFESSOR DO MAGISTERIO SUPERIOR | G93: FUC-0001 | H93: FUC-0001 | I93: 45153 | J93: 45157 | K93: Trata-se de uma viagem que visa formalizar um convénio altamente relevante para o PPGE da UFPB, por se tratar de abertura de Turma Fora da Sede, na cidade de Vitória da Conquista/BA. Em parceria com a Secretaria Municipal de Educação, o Programa de Pós-Graduação em Educação busca através desta atividade aprofundar o processo de regionalização de suas atividades de ensino, pesquisa e extensão. | L93: 45153 | M93: 45157 | N93: João Pessoa | O93: Vitória da Conquista | P93: =VLOOKUP(N93,[1]ID_Cidades!$A$1:$E$5900,2,FALSE) -> 295765 | Q93: =VLOOKUP(O93,[1]ID_Cidades!$A$1:$E$5900,2,FALSE) -> 301606 | R93: =P93*Q93 -> 89204498590 | S93: =VLOOKUP(R93,'[1]GCD base'!$A$1:$M$200,7,FALSE) -> 1081.5366 | T93: Aéreo | U93: Sim | V93: Realizada | W93: SIM | X93: Não há urgência. | Y93: 0 | Z93: 0 | AA93: 1991.29 | AB93: 0 | AC93: 45147 | AD93: Econômica | AE93: {=_xlfn.IFS(S93<=Constantes!$G$2,"Muito Curta (evitável)",S93<=Constantes!$H$2,"Curta Distância",S93>Constantes!$H$2,"Longa Distância")} -> Curta Distância | AF93: =IFERROR(VLOOKUP(AE93,Constantes!$A$1:$E$5,MATCH(AD93,Constantes!$A$1:$E$1,0),0),"") -> 0.18286935 | AG93: =AF93*S93 -> 197.77991
... A113: =COUNTIF($B$2:B113,B113) -> 2 | B113: 18997079 | C113: 000432/23 | D113: ***.464.914-** | E113: PRISCILA OLIVEIRA COSTA SILVA | F113: PROFESSOR DO MAGISTERIO SUPERIOR | G113: -1 | H113: Sem informação | I113: 45161 | J113: 45165 | K113: O PROPOSTO IRÁ PARTICIPAR DO 22° CONGRESSO DA FUNDAÇÃO OTORRINOLARINGOLOGIA, QUE OCORRERÁ NO CENTRO DE CONVENÇÕES FREI CANECA (SÃO PAULO/SP), NOS DIAS 24 A 26 DE AGOSTO DE 2023. | L113: 45161 | M113: 45164 | N113: João Pessoa | O113: São Paulo | P113: =VLOOKUP(N113,[1]ID_Cidades!$A$1:$E$5900,2,FALSE) -> 295765 | Q113: =VLOOKUP(O113,[1]ID_Cidades!$A$1:$E$5900,2,FALSE) -> 295779 | R113: =P113*Q113 -> 87481075935 | S113: =VLOOKUP(R113,'[1]GCD base'!$A$1:$M$200,7,FALSE) -> 2189.9742 | T113: Aéreo | U113: Sim | V113: Realizada | W113: NÃO | X113: Sem informação | Y113: 0 | Z113: 0 | AA113: 677.53 | AB113: 0 | AC113: 45091 | AD113: Econômica | AE113: {=_xlfn.IFS(S113<=Constantes!$G$2,"Muito Curta (evitável)",S113<=Constantes!$H$2,"Curta Distância",S113>Constantes!$H$2,"Longa Distância")} -> Curta Distância | AF113: =IFERROR(VLOOKUP(AE113,Constantes!$A$1:$E$5,MATCH(AD113,Constantes!$A$1:$E$1,0),0),"") -> 0.18286935 | AG113: =AF113*S113 -> 400.47918
A114: =COUNTIF($B$2:B114,B114) -> 1 | B114: 19203431 | C114: 000866/23 | D114: ***.847.738-** | E114: CATERINE SOFFIATI CABRAL | G114: -1 | H114: Sem informação | I114: 45164 | J114: 45170 | K114: Viagem para o 10° Encontro das Redes Rurais, que será realizado em São Carlos, no interior de São Paulo. | L114: 45164 | M114: 45170 | N114: João Pessoa | O114: São Paulo | P114: =VLOOKUP(N114,[1]ID_Cidades!$A$1:$E$5900,2,FALSE) -> 295765 | Q114: =VLOOKUP(O114,[1]ID_Cidades!$A$1:$E$5900,2,FALSE) -> 295779 | R114: =P114*Q114 -> 87481075935 | S114: =VLOOKUP(R114,'[1]GCD base'!$A$1:$M$200,7,FALSE) -> 2189.9742 | T114: Aéreo | U114: Sim | V114: Realizada | W114: SIM | X114: Gestão dos recursos do PROAP no PPGS. Não foi possível encaminhar o pedido anteriormente. Tambpem foi necessário corrigir a PCDP, cancelando a anterior. | Y114: 0 | Z114: 0 | AA114: 3734.24 | AB114: 0 | AC114: 45159 | AD114: Econômica | AE114: {=_xlfn.IFS(S114<=Constantes!$G$2,"Muito Curta (evitável)",S114<=Constantes!$H$2,"Curta Distância",S114>Constantes!$H$2,"Longa Distância")} -> Curta Distância | AF114: =IFERROR(VLOOKUP(AE114,Constantes!$A$1:$E$5,MATCH(AD114,Constantes!$A$1:$E$1,0),0),"") -> 0.18286935 | AG114: =AF114*S114 -> 400.47918
A115: =COUNTIF($B$2:B115,B115) -> 2 | B115: 19203431 | C115: 000866/23 | D115: ***.847.738-** | E115: CATERINE SOFFIATI CABRAL | G115: -1 | H115: Sem informação | I115: 45164 | J115: 45170 | K115: Viagem para o 10° Encontro das Redes Rurais, que será realizado em São Carlos, no interior de São Paulo. | L115: 45170 | M115: 45170 | N115: São Paulo | O115: João Pessoa | P115: =VLOOKUP(N115,[1]ID_Cidades!$A$1:$E$5900,2,FALSE) -> 295779 | Q115: =VLOOKUP(O115,[1]ID_Cidades!$A$1:$E$5900,2,FALSE) -> 295765 | R115: =P115*Q115 -> 87481075935 | S115: =VLOOKUP(R115,'[1]GCD base'!$A$1:$M$200,7,FALSE) -> 2189.9742 | T115: Aéreo | U115: Não | V115: Realizada | W115: SIM | X115: Gestão dos recursos do PROAP no PPGS. Não foi possível encaminhar o pedido anteriormente. Tambpem foi necessário corrigir a PCDP, cancelando a anterior. | Y115: 0 | Z115: 0 | AA115: 0 | AB115: 0 | AC115: 0 | AD115: Econômica | AE115: {=_xlfn.IFS(S115<=Constantes!$G$2,"Muito Curta (evitável)",S115<=Constantes!$H$2,"Curta Distância",S115>Constantes!$H$2,"Longa Distância")} -> Curta Distância | AF115: =IFERROR(VLOOKUP(AE115,Constantes!$A$1:$E$5,MATCH(AD115,Constantes!$A$1:$E$1,0),0),"") -> 0.18286935 | AG115: =AF115*S115 -> 400.47918
A116: =COUNTIF($B$2:B116,B116) -> 1 | B116: 19165342 | C116: 000830/23 | D116: ***.460.996-** | E116: MATEUS DE SOUSA VAN STRALEN | F116: PROFESSOR DO MAGISTERIO SUPERIOR | G116: FG-0001 | H116: FG-0001 | I116: 45165 | J116: 45170 | K116: Participar em Banca Examinadora referente ao Concurso Público de Provas e Títulos para provimento de cargos de Professor do Magistério Superior para o Departamento de Arquitetura e Urbanismo - DAU/CT, regido pelo EDITAL Nº 61 de 06 de julho de 2023, publicado no DOU em 07/07/2023 - Edição: 128 | Seção: 3, Página: 77, regime de trabalho Dedicação Exclusiva, na Área de Projeto e Representação Gráfica. | L116: 45165 | M116: 45170 | N116: Belo Horizonte | O116: João Pessoa | P116: =VLOOKUP(N116,[1]ID_Cidades!$A$1:$E$5900,2,FALSE) -> 295777 | Q116: =VLOOKUP(O116,[1]ID_Cidades!$A$1:$E$5900,2,FALSE) -> 295765 | R116: =P116*Q116 -> 87480484405 | S116: =VLOOKUP(R116,'[1]GCD base'!$A$1:$M$200,7,FALSE) -> 1714.8365 | T116: Aéreo | U116: Sim | V116: Realizada | W116: SIM | X116: Devido a necessidade de aguardar o período de inscrição determinado no cronograma do concurso para que a Banca Examinadora seja confirmada sem que não tenha membros com impedimentos de acordo com a Resolução 74/2013 - CONSEPE. | Y116: 1821.06 | Z116: 0 | AA116: 1529.6 | AB116: 0 | AC116: 45155 | AD116: Econômica | AE116: {=_xlfn.IFS(S116<=Constantes!$G$2,"Muito Curta (evitável)",S116<=Constantes!$H$2,"Curta Distância",S116>Constantes!$H$2,"Longa Distância")} -> Curta Distância | AF116: =IFERROR(VLOOKUP(AE116,Constantes!$A$1:$E$5,MATCH(AD116,Constantes!$A$1:$E$1,0),0),"") -> 0.18286935 | AG116: =AF116*S116 -> 313.59105
A117: =COUNTIF($B$2:B117,B117) -> 2 | B117: 19165342 | C117: 000830/23 | D117: ***.460.996-** | E117: MATEUS DE SOUSA VAN STRALEN | F117: PROFESSOR DO MAGISTERIO SUPERIOR | G117: FG-0001 | H117: FG-0001 | I117: 45165 | J117: 45170 | K117: Participar em Banca Examinadora referente ao Concurso Público de Provas e Títulos para provimento de cargos de Professor do Magistério Superior para o Departamento de Arquitetura e Urbanismo - DAU/CT, regido pelo EDITAL Nº 61 de 06 de julho de 2023, publicado no DOU em 07/07/2023 - Edição: 128 | Seção: 3, Página: 77, regime de trabalho Dedicação Exclusiva, na Área de Projeto e Representação Gráfica. | L117: 45170 | M117: 45170 | N117: João Pessoa | O117: Belo Horizonte | P117: =VLOOKUP(N117,[1]ID_Cidades!$A$1:$E$5900,2,FALSE) -> 295765 | Q117: =VLOOKUP(O117,[1]ID_Cidades!$A$1:$E$5900,2,FALSE) -> 295777 | R117: =P117*Q117 -> 87480484405 | S117: =VLOOKUP(R117,'[1]GCD base'!$A$1:$M$200,7,FALSE) -> 1714.8365 | T117: Aéreo | U117: Não | V117: Realizada | W117: SIM | X117: Devido a necessidade de aguardar o período de inscrição determinado no cronograma do concurso para que a Banca Examinadora seja confirmada sem que não tenha membros com impedimentos de acordo com a Resolução 74/2013 - CONSEPE. | Y117: 0 | Z117: 0 | AA117: 1437.19 | AB117: 0 | AC117: 45155 | AD117: Econômica | AE117: {=_xlfn.IFS(S117<=Constantes!$G$2,"Muito Curta (evitável)",S117<=Constantes!$H$2,"Curta Distância",S117>Constantes!$H$2,"Longa Distância")} -> Curta Distância | AF117: =IFERROR(VLOOKUP(AE117,Constantes!$A$1:$E$5,MATCH(AD117,Constantes!$A$1:$E$1,0),0),"") -> 0.18286935 | AG117: =AF117*S117 -> 313.59105
A118: =COUNTIF($B$2:B118,B118) -> 1 | B118: 19180265 | C118: 000820/23 | D118: ***.734.353-** | E118: FELIX ALVES DA SILVA JUNIOR | F118: PROFESSOR DO MAGISTERIO SUPERIOR | G118: -1 | H118: Sem informação | I118: 45165 | J118: 45170 | K118: Participar da banca examinadora de concurso público, regido pelo EDITAL No 61, DE 6 DE JULHO DE 2023 CONCURSO PÚBLICO DE PROVAS E TÍTULOS - PARA PROFESSOR DO MAGISTÉRIO SUPERIOR, do Departamento de Arquitetura e Urbanismo - DAU/CT/UFPB, publicado no DOU em 07/07/2023 - Edição: 128 | Seção: 3, Página: 77, regime de trabalho Dedicação Exclusiva, na Área de Projeto e Representação Gráfica. | L118: 45170 | M118: 45170 | N118: João Pessoa | O118: Brasília | P118: =VLOOKUP(N118,[1]ID_Cidades!$A$1:$E$5900,2,FALSE) -> 295765 | Q118: =VLOOKUP(O118,[1]ID_Cidades!$A$1:$E$5900,2,FALSE) -> 295763 | R118: =P118*Q118 -> 87476343695 | S118: =VLOOKUP(R118,'[1]GCD base'!$A$1:$M$200,7,FALSE) -> 1713.42 | T118: Aéreo | U118: Não | V118: Realizada | W118: SIM | X118: Devido a necessidade de aguardar o período de inscrição determinado no cronograma do concurso para que a Banca Examinadora seja confirmada sem que não tenha membros com impedimentos de acordo com a Resolução 74/2013 - CONSEPE. | Y118: 1821.06 | Z118: 0 | AA118: 1572.49 | AB118: 0 | AC118: 45155 | AD118: Econômica | AE118: {=_xlfn.IFS(S118<=Constantes!$G$2,"Muito Curta (evitável)",S118<=Constantes!$H$2,"Curta Distância",S118>Constantes!$H$2,"Longa Distância")} -> Curta Distância | AF118: =IFERROR(VLOOKUP(AE118,Constantes!$A$1:$E$5,MATCH(AD118,Constantes!$A$1:$E$1,0),0),"") -> 0.18286935 | AG118: =AF118*S118 -> 313.33201
A119: =COUNTIF($B$2:B119,B119) -> 2 | B119: 19180265 | C119: 000820/23 | D119: ***.734.353-** | E119: FELIX ALVES DA SILVA JUNIOR | F119: PROFESSOR DO MAGISTERIO SUPERIOR | G119: -1 | H119: Sem informação | I119: 45165 | J119: 45170 | K119: Participar da banca examinadora de concurso público, regido pelo EDITAL No 61, DE 6 DE JULHO DE 2023 CONCURSO PÚBLICO DE PROVAS E TÍTULOS - PARA PROFESSOR DO MAGISTÉRIO SUPERIOR, do Departamento de Arquitetura e Urbanismo - DAU/CT/UFPB, publicado no DOU em 07/07/2023 - Edição: 128 | Seção: 3, Página: 77, regime de trabalho Dedicação Exclusiva, na Área de Projeto e Representação Gráfica. | L119: 45165 | M119: 45170 | N119: Brasília | O119: João Pessoa | P119: =VLOOKUP(N119,[1]ID_Cidades!$A$1:$E$5900,2,FALSE) -> 295763 | Q119: =VLOOKUP(O119,[1]ID_Cidades!$A$1:$E$5900,2,FALSE) -> 295765 | R119: =P119*Q119 -> 87476343695 | S119: =VLOOKUP(R119,'[1]GCD base'!$A$1:$M$200,7,FALSE) -> 1713.42 | T119: Aéreo | U119: Sim | V119: Realizada | W119: SIM | X119: Devido a necessidade de aguardar o período de inscrição determinado no cronograma do concurso para que a Banca Examinadora seja confirmada sem que não tenha membros com impedimentos de acordo com a Resolução 74/2013 - CONSEPE. | Y119: 0 | Z119: 0 | AA119: 2000.81 | AB119: 0 | AC119: 45155 | AD119: Econômica | AE119: {=_xlfn.IFS(S119<=Constantes!$G$2,"Muito Curta (evitável)",S119<=Constantes!$H$2,"Curta Distância",S119>Constantes!$H$2,"Longa Distância")} -> Curta Distância | AF119: =IFERROR(VLOOKUP(AE119,Constantes!$A$1:$E$5,MATCH(AD119,Constantes!$A$1:$E$1,0),0),"") -> 0.18286935 | AG119: =AF119*S119 -> 313.33201
A120: =COUNTIF($B$2:B120,B120) -> 1 | B120: 19205181 | C120: 000870/23 | D120: ***.567.773-** | E120: BERLA MOREIRA DE MORAES | F120: PROFESSOR DO MAGISTERIO SUPERIOR | G120: CD-0002 | H120: Cargo Comissionado de Direção | I120: 45166 | J120: 45171 | K120: Representar a UFPB no VII Fórum Permanente de Museus Universitário, em formato presencial, nos dias 28 de agosto a 01 de setembro de 2023, na cidade de Rio de Janeiro - RJ, no Instituto Benjamim Constant, tema: 30 anos depois... para que(m) ainda serve(m) os museus e coleções universitárias? | L120: 45166 | M120: 45171 | N120: João Pessoa | O120: Rio de Janeiro | P120: =VLOOKUP(N120,[1]ID_Cidades!$A$1:$E$5900,2,FALSE) -> 295765 | Q120: =VLOOKUP(O120,[1]ID_Cidades!$A$1:$E$5900,2,FALSE) -> 295778 | R120: =P120*Q120 -> 87480780170 | S120: =VLOOKUP(R120,'[1]GCD base'!$A$1:$M$200,7,FALSE) -> 1961.5008 | T120: Aéreo | U120: Sim | V120: Realizada | W120: SIM | X120: Embora o convite tenha sido enviado, no ato da inscrição as vagas estavam esgotadas, houve hoje, dia 18/08/2023 nova abertura de vagas e com a inscrição aprovada, estamos submetendo para pedido de emissão de passagem e diárias. | Y120: 2329.64 | Z120: 0 | AA120: 2569.59 | AB120: 0 | AC120: 45161 | AD120: Econômica | AE120: {=_xlfn.IFS(S120<=Constantes!$G$2,"Muito Curta (evitável)",S120<=Constantes!$H$2,"Curta Distância",S120>Constantes!$H$2,"Longa Distância")} -> Curta Distância | AF120: =IFERROR(VLOOKUP(AE120,Constantes!$A$1:$E$5,MATCH(AD120,Constantes!$A$1:$E$1,0),0),"") -> 0.18286935 | AG120: =AF120*S120 -> 358.69838
A121: =COUNTIF($B$2:B121,B121) -> 2 | B121: 19205181 | C121: 000870/23 | D121: ***.567.773-** | E121: BERLA MOREIRA DE MORAES | F121: PROFESSOR DO MAGISTERIO SUPERIOR | G121: CD-0002 | H121: Cargo Comissionado de Direção | I121: 45166 | J121: 45171 | K121: Representar a UFPB no VII Fórum Permanente de Museus Universitário, em formato presencial, nos dias 28 de agosto a 01 de setembro de 2023, na cidade de Rio de Janeiro - RJ, no Instituto Benjamim Constant, tema: 30 anos depois... para que(m) ainda serve(m) os museus e coleções universitárias? | L121: 45171 | M121: 45171 | N121: Rio de Janeiro | O121: João Pessoa | P121: =VLOOKUP(N121,[1]ID_Cidades!$A$1:$E$5900,2,FALSE) -> 295778 | Q121: =VLOOKUP(O121,[1]ID_Cidades!$A$1:$E$5900,2,FALSE) -> 295765 | R121: =P121*Q121 -> 87480780170 | S121: =VLOOKUP(R121,'[1]GCD base'!$A$1:$M$200,7,FALSE) -> 1961.5008 | T121: Aéreo | U121: Não | V121: Realizada | W121: SIM | X121: Embora o convite tenha sido enviado, no ato da inscrição as vagas estavam esgotadas, houve hoje, dia 18/08/2023 nova abertura de vagas e com a inscrição aprovada, estamos submetendo para pedido de emissão de passagem e diárias. | Y121: 0 | Z121: 0 | AA121: 0 | AB121: 0 | AC121: 0 | AD121: Econômica | AE121: {=_xlfn.IFS(S121<=Constantes!$G$2,"Muito Curta (evitável)",S121<=Constantes!$H$2,"Curta Distância",S121>Constantes!$H$2,"Longa Distância")} -> Curta Distância | AF121: =IFERROR(VLOOKUP(AE121,Constantes!$A$1:$E$5,MATCH(AD121,Constantes!$A$1:$E$1,0),0),"") -> 0.18286935 | AG121: =AF121*S121 -> 358.69838
A122: =COUNTIF($B$2:B122,B122) -> 1 | B122: 19066792 | C122: 000529/23 | D122: ***.374.464-** | E122: YURI WANDERLEY CAVALCANTI | F122: PROFESSOR DO MAGISTERIO SUPERIOR | G122: FUC-0001 | H122: FUC-0001 | I122: 45171 | J122: 45175 | K122: Apresentar trabalho na 40ª Reunião Anual da SBPqO e participar da Reunião de Coordenadores de Programas de Pós-Graduação em Odontologia | L122: 45174 | M122: 45175 | N122: Campinas | O122: João Pessoa | P122: =VLOOKUP(N122,[1]ID_Cidades!$A$1:$E$5900,2,FALSE) -> 303652 | Q122: =VLOOKUP(O122,[1]ID_Cidades!$A$1:$E$5900,2,FALSE) -> 295765 | R122: =P122*Q122 -> 89809633780 | S122: =VLOOKUP(R122,'[1]GCD base'!$A$1:$M$200,7,FALSE) -> 2193.865 | T122: Aéreo | U122: Não | V122: Realizada | W122: NÃO | X122: Sem informação | Y122: 1359.32 | Z122: 0 | AA122: 1839.72 | AB122: 0 | AC122: 45113 | AD122: Econômica | AE122: {=_xlfn.IFS(S122<=Constantes!$G$2,"Muito Curta (evitável)",S122<=Constantes!$H$2,"Curta Distância",S122>Constantes!$H$2,"Longa Distância")} -> Curta Distância | AF122: =IFERROR(VLOOKUP(AE122,Constantes!$A$1:$E$5,MATCH(AD122,Constantes!$A$1:$E$1,0),0),"") -> 0.18286935 | AG122: =AF122*S122 -> 401.19068
A123: =COUNTIF($B$2:B123,B123) -> 2 | B123: 19066792 | C123: 000529/23 | D123: ***.374.464-** | E123: YURI WANDERLEY CAVALCANTI | F123: PROFESSOR DO MAGISTERIO SUPERIOR | G123: FUC-0001 | H123: FUC-0001 | I123: 45171 | J123: 45175 | K123: Apresentar trabalho na 40ª Reunião Anual da SBPqO e participar da Reunião de Coordenadores de Programas de Pós-Graduação em Odontologia | L123: 45171 | M123: 45174 | N123: João Pessoa | O123: Campinas | P123: =VLOOKUP(N123,[1]ID_Cidades!$A$1:$E$5900,2,FALSE) -> 295765 | Q123: =VLOOKUP(O123,[1]ID_Cidades!$A$1:$E$5900,2,FALSE) -> 303652 | R123: =P123*Q123 -> 89809633780 | S123: =VLOOKUP(R123,'[1]GCD base'!$A$1:$M$200,7,FALSE) -> 2193.865 | T123: Aéreo | U123: Sim | V123: Realizada | W123: NÃO | X123: Sem informação | Y123: 0 | Z123: 0 | AA123: 721.79 | AB123: 0 | AC123: 45113 | AD123: Econômica | AE123: {=_xlfn.IFS(S123<=Constantes!$G$2,"Muito Curta (evitável)",S123<=Constantes!$H$2,"Curta Distância",S123>Constantes!$H$2,"Longa Distância")} -> Curta Distância | AF123: =IFERROR(VLOOKUP(AE123,Constantes!$A$1:$E$5,MATCH(AD123,Constantes!$A$1:$E$1,0),0),"") -> 0.18286935 | AG123: =AF123*S123 -> 401.19068
A124: =COUNTIF($B$2:B124,B124) -> 1 | B124: 19067746 | C124: 000530/23 | D124: ***.221.594-** | E124: LEOPOLDINA DE FATIMA DANTAS DE ALMEIDA CAVALCANTI | F124: PROFESSOR DO MAGISTERIO SUPERIOR | G124: -1 | H124: Sem informação | I124: 45171 | J124: 45175 | K124: Participar da 40ª reunião anual da Sociedade Brasileira de Pesquisa Odontológica, na qual apresentará trabalhos e dará suporte aos alunos de pós-graduação que também tiveram seus resumos aprovados. | L124: 45174 | M124: 45175 | N124: Campinas | O124: João Pessoa | P124: =VLOOKUP(N124,[1]ID_Cidades!$A$1:$E$5900,2,FALSE) -> 303652 | Q124: =VLOOKUP(O124,[1]ID_Cidades!$A$1:$E$5900,2,FALSE) -> 295765 | R124: =P124*Q124 -> 89809633780 | S124: =VLOOKUP(R124,'[1]GCD base'!$A$1:$M$200,7,FALSE) -> 2193.865 | T124: Aéreo | U124: Não | V124: Realizada | W124: NÃO | X124: Sem informação | Y124: 1359.32 | Z124: 0 | AA124: 1839.72 | AB124: 0 | AC124: 45113 | AD124: Econômica | AE124: {=_xlfn.IFS(S124<=Constantes!$G$2,"Muito Curta (evitável)",S124<=Constantes!$H$2,"Curta Distância",S124>Constantes!$H$2,"Longa Distância")} -> Curta Distância | AF124: =IFERROR(VLOOKUP(AE124,Constantes!$A$1:$E$5,MATCH(AD124,Constantes!$A$1:$E$1,0),0),"") -> 0.18286935 | AG124: =AF124*S124 -> 401.19068
A125: =COUNTIF($B$2:B125,B125) -> 2 | B125: 19067746 | C125: 000530/23 | D125: ***.221.594-** | E125: LEOPOLDINA DE FATIMA DANTAS DE ALMEIDA CAVALCANTI | F125: PROFESSOR DO MAGISTERIO SUPERIOR | G125: -1 | H125: Sem informação | I125: 45171 | J125: 45175 | K125: Participar da 40ª reunião anual da Sociedade Brasileira de Pesquisa Odontológica, na qual apresentará trabalhos e dará suporte aos alunos de pós-graduação que também tiveram seus resumos aprovados. | L125: 45171 | M125: 45174 | N125: João Pessoa | O125: Campinas | P125: =VLOOKUP(N125,[1]ID_Cidades!$A$1:$E$5900,2,FALSE) -> 295765 | Q125: =VLOOKUP(O125,[1]ID_Cidades!$A$1:$E$5900,2,FALSE) -> 303652 | R125: =P125*Q125 -> 89809633780 | S125: =VLOOKUP(R125,'[1]GCD base'!$A$1:$M$200,7,FALSE) -> 2193.865 | T125: Aéreo | U125: Sim | V125: Realizada | W125: NÃO | X125: Sem informação | Y125: 0 | Z125: 0 | AA125: 721.79 | AB125: 0 | AC125: 45113 | AD125: Econômica | AE125: {=_xlfn.IFS(S125<=Constantes!$G$2,"Muito Curta (evitável)",S125<=Constantes!$H$2,"Curta Distância",S125>Constantes!$H$2,"Longa Distância")} -> Curta Distância | AF125: =IFERROR(VLOOKUP(AE125,Constantes!$A$1:$E$5,MATCH(AD125,Constantes!$A$1:$E$1,0),0),"") -> 0.18286935 | AG125: =AF125*S125 -> 401.19068
A126: =COUNTIF($B$2:B126,B126) -> 1 | B126: 19203473 | C126: 000868/23 | E126: THAYNNARA PEREIRA MELO | G126: -1 | H126: Sem informação | I126: 45172 | J126: 45177 | K126: Proposto irá participar do Encontro Nacional de Ensino e Pesquisa do Campo de Públicas (ENEPCP 2023), realizando apresentação de trabalho oriundo do projeto de extensão Laboratório de Inovação em Contratos Públicos, vinculado ao Departamento de Gestão Pública. | L126: 45172 | M126: 45176 | N126: João Pessoa | O126: Belo Horizonte | P126: =VLOOKUP(N126,[1]ID_Cidades!$A$1:$E$5900,2,FALSE) -> 295765 | Q126: =VLOOKUP(O126,[1]ID_Cidades!$A$1:$E$5900,2,FALSE) -> 295777 | R126: =P126*Q126 -> 87480484405 | S126: =VLOOKUP(R126,'[1]GCD base'!$A$1:$M$200,7,FALSE) -> 1714.8365 | T126: Aéreo | U126: Sim | V126: Realizada | W126: SIM | X126: DEVIDO AO VOLUME DE DEMANDAS DO SETOR, NÃO FOI POSSÍVEL REALIZAR O CADASTRAMENTO DESSA VIAGEM NO PRAZO HABITUAL. | Y126: 0 | Z126: 0 | AA126: 1403.69 | AB126: 0 | AC126: 45160 | AD126: Econômica | AE126: {=_xlfn.IFS(S126<=Constantes!$G$2,"Muito Curta (evitável)",S126<=Constantes!$H$2,"Curta Distância",S126>Constantes!$H$2,"Longa Distância")} -> Curta Distância | AF126: =IFERROR(VLOOKUP(AE126,Constantes!$A$1:$E$5,MATCH(AD126,Constantes!$A$1:$E$1,0),0),"") -> 0.18286935 | AG126: =AF126*S126 -> 313.59105
...

Sheet Entrada Lvl 5-4 qt
A1: aux | B1: {=_xlfn.UNIQUE(Entradas!B1:B823)} -> Identificador do processo de viagem | C1: Número da Proposta (PCDP) | D1: CPF viajante | E1: Nome | F1: Cargo | G1: Função | H1: Descrição Função | I1: Período - Data de início | J1: Período - Data de fim | K1: Motivo | L1: Distância (km) | M1: Meio de transporte | N1: Missao? | O1: Situação | P1: Viagem Urgente | Q1: Justificativa Urgência Viagem | R1: Valor diárias | S1: Valor outros gastos | T1: Valor da passagem | U1: Taxa de serviço | V1: Data da emissão/compra | W1: Dias de viagem | X1: Classe | Y1: Voo com Escala | Z1: Custo da passagem | AA1: Outros custos | AB1: Motivo da Viagem | AC1: Vínculo Institucional | AD1: dsh, dmh ou dlh | AE1: Viagem Urgente sem justificativa | AF1: Emissões | AG1: ED1.1.1 | AH1: ED1.1.2 | AI1: ED1.1.3 | AJ1: ED1.1 | AK1: ED1.2 | AL1: ED2.1 | AM1: ED2.2 | AN1: ED2.3.1 | AO1: ED2.3.2 | AP1: ED2.3.3 | AQ1: ED2.3 | AR1: ED2.4 | AS1: Tb | AT1: ED2.5 | AU1: ED3.1 | AV1: ED3.2 | AW1: ED3.3 | AX1: DF1.4 | AY1: DF1.5 | AZ1: DF2.1.1 | BA1: DF2.1.2 | BB1: DF2.1.3 | BC1: DF2.1.4 | BD1: DF2.1
A2: =_xlfn.XLOOKUP(B2,Entradas!B:B,Entradas!A:A,,0,-1) -> 2 | B2: 19001658 | C2: =_xlfn.XLOOKUP($B2,Entradas!$B:$B,Entradas!C:C,,0,1) -> 000450/23 | D2: =_xlfn.XLOOKUP($B2,Entradas!$B:$B,Entradas!D:D,,0,1) -> ***.518.375-** | E2: =_xlfn.XLOOKUP($B2,Entradas!$B:$B,Entradas!E:E,,0,1) -> ANGELA DE OLIVEIRA CARNEIRO | F2: =_xlfn.XLOOKUP($B2,Entradas!$B:$B,Entradas!F:F,,0,1) -> PROFESSOR DO MAGISTERIO SUPERIOR | G2: =_xlfn.XLOOKUP($B2,Entradas!$B:$B,Entradas!G:G,,0,1) -> -1 | H2: =_xlfn.XLOOKUP($B2,Entradas!$B:$B,Entradas!H:H,,0,1) -> Sem informação | I2: =_xlfn.XLOOKUP($B2,Entradas!$B:$B,Entradas!I:I,,0,1) -> 45109 | J2: =_xlfn.XLOOKUP($B2,Entradas!$B:$B,Entradas!J:J,,0,1) -> 45121 | K2: =_xlfn.XLOOKUP($B2,Entradas!$B:$B,Entradas!K:K,,0,1) -> O PROPOSTO IRÁ PARTICIPAR COMO MEMBRO DE BANCA DE CONCURSO PÚBLICO DO DEPARTAMENTO DE ENFERMAGEM CLÍNICA | L2: =SUMIF(Entradas!$B:$B,'Entrada Lvl 5-4 qt'!$B2,Entradas!S:S) -> 1331.4793 | M2: =_xlfn.XLOOKUP($B2,Entradas!$B:$B,Entradas!T:T,,0,1) -> Aéreo | N2: =_xlfn.XLOOKUP($B2,Entradas!$B:$B,Entradas!U:U,,0,1) -> Sim | O2: =_xlfn.XLOOKUP($B2,Entradas!$B:$B,Entradas!V:V,,0,1) -> Realizada | P2: =_xlfn.XLOOKUP($B2,Entradas!$B:$B,Entradas!W:W,,0,1) -> SIM | Q2: =_xlfn.XLOOKUP($B2,Entradas!$B:$B,Entradas!X:X,,0,1) -> justificativa em anexo. | R2: =SUMIF(Entradas!$B:$B,'Entrada Lvl 5-4 qt'!$B2,Entradas!Y:Y) -> 4058.65 | S2: =SUMIF(Entradas!$B:$B,'Entrada Lvl 5-4 qt'!$B2,Entradas!Z:Z) -> 0 | T2: =SUMIF(Entradas!$B:$B,'Entrada Lvl 5-4 qt'!$B2,Entradas!AA:AA) -> 4880.98 | U2: =SUMIF(Entradas!$B:$B,'Entrada Lvl 5-4 qt'!$B2,Entradas!AB:AB) -> 0 | V2: =_xlfn.XLOOKUP($B2,Entradas!$B:$B,Entradas!AC:AC,,0,1) -> 45097 | W2: =J2-I2 -> 12 | X2: Econômica | Y2: =IF(A2<3,0,1) -> 0 | Z2: =IFERROR(SUM(T2:U2),0) -> 4880.98 | AA2: =IFERROR(SUM(R2:S2),0) -> 4058.65 | AB2: Participação em Banca Avaliadora | AC2: Acadêmico | AD2: {=_xlfn.IFS(L2<=Constantes!$G$2,"Muito Curta (evitável)",L2<=Constantes!$H$2,"Curta Distância",L2>Constantes!$H$2,"Longa Distância")} -> Curta Distância | AE2: =IF(P2="SIM",IF(Q2="Sem Informação","SIM","NÃO"),"NÃO") -> NÃO | AF2: =SUMIF(Entradas!$B:$B,'Entrada Lvl 5-4 qt'!$B2,Entradas!$AG:$AG) -> 243.48676 | AG2: =SUMIF($AD:$AD,"Muito Curta (evitável)",$AF:$AF) -> 805.86647 | AH2: =SUMIF($AD:$AD,"Curta Distância",$AF:$AF) -> 103690.82 | AI2: =SUMIF($AD:$AD,"Longa Distância",$AF:$AF) -> 194561.12 | AJ2: =SUM(AG2:AI2) -> 299057.81 | AK2: =IFERROR(AJ2/AQ2,0) -> 722.36185 | AL2: =SUM(L:L) -> 1610128.8 | AM2: =AL2/AQ2 -> 3889.1999 | AN2: =COUNTIF($AD:$AD,"Muito Curta (evitável)") -> 6 | AO2: =COUNTIF($AD:$AD,"Curta Distância") -> 204 | AP2: =COUNTIF($AD:$AD,"Longa Distância") -> 204 | AQ2: =SUM(AN2:AP2) -> 414 | AR2: =SUM(Y:Y)/AQ2 -> 0.0072463768 | AS2: =COUNTIF(X:X,"Econômica") -> 414 | AT2: =AS2/AQ2 -> 1 | AU2: =SUM(Z:Z) -> 1150238 | AV2: =SUM(AA:AA) -> 547335.04 | AW2: =SUM(AU2:AV2)/AQ2 -> 4100.418 | AX2: =(SUM((COUNTIF(W:W,"<"&2)),COUNTIF(AD:AD,"Muito Curta (evitável)")))/AQ2 -> 0.031400966 | AY2: =COUNTIFS(P:P,"SIM",Q:Q,"Sem informação")/AS2 -> 0 | AZ2: =(COUNTIF($AC:$AC,"Servidor"))/AQ2 -> 0.31884058 | BA2: =COUNTIF($AC:$AC,"Acadêmico")/AQ2 -> 0.42995169 | BB2: =COUNTIF($AC:$AC,"Discente")/AQ2 -> 0.15217391 | BC2: =COUNTIF($AC:$AC,"Externo")/AQ2 -> 0.099033816 | BD2: =SUM(AZ2:BC2) -> 1
A3: =_xlfn.XLOOKUP(B3,Entradas!B:B,Entradas!A:A,,0,-1) -> 2 | B3: 19016293 | C3: =_xlfn.XLOOKUP($B3,Entradas!$B:$B,Entradas!C:C,,0,1) -> 000452/23 | D3: =_xlfn.XLOOKUP($B3,Entradas!$B:$B,Entradas!D:D,,0,1) -> ***.187.354-** | E3: =_xlfn.XLOOKUP($B3,Entradas!$B:$B,Entradas!E:E,,0,1) -> MARIA FATIMA DE SOUSA | F3: =_xlfn.XLOOKUP($B3,Entradas!$B:$B,Entradas!F:F,,0,1) -> PROFESSOR DO MAGISTERIO SUPERIOR | G3: =_xlfn.XLOOKUP($B3,Entradas!$B:$B,Entradas!G:G,,0,1) -> -1 | H3: =_xlfn.XLOOKUP($B3,Entradas!$B:$B,Entradas!H:H,,0,1) -> Sem informação | I3: =_xlfn.XLOOKUP($B3,Entradas!$B:$B,Entradas!I:I,,0,1) -> 45109 | J3: =_xlfn.XLOOKUP($B3,Entradas!$B:$B,Entradas!J:J,,0,1) -> 45122 | K3: =_xlfn.XLOOKUP($B3,Entradas!$B:$B,Entradas!K:K,,0,1) -> O PROPOSTO IRÁ PARTICIPAR COMO MEMBRO DE BANCA DE CONCURSO PÚBLICO DO DEPARTAMENTO DE ENFERMAGEM CLÍNICA | L3: =SUMIF(Entradas!$B:$B,'Entrada Lvl 5-4 qt'!$B3,Entradas!S:S) -> 3426.84 | M3: =_xlfn.XLOOKUP($B3,Entradas!$B:$B,Entradas!T:T,,0,1) -> Aéreo | N3: =_xlfn.XLOOKUP($B3,Entradas!$B:$B,Entradas!U:U,,0,1) -> Não | O3: =_xlfn.XLOOKUP($B3,Entradas!$B:$B,Entradas!V:V,,0,1) -> Realizada | P3: =_xlfn.XLOOKUP($B3,Entradas!$B:$B,Entradas!W:W,,0,1) -> SIM | Q3: =_xlfn.XLOOKUP($B3,Entradas!$B:$B,Entradas!X:X,,0,1) -> justificativa em anexo. | R3: =SUMIF(Entradas!$B:$B,'Entrada Lvl 5-4 qt'!$B3,Entradas!Y:Y) -> 4399.67 | S3: =SUMIF(Entradas!$B:$B,'Entrada Lvl 5-4 qt'!$B3,Entradas!Z:Z) -> 0 | T3: =SUMIF(Entradas!$B:$B,'Entrada Lvl 5-4 qt'!$B3,Entradas!AA:AA) -> 2590.96 | U3: =SUMIF(Entradas!$B:$B,'Entrada Lvl 5-4 qt'!$B3,Entradas!AB:AB) -> 0 | V3: =_xlfn.XLOOKUP($B3,Entradas!$B:$B,Entradas!AC:AC,,0,1) -> 45097 | W3: =J3-I3 -> 13 | X3: Econômica | Y3: =IF(A3<3,0,1) -> 0 | Z3: =IFERROR(SUM(T3:U3),0) -> 2590.96 | AA3: =IFERROR(SUM(R3:S3),0) -> 4399.67 | AB3: Participação em Banca Avaliadora | AC3: Acadêmico | AD3: {=_xlfn.IFS(L3<=Constantes!$G$2,"Muito Curta (evitável)",L3<=Constantes!$H$2,"Curta Distância",L3>Constantes!$H$2,"Longa Distância")} -> Curta Distância | AE3: =IF(P3="SIM",IF(Q3="Sem Informação","SIM","NÃO"),"NÃO") -> NÃO | AF3: =SUMIF(Entradas!$B:$B,'Entrada Lvl 5-4 qt'!$B3,Entradas!$AG:$AG) -> 626.66402
A4: =_xlfn.XLOOKUP(B4,Entradas!B:B,Entradas!A:A,,0,-1) -> 2 | B4: 19019910 | C4: =_xlfn.XLOOKUP($B4,Entradas!$B:$B,Entradas!C:C,,0,1) -> 000457/23 | D4: =_xlfn.XLOOKUP($B4,Entradas!$B:$B,Entradas!D:D,,0,1) -> ***.105.073-** | E4: =_xlfn.XLOOKUP($B4,Entradas!$B:$B,Entradas!E:E,,0,1) -> ROBERTA MENESES OLIVEIRA | F4: =_xlfn.XLOOKUP($B4,Entradas!$B:$B,Entradas!F:F,,0,1) -> PROFESSOR DO MAGISTERIO SUPERIOR | G4: =_xlfn.XLOOKUP($B4,Entradas!$B:$B,Entradas!G:G,,0,1) -> -1 | H4: =_xlfn.XLOOKUP($B4,Entradas!$B:$B,Entradas!H:H,,0,1) -> Sem informação | I4: =_xlfn.XLOOKUP($B4,Entradas!$B:$B,Entradas!I:I,,0,1) -> 45109 | J4: =_xlfn.XLOOKUP($B4,Entradas!$B:$B,Entradas!J:J,,0,1) -> 45122 | K4: =_xlfn.XLOOKUP($B4,Entradas!$B:$B,Entradas!K:K,,0,1) -> O PROPOSTO IRÁ PARTICIPAR COMO MEMBRO DE BANCA DE CONCURSO PÚBLICO DO DEPARTAMENTO DE ENFERMAGEM CLÍNICA | L4: =SUMIF(Entradas!$B:$B,'Entrada Lvl 5-4 qt'!$B4,Entradas!S:S) -> 1092.4729 | M4: =_xlfn.XLOOKUP($B4,Entradas!$B:$B,Entradas!T:T,,0,1) -> Aéreo | N4: =_xlfn.XLOOKUP($B4,Entradas!$B:$B,Entradas!U:U,,0,1) -> Sim | O4: =_xlfn.XLOOKUP($B4,Entradas!$B:$B,Entradas!V:V,,0,1) -> Realizada | P4: =_xlfn.XLOOKUP($B4,Entradas!$B:$B,Entradas!W:W,,0,1) -> SIM | Q4: =_xlfn.XLOOKUP($B4,Entradas!$B:$B,Entradas!X:X,,0,1) -> justificativa em anexo. | R4: =SUMIF(Entradas!$B:$B,'Entrada Lvl 5-4 qt'!$B4,Entradas!Y:Y) -> 4399.67 | S4: =SUMIF(Entradas!$B:$B,'Entrada Lvl 5-4 qt'!$B4,Entradas!Z:Z) -> 0 | T4: =SUMIF(Entradas!$B:$B,'Entrada Lvl 5-4 qt'!$B4,Entradas!AA:AA) -> 1709.7 | U4: =SUMIF(Entradas!$B:$B,'Entrada Lvl 5-4 qt'!$B4,Entradas!AB:AB) -> 0 | V4: =_xlfn.XLOOKUP($B4,Entradas!$B:$B,Entradas!AC:AC,,0,1) -> 45098 | W4: =J4-I4 -> 13 | X4: Econômica | Y4: =IF(A4<3,0,1) -> 0 | Z4: =IFERROR(SUM(T4:U4),0) -> 1709.7 | AA4: =IFERROR(SUM(R4:S4),0) -> 4399.67 | AB4: Participação em Banca Avaliadora | AC4: Acadêmico | AD4: {=_xlfn.IFS(L4<=Constantes!$G$2,"Muito Curta (evitável)",L4<=Constantes!$H$2,"Curta Distância",L4>Constantes!$H$2,"Longa Distância")} -> Curta Distância | AE4: =IF(P4="SIM",IF(Q4="Sem Informação","SIM","NÃO"),"NÃO") -> NÃO | AF4: =SUMIF(Entradas!$B:$B,'Entrada Lvl 5-4 qt'!$B4,Entradas!$AG:$AG) -> 297.78274
A5: =_xlfn.XLOOKUP(B5,Entradas!B:B,Entradas!A:A,,0,-1) -> 2 | B5: 19041737 | C5: =_xlfn.XLOOKUP($B5,Entradas!$B:$B,Entradas!C:C,,0,1) -> 000481/23-3C | D5: =_xlfn.XLOOKUP($B5,Entradas!$B:$B,Entradas!D:D,,0,1) -> ***.567.773-** | E5: =_xlfn.XLOOKUP($B5,Entradas!$B:$B,Entradas!E:E,,0,1) -> BERLA MOREIRA DE MORAES | F5: =_xlfn.XLOOKUP($B5,Entradas!$B:$B,Entradas!F:F,,0,1) -> PROFESSOR DO MAGISTERIO SUPERIOR | G5: =_xlfn.XLOOKUP($B5,Entradas!$B:$B,Entradas!G:G,,0,1) -> CD-0002 | H5: =_xlfn.XLOOKUP($B5,Entradas!$B:$B,Entradas!H:H,,0,1) -> Cargo Comissionado de Direção | I5: =_xlfn.XLOOKUP($B5,Entradas!$B:$B,Entradas!I:I,,0,1) -> 45110 | J5: =_xlfn.XLOOKUP($B5,Entradas!$B:$B,Entradas!J:J,,0,1) -> 45113 | K5: =_xlfn.XLOOKUP($B5,Entradas!$B:$B,Entradas!K:K,,0,1) -> Participar do I ENCONTRO NACIONAL DE CULTURA & ARTE NAS UNIVERSIDADES FEDERAIS BRASILEIRAS, em Salvador/BA, no período de 03 a 05/07/2023 | L5: =SUMIF(Entradas!$B:$B,'Entrada Lvl 5-4 qt'!$B5,Entradas!S:S) -> 1482.2388 | M5: =_xlfn.XLOOKUP($B5,Entradas!$B:$B,Entradas!T:T,,0,1) -> Aéreo | N5: =_xlfn.XLOOKUP($B5,Entradas!$B:$B,Entradas!U:U,,0,1) -> Sim | O5: =_xlfn.XLOOKUP($B5,Entradas!$B:$B,Entradas!V:V,,0,1) -> Realizada | P5: =_xlfn.XLOOKUP($B5,Entradas!$B:$B,Entradas!W:W,,0,1) -> SIM | Q5: =_xlfn.XLOOKUP($B5,Entradas!$B:$B,Entradas!X:X,,0,1) -> 0 convite para participar do evento chegou fora do prazo, conforme justificativa no formulário de solicitação | R5: =SUMIF(Entradas!$B:$B,'Entrada Lvl 5-4 qt'!$B5,Entradas!Y:Y) -> 1720.73 | S5: =SUMIF(Entradas!$B:$B,'Entrada Lvl 5-4 qt'!$B5,Entradas!Z:Z) -> 0 | T5: =SUMIF(Entradas!$B:$B,'Entrada Lvl 5-4 qt'!$B5,Entradas!AA:AA) -> 3694.45 | U5: =SUMIF(Entradas!$B:$B,'Entrada Lvl 5-4 qt'!$B5,Entradas!AB:AB) -> 0 | V5: =_xlfn.XLOOKUP($B5,Entradas!$B:$B,Entradas!AC:AC,,0,1) -> 45104 | W5: =J5-I5 -> 3 | X5: Econômica | Y5: =IF(A5<3,0,1) -> 0 | Z5: =IFERROR(SUM(T5:U5),0) -> 3694.45 | AA5: =IFERROR(SUM(R5:S5),0) -> 1720.73 | AB5: Representação em Evento Institucional | AC5: Servidor | AD5: {=_xlfn.IFS(L5<=Constantes!$G$2,"Muito Curta (evitável)",L5<=Constantes!$H$2,"Curta Distância",L5>Constantes!$H$2,"Longa Distância")} -> Curta Distância | AE5: =IF(P5="SIM",IF(Q5="Sem Informação","SIM","NÃO"),"NÃO") -> NÃO | AF5: =SUMIF(Entradas!$B:$B,'Entrada Lvl 5-4 qt'!$B5,Entradas!$AG:$AG) -> 271.05606
A6: =_xlfn.XLOOKUP(B6,Entradas!B:B,Entradas!A:A,,0,-1) -> 2 | B6: 19041166 | C6: =_xlfn.XLOOKUP($B6,Entradas!$B:$B,Entradas!C:C,,0,1) -> 000484/23 | D6: =_xlfn.XLOOKUP($B6,Entradas!$B:$B,Entradas!D:D,,0,1) -> ***.028.207-** | E6: =_xlfn.XLOOKUP($B6,Entradas!$B:$B,Entradas!E:E,,0,1) -> MARCELO FERNANDES | F6: =_xlfn.XLOOKUP($B6,Entradas!$B:$B,Entradas!F:F,,0,1) | G6: =_xlfn.XLOOKUP($B6,Entradas!$B:$B,Entradas!G:G,,0,1) -> -1 | H6: =_xlfn.XLOOKUP($B6,Entradas!$B:$B,Entradas!H:H,,0,1) -> Sem informação | I6: =_xlfn.XLOOKUP($B6,Entradas!$B:$B,Entradas!I:I,,0,1) -> 45112 | J6: =_xlfn.XLOOKUP($B6,Entradas!$B:$B,Entradas!J:J,,0,1) -> 45114 | K6: =_xlfn.XLOOKUP($B6,Entradas!$B:$B,Entradas!K:K,,0,1) -> Ministrar um mini-curso e seminário acadêmico no PPGE/CCSA, nos dias 06 e 07 de julho de 2023. | L6: =SUMIF(Entradas!$B:$B,'Entrada Lvl 5-4 qt'!$B6,Entradas!S:S) -> 4379.9485 | M6: =_xlfn.XLOOKUP($B6,Entradas!$B:$B,Entradas!T:T,,0,1) -> Aéreo | N6: =_xlfn.XLOOKUP($B6,Entradas!$B:$B,Entradas!U:U,,0,1) -> Não | O6: =_xlfn.XLOOKUP($B6,Entradas!$B:$B,Entradas!V:V,,0,1) -> Realizada | P6: =_xlfn.XLOOKUP($B6,Entradas!$B:$B,Entradas!W:W,,0,1) -> SIM | Q6: =_xlfn.XLOOKUP($B6,Entradas!$B:$B,Entradas!X:X,,0,1) -> Aguardava-se a liberação dos recurso do PROAP, por essa razão, não foi solicitado antes. | R6: =SUMIF(Entradas!$B:$B,'Entrada Lvl 5-4 qt'!$B6,Entradas!Y:Y) -> 947.55 | S6: =SUMIF(Entradas!$B:$B,'Entrada Lvl 5-4 qt'!$B6,Entradas!Z:Z) -> 0 | T6: =SUMIF(Entradas!$B:$B,'Entrada Lvl 5-4 qt'!$B6,Entradas!AA:AA) -> 3147.82 | U6: =SUMIF(Entradas!$B:$B,'Entrada Lvl 5-4 qt'!$B6,Entradas!AB:AB) -> 0 | V6: =_xlfn.XLOOKUP($B6,Entradas!$B:$B,Entradas!AC:AC,,0,1) -> 45105 | W6: =J6-I6 -> 2 | X6: Econômica | Y6: =IF(A6<3,0,1) -> 0 | Z6: =IFERROR(SUM(T6:U6),0) -> 3147.82 | AA6: =IFERROR(SUM(R6:S6),0) -> 947.55 | AB6: Participação em Evento Acadêmico | AC6: Externo | AD6: {=_xlfn.IFS(L6<=Constantes!$G$2,"Muito Curta (evitável)",L6<=Constantes!$H$2,"Curta Distância",L6>Constantes!$H$2,"Longa Distância")} -> Longa Distância | AE6: =IF(P6="SIM",IF(Q6="Sem Informação","SIM","NÃO"),"NÃO") -> NÃO | AF6: =SUMIF(Entradas!$B:$B,'Entrada Lvl 5-4 qt'!$B6,Entradas!$AG:$AG) -> 800.95835
A7: =_xlfn.XLOOKUP(B7,Entradas!B:B,Entradas!A:A,,0,-1) -> 2 | B7: 19062585 | C7: =_xlfn.XLOOKUP($B7,Entradas!$B:$B,Entradas!C:C,,0,1) -> 000508/23 | D7: =_xlfn.XLOOKUP($B7,Entradas!$B:$B,Entradas!D:D,,0,1) -> ***.731.370-** | E7: =_xlfn.XLOOKUP($B7,Entradas!$B:$B,Entradas!E:E,,0,1) -> SERGIO BOTTON BARCELLOS | F7: =_xlfn.XLOOKUP($B7,Entradas!$B:$B,Entradas!F:F,,0,1) -> PROFESSOR DO MAGISTERIO SUPERIOR | G7: =_xlfn.XLOOKUP($B7,Entradas!$B:$B,Entradas!G:G,,0,1) -> FUC-0001 | H7: =_xlfn.XLOOKUP($B7,Entradas!$B:$B,Entradas!H:H,,0,1) -> FUC-0001 | I7: =_xlfn.XLOOKUP($B7,Entradas!$B:$B,Entradas!I:I,,0,1) -> 45117 | J7: =_xlfn.XLOOKUP($B7,Entradas!$B:$B,Entradas!J:J,,0,1) -> 45122 | K7: =_xlfn.XLOOKUP($B7,Entradas!$B:$B,Entradas!K:K,,0,1) -> Participação no 21º Congresso Brasileiro de Sociologia para mediação de um Comitê de Pesquisa e apresentação de um trabalho em GT. Ao mesmo tempo irei representando o PPGS-UFOB como coordenador na Plenária de Programas da área de Sociologia. | L7: =SUMIF(Entradas!$B:$B,'Entrada Lvl 5-4 qt'!$B7,Entradas!S:S) -> 3262.9123 | M7: =_xlfn.XLOOKUP($B7,Entradas!$B:$B,Entradas!T:T,,0,1) -> Aéreo | N7: =_xlfn.XLOOKUP($B7,Entradas!$B:$B,Entradas!U:U,,0,1) -> Sim | O7: =_xlfn.XLOOKUP($B7,Entradas!$B:$B,Entradas!V:V,,0,1) -> Realizada | P7: =_xlfn.XLOOKUP($B7,Entradas!$B:$B,Entradas!W:W,,0,1) -> SIM | Q7: =_xlfn.XLOOKUP($B7,Entradas!$B:$B,Entradas!X:X,,0,1) -> Recurso PROAP não foi disponibilizado com antecedência. | R7: =SUMIF(Entradas!$B:$B,'Entrada Lvl 5-4 qt'!$B7,Entradas!Y:Y) -> 1821.06 | S7: =SUMIF(Entradas!$B:$B,'Entrada Lvl 5-4 qt'!$B7,Entradas!Z:Z) -> 0 | T7: =SUMIF(Entradas!$B:$B,'Entrada Lvl 5-4 qt'!$B7,Entradas!AA:AA) -> 5292.78 | U7: =SUMIF(Entradas!$B:$B,'Entrada Lvl 5-4 qt'!$B7,Entradas!AB:AB) -> 0 | V7: =_xlfn.XLOOKUP($B7,Entradas!$B:$B,Entradas!AC:AC,,0,1) -> 45113 | W7: =J7-I7 -> 5 | X7: Econômica | Y7: =IF(A7<3,0,1) -> 0 | Z7: =IFERROR(SUM(T7:U7),0) -> 5292.78 | AA7: =IFERROR(SUM(R7:S7),0) -> 1821.06 | AB7: Participação em Evento Acadêmico | AC7: Acadêmico | AD7: {=_xlfn.IFS(L7<=Constantes!$G$2,"Muito Curta (evitável)",L7<=Constantes!$H$2,"Curta Distância",L7>Constantes!$H$2,"Longa Distância")} -> Curta Distância | AE7: =IF(P7="SIM",IF(Q7="Sem Informação","SIM","NÃO"),"NÃO") -> NÃO | AF7: =SUMIF(Entradas!$B:$B,'Entrada Lvl 5-4 qt'!$B7,Entradas!$AG:$AG) -> 596.68666
A8: =_xlfn.XLOOKUP(B8,Entradas!B:B,Entradas!A:A,,0,-1) -> 2 | B8: 19065213 | C8: =_xlfn.XLOOKUP($B8,Entradas!$B:$B,Entradas!C:C,,0,1) -> 000509/23 | D8: =_xlfn.XLOOKUP($B8,Entradas!$B:$B,Entradas!D:D,,0,1) -> ***.585.343-** | E8: =_xlfn.XLOOKUP($B8,Entradas!$B:$B,Entradas!E:E,,0,1) -> TERESA CRISTINA FURTADO MATOS | F8: =_xlfn.XLOOKUP($B8,Entradas!$B:$B,Entradas!F:F,,0,1) -> PROFESSOR DO MAGISTERIO SUPERIOR | G8: =_xlfn.XLOOKUP($B8,Entradas!$B:$B,Entradas!G:G,,0,1) -> -1 | H8: =_xlfn.XLOOKUP($B8,Entradas!$B:$B,Entradas!H:H,,0,1) -> Sem informação | I8: =_xlfn.XLOOKUP($B8,Entradas!$B:$B,Entradas!I:I,,0,1) -> 45117 | J8: =_xlfn.XLOOKUP($B8,Entradas!$B:$B,Entradas!J:J,,0,1) -> 45122 | K8: =_xlfn.XLOOKUP($B8,Entradas!$B:$B,Entradas!K:K,,0,1) -> Participação no 21º Congresso Brasileiro de Sociologia, com apresentação de trabalho no GT 10 do evento. | L8: =SUMIF(Entradas!$B:$B,'Entrada Lvl 5-4 qt'!$B8,Entradas!S:S) -> 3262.9123 | M8: =_xlfn.XLOOKUP($B8,Entradas!$B:$B,Entradas!T:T,,0,1) -> Aéreo | N8: =_xlfn.XLOOKUP($B8,Entradas!$B:$B,Entradas!U:U,,0,1) -> Sim | O8: =_xlfn.XLOOKUP($B8,Entradas!$B:$B,Entradas!V:V,,0,1) -> Realizada | P8: =_xlfn.XLOOKUP($B8,Entradas!$B:$B,Entradas!W:W,,0,1) -> SIM | Q8: =_xlfn.XLOOKUP($B8,Entradas!$B:$B,Entradas!X:X,,0,1) -> PROAP não foi liberado anteriormente. | R8: =SUMIF(Entradas!$B:$B,'Entrada Lvl 5-4 qt'!$B8,Entradas!Y:Y) -> 1821.06 | S8: =SUMIF(Entradas!$B:$B,'Entrada Lvl 5-4 qt'!$B8,Entradas!Z:Z) -> 0 | T8: =SUMIF(Entradas!$B:$B,'Entrada Lvl 5-4 qt'!$B8,Entradas!AA:AA) -> 5292.78 | U8: =SUMIF(Entradas!$B:$B,'Entrada Lvl 5-4 qt'!$B8,Entradas!AB:AB) -> 0 | V8: =_xlfn.XLOOKUP($B8,Entradas!$B:$B,Entradas!AC:AC,,0,1) -> 45114 | W8: =J8-I8 -> 5 | X8: Econômica | Y8: =IF(A8<3,0,1) -> 0 | Z8: =IFERROR(SUM(T8:U8),0) -> 5292.78 | AA8: =IFERROR(SUM(R8:S8),0) -> 1821.06 | AB8: Participação em Evento Acadêmico | AC8: Acadêmico | AD8: {=_xlfn.IFS(L8<=Constantes!$G$2,"Muito Curta (evitável)",L8<=Constantes!$H$2,"Curta Distância",L8>Constantes!$H$2,"Longa Distância")} -> Curta Distância | AE8: =IF(P8="SIM",IF(Q8="Sem Informação","SIM","NÃO"),"NÃO") -> NÃO | AF8: =SUMIF(Entradas!$B:$B,'Entrada Lvl 5-4 qt'!$B8,Entradas!$AG:$AG) -> 596.68666
A9: =_xlfn.XLOOKUP(B9,Entradas!B:B,Entradas!A:A,,0,-1) -> 2 | B9: 19012122 | C9: =_xlfn.XLOOKUP($B9,Entradas!$B:$B,Entradas!C:C,,0,1) -> 000532/23 | D9: =_xlfn.XLOOKUP($B9,Entradas!$B:$B,Entradas!D:D,,0,1) -> ***.103.474-** | E9: =_xlfn.XLOOKUP($B9,Entradas!$B:$B,Entradas!E:E,,0,1) -> HIDELBRANDO JOSE FARKAT DIOGENES | F9: =_xlfn.XLOOKUP($B9,Entradas!$B:$B,Entradas!F:F,,0,1) -> PROFESSOR DO MAGISTERIO SUPERIOR | G9: =_xlfn.XLOOKUP($B9,Entradas!$B:$B,Entradas!G:G,,0,1) -> FUC-0001 | H9: =_xlfn.XLOOKUP($B9,Entradas!$B:$B,Entradas!H:H,,0,1) -> FUC-0001 | I9: =_xlfn.XLOOKUP($B9,Entradas!$B:$B,Entradas!I:I,,0,1) -> 45118 | J9: =_xlfn.XLOOKUP($B9,Entradas!$B:$B,Entradas!J:J,,0,1) -> 45123 | K9: =_xlfn.XLOOKUP($B9,Entradas!$B:$B,Entradas!K:K,,0,1) -> Trata-se da participação em evento científico internacional, a fim de divulgar resultados parciais do doutoramento de Lays Costa, aluna do PPGECAM sob orientação do Prof. Hidelbrando José Farkat Diógenes. | L9: =SUMIF(Entradas!$B:$B,'Entrada Lvl 5-4 qt'!$B9,Entradas!S:S) -> 9403.3229 | M9: =_xlfn.XLOOKUP($B9,Entradas!$B:$B,Entradas!T:T,,0,1) -> Aéreo | N9: =_xlfn.XLOOKUP($B9,Entradas!$B:$B,Entradas!U:U,,0,1) -> Não | O9: =_xlfn.XLOOKUP($B9,Entradas!$B:$B,Entradas!V:V,,0,1) -> Realizada | P9: =_xlfn.XLOOKUP($B9,Entradas!$B:$B,Entradas!W:W,,0,1) -> SIM | Q9: =_xlfn.XLOOKUP($B9,Entradas!$B:$B,Entradas!X:X,,0,1) -> A viagem só pode ser cadastrada nesta data devido ao recurso do PROAP destinado ao pagamento da despesa só foi liberado dia 05/07 e estávamos aguardando, também, a realização do empenho específico. | R9: =SUMIF(Entradas!$B:$B,'Entrada Lvl 5-4 qt'!$B9,Entradas!Y:Y) -> 4252.24 | S9: =SUMIF(Entradas!$B:$B,'Entrada Lvl 5-4 qt'!$B9,Entradas!Z:Z) -> 0 | T9: =SUMIF(Entradas!$B:$B,'Entrada Lvl 5-4 qt'!$B9,Entradas!AA:AA) -> 6690.84 | U9: =SUMIF(Entradas!$B:$B,'Entrada Lvl 5-4 qt'!$B9,Entradas!AB:AB) -> 0 | V9: =_xlfn.XLOOKUP($B9,Entradas!$B:$B,Entradas!AC:AC,,0,1) -> 45113 | W9: =J9-I9 -> 5 | X9: Econômica | Y9: =IF(A9<3,0,1) -> 0 | Z9: =IFERROR(SUM(T9:U9),0) -> 6690.84 | AA9: =IFERROR(SUM(R9:S9),0) -> 4252.24 | AB9: Participação em Evento Acadêmico | AC9: Acadêmico | AD9: {=_xlfn.IFS(L9<=Constantes!$G$2,"Muito Curta (evitável)",L9<=Constantes!$H$2,"Curta Distância",L9>Constantes!$H$2,"Longa Distância")} -> Longa Distância | AE9: =IF(P9="SIM",IF(Q9="Sem Informação","SIM","NÃO"),"NÃO") -> NÃO | AF9: =SUMIF(Entradas!$B:$B,'Entrada Lvl 5-4 qt'!$B9,Entradas!$AG:$AG) -> 1881.6828
A10: =_xlfn.XLOOKUP(B10,Entradas!B:B,Entradas!A:A,,0,-1) -> 2 | B10: 18932951 | C10: =_xlfn.XLOOKUP($B10,Entradas!$B:$B,Entradas!C:C,,0,1) -> 000393/23 | D10: =_xlfn.XLOOKUP($B10,Entradas!$B:$B,Entradas!D:D,,0,1) -> ***.778.616-** | E10: =_xlfn.XLOOKUP($B10,Entradas!$B:$B,Entradas!E:E,,0,1) -> PRISCILLA GONTIJO LEITE | F10: =_xlfn.XLOOKUP($B10,Entradas!$B:$B,Entradas!F:F,,0,1) -> PROFESSOR DO MAGISTERIO SUPERIOR | G10: =_xlfn.XLOOKUP($B10,Entradas!$B:$B,Entradas!G:G,,0,1) -> -1 | H10: =_xlfn.XLOOKUP($B10,Entradas!$B:$B,Entradas!H:H,,0,1) -> Sem informação | I10: =_xlfn.XLOOKUP($B10,Entradas!$B:$B,Entradas!I:I,,0,1) -> 45120 | J10: =_xlfn.XLOOKUP($B10,Entradas!$B:$B,Entradas!J:J,,0,1) -> 45128 | K10: =_xlfn.XLOOKUP($B10,Entradas!$B:$B,Entradas!K:K,,0,1) -> Participação da Plenária de Coordenadores do ProfHistória que reúne duas vezes por ano. Esta será a primeira plenária que tem como finalidade de debater e deliberar sobre temas e questões pertinentes ao ProfHistória, propostos pela Comissão Acadêmica Nacional e ou pelas Comissões Acadêmicas Locais. Participação do 32º Simpósio Nacional de História da ANPUH com a comunicação 'Ensino de História Antiga e gamificação para a aprendizagem das formas de governo'. | L10: =SUMIF(Entradas!$B:$B,'Entrada Lvl 5-4 qt'!$B10,Entradas!S:S) -> 2294.6939 | M10: =_xlfn.XLOOKUP($B10,Entradas!$B:$B,Entradas!T:T,,0,1) -> Aéreo | N10: =_xlfn.XLOOKUP($B10,Entradas!$B:$B,Entradas!U:U,,0,1) -> Não | O10: =_xlfn.XLOOKUP($B10,Entradas!$B:$B,Entradas!V:V,,0,1) -> Realizada | P10: =_xlfn.XLOOKUP($B10,Entradas!$B:$B,Entradas!W:W,,0,1) -> NÃO | Q10: =_xlfn.XLOOKUP($B10,Entradas!$B:$B,Entradas!X:X,,0,1) -> Sem informação | R10: =SUMIF(Entradas!$B:$B,'Entrada Lvl 5-4 qt'!$B10,Entradas!Y:Y) -> 2784.3 | S10: =SUMIF(Entradas!$B:$B,'Entrada Lvl 5-4 qt'!$B10,Entradas!Z:Z) -> 0 | T10: =SUMIF(Entradas!$B:$B,'Entrada Lvl 5-4 qt'!$B10,Entradas!AA:AA) -> 3284.38 | U10: =SUMIF(Entradas!$B:$B,'Entrada Lvl 5-4 qt'!$B10,Entradas!AB:AB) -> 0 | V10: =_xlfn.XLOOKUP($B10,Entradas!$B:$B,Entradas!AC:AC,,0,1) -> 45083 | W10: =J10-I10 -> 8 | X10: Econômica | Y10: =IF(A10<3,0,1) -> 0 | Z10: =IFERROR(SUM(T10:U10),0) -> 3284.38 | AA10: =IFERROR(SUM(R10:S10),0) -> 2784.3 | AB10: Representação em Reunião Institucional | AC10: Acadêmico | AD10: {=_xlfn.IFS(L10<=Constantes!$G$2,"Muito Curta (evitável)",L10<=Constantes!$H$2,"Curta Distância",L10>Constantes!$H$2,"Longa Distância")} -> Curta Distância | AE10: =IF(P10="SIM",IF(Q10="Sem Informação","SIM","NÃO"),"NÃO") -> NÃO | AF10: =SUMIF(Entradas!$B:$B,'Entrada Lvl 5-4 qt'!$B10,Entradas!$AG:$AG) -> 419.62919
A11: =_xlfn.XLOOKUP(B11,Entradas!B:B,Entradas!A:A,,0,-1) -> 2 | B11: 19032444 | C11: =_xlfn.XLOOKUP($B11,Entradas!$B:$B,Entradas!C:C,,0,1) -> 000472/23 | D11: =_xlfn.XLOOKUP($B11,Entradas!$B:$B,Entradas!D:D,,0,1) -> ***.888.244-** | E11: =_xlfn.XLOOKUP($B11,Entradas!$B:$B,Entradas!E:E,,0,1) -> CARLOS ALBERTO OLIVEIRA BONIFACIO JUNIOR | F11: =_xlfn.XLOOKUP($B11,Entradas!$B:$B,Entradas!F:F,,0,1) | G11: =_xlfn.XLOOKUP($B11,Entradas!$B:$B,Entradas!G:G,,0,1) -> -1 | H11: =_xlfn.XLOOKUP($B11,Entradas!$B:$B,Entradas!H:H,,0,1) -> Sem informação | I11: =_xlfn.XLOOKUP($B11,Entradas!$B:$B,Entradas!I:I,,0,1) -> 45120 | J11: =_xlfn.XLOOKUP($B11,Entradas!$B:$B,Entradas!J:J,,0,1) -> 45125 | K11: =_xlfn.XLOOKUP($B11,Entradas!$B:$B,Entradas!K:K,,0,1) -> PROPOSTO APRESENTARÁ TRABALHO NO 25º FONEPE, QUE OCORRERÁ EM DOURADOS (MS), ENTRE OS DIAS 14,15 E 16 DE JULHO. | L11: =SUMIF(Entradas!$B:$B,'Entrada Lvl 5-4 qt'!$B11,Entradas!S:S) -> 5177.7979 | M11: =_xlfn.XLOOKUP($B11,Entradas!$B:$B,Entradas!T:T,,0,1) -> Aéreo | N11: =_xlfn.XLOOKUP($B11,Entradas!$B:$B,Entradas!U:U,,0,1) -> Não | O11: =_xlfn.XLOOKUP($B11,Entradas!$B:$B,Entradas!V:V,,0,1) -> Realizada | P11: =_xlfn.XLOOKUP($B11,Entradas!$B:$B,Entradas!W:W,,0,1) -> SIM | Q11: =_xlfn.XLOOKUP($B11,Entradas!$B:$B,Entradas!X:X,,0,1) -> Tendo em vista problemas na emissão da passagem terrestre, a viagem entrou em período de urgência. | R11: =SUMIF(Entradas!$B:$B,'Entrada Lvl 5-4 qt'!$B11,Entradas!Y:Y) -> 0 | S11: =SUMIF(Entradas!$B:$B,'Entrada Lvl 5-4 qt'!$B11,Entradas!Z:Z) -> 0 | T11: =SUMIF(Entradas!$B:$B,'Entrada Lvl 5-4 qt'!$B11,Entradas!AA:AA) -> 2012.46 | U11: =SUMIF(Entradas!$B:$B,'Entrada Lvl 5-4 qt'!$B11,Entradas!AB:AB) -> 0 | V11: =_xlfn.XLOOKUP($B11,Entradas!$B:$B,Entradas!AC:AC,,0,1) -> 45103 | W11: =J11-I11 -> 5 | X11: Econômica | Y11: =IF(A11<3,0,1) -> 0 | Z11: =IFERROR(SUM(T11:U11),0) -> 2012.46 | AA11: =IFERROR(SUM(R11:S11),0) -> 0 | AB11: Participação em Evento Acadêmico | AC11: Discente | AD11: {=_xlfn.IFS(L11<=Constantes!$G$2,"Muito Curta (evitável)",L11<=Constantes!$H$2,"Curta Distância",L11>Constantes!$H$2,"Longa Distância")} -> Longa Distância | AE11: =IF(P11="SIM",IF(Q11="Sem Informação","SIM","NÃO"),"NÃO") -> NÃO | AF11: =SUMIF(Entradas!$B:$B,'Entrada Lvl 5-4 qt'!$B11,Entradas!$AG:$AG) -> 946.86055
A12: =_xlfn.XLOOKUP(B12,Entradas!B:B,Entradas!A:A,,0,-1) -> 2 | B12: 19098667 | C12: =_xlfn.XLOOKUP($B12,Entradas!$B:$B,Entradas!C:C,,0,1) -> 000601/23 | D12: =_xlfn.XLOOKUP($B12,Entradas!$B:$B,Entradas!D:D,,0,1) -> ***.096.714-** | E12: =_xlfn.XLOOKUP($B12,Entradas!$B:$B,Entradas!E:E,,0,1) -> FRANCISCO HUMBERTO XAVIER JUNIOR | F12: =_xlfn.XLOOKUP($B12,Entradas!$B:$B,Entradas!F:F,,0,1) -> PROFESSOR DO MAGISTERIO SUPERIOR | G12: =_xlfn.XLOOKUP($B12,Entradas!$B:$B,Entradas!G:G,,0,1) -> -1 | H12: =_xlfn.XLOOKUP($B12,Entradas!$B:$B,Entradas!H:H,,0,1) -> Sem informação | I12: =_xlfn.XLOOKUP($B12,Entradas!$B:$B,Entradas!I:I,,0,1) -> 45129 | J12: =_xlfn.XLOOKUP($B12,Entradas!$B:$B,Entradas!J:J,,0,1) -> 45134 | K12: =_xlfn.XLOOKUP($B12,Entradas!$B:$B,Entradas!K:K,,0,1) -> Recebimento do prêmio da 20ª edição do Destaque na Iniciação Científica e Tecnológica entregue pelo presidente do Conselho Nacional de Desenvolvimento Científico e Tecnológico (CNPq), o qual foi concedido a premiação na categoria Iniciação Tecnológica na área das Ciências da Vida para a aluna Ana Flávia Chaves Uchôa, sob minha orientação (anexo I), e será entregue na 75ª Reunião Anual da Sociedade Brasileira para o Progresso da Ciência (SBPC) entre os dias 23 a 29 de julho na Universidade Federal do Paraná (UFPR), em Curitiba | L12: =SUMIF(Entradas!$B:$B,'Entrada Lvl 5-4 qt'!$B12,Entradas!S:S) -> 5083.2953 | M12: =_xlfn.XLOOKUP($B12,Entradas!$B:$B,Entradas!T:T,,0,1) -> Aéreo | N12: =_xlfn.XLOOKUP($B12,Entradas!$B:$B,Entradas!U:U,,0,1) -> Não | O12: =_xlfn.XLOOKUP($B12,Entradas!$B:$B,Entradas!V:V,,0,1) -> Realizada | P12: =_xlfn.XLOOKUP($B12,Entradas!$B:$B,Entradas!W:W,,0,1) -> SIM | Q12: =_xlfn.XLOOKUP($B12,Entradas!$B:$B,Entradas!X:X,,0,1) -> Formulário em anexo | R12: =SUMIF(Entradas!$B:$B,'Entrada Lvl 5-4 qt'!$B12,Entradas!Y:Y) -> 1850.97 | S12: =SUMIF(Entradas!$B:$B,'Entrada Lvl 5-4 qt'!$B12,Entradas!Z:Z) -> 0 | T12: =SUMIF(Entradas!$B:$B,'Entrada Lvl 5-4 qt'!$B12,Entradas!AA:AA) -> 2660.48 | U12: =SUMIF(Entradas!$B:$B,'Entrada Lvl 5-4 qt'!$B12,Entradas!AB:AB) -> 0 | V12: =_xlfn.XLOOKUP($B12,Entradas!$B:$B,Entradas!AC:AC,,0,1) -> 45125 | W12: =J12-I12 -> 5 | X12: Econômica | Y12: =IF(A12<3,0,1) -> 0 | Z12: =IFERROR(SUM(T12:U12),0) -> 2660.48 | AA12: =IFERROR(SUM(R12:S12),0) -> 1850.97 | AB12: Participação em Evento Acadêmico | AC12: Acadêmico | AD12: {=_xlfn.IFS(L12<=Constantes!$G$2,"Muito Curta (evitável)",L12<=Constantes!$H$2,"Curta Distância",L12>Constantes!$H$2,"Longa Distância")} -> Longa Distância | AE12: =IF(P12="SIM",IF(Q12="Sem Informação","SIM","NÃO"),"NÃO") -> NÃO | AF12: =SUMIF(Entradas!$B:$B,'Entrada Lvl 5-4 qt'!$B12,Entradas!$AG:$AG) -> 929.57892
A13: =_xlfn.XLOOKUP(B13,Entradas!B:B,Entradas!A:A,,0,-1) -> 2 | B13: 18973156 | C13: =_xlfn.XLOOKUP($B13,Entradas!$B:$B,Entradas!C:C,,0,1) -> 000407/23 | D13: =_xlfn.XLOOKUP($B13,Entradas!$B:$B,Entradas!D:D,,0,1) -> ***.961.302-** | E13: =_xlfn.XLOOKUP($B13,Entradas!$B:$B,Entradas!E:E,,0,1) -> MARCIA CRISTINA SILVA PAIXAO | F13: =_xlfn.XLOOKUP($B13,Entradas!$B:$B,Entradas!F:F,,0,1) -> PROFESSOR DO MAGISTERIO SUPERIOR | G13: =_xlfn.XLOOKUP($B13,Entradas!$B:$B,Entradas!G:G,,0,1) -> -1 | H13: =_xlfn.XLOOKUP($B13,Entradas!$B:$B,Entradas!H:H,,0,1) -> Sem informação | I13: =_xlfn.XLOOKUP($B13,Entradas!$B:$B,Entradas!I:I,,0,1) -> 45130 | J13: =_xlfn.XLOOKUP($B13,Entradas!$B:$B,Entradas!J:J,,0,1) -> 45135 | K13: =_xlfn.XLOOKUP($B13,Entradas!$B:$B,Entradas!K:K,,0,1) -> Participação do Congresso Nacional da SOBER - Sociedade Brasileira de Economia, Administração e Sociologia Rural como apresentadora de trabalhos, caso o primeiro autor não possa comparecer ao evento. ? Participação do evento como um todo na condição de congressista. Participação da Assembleia Geral da SOBER como componente do seu Conselho Fiscal. | L13: =SUMIF(Entradas!$B:$B,'Entrada Lvl 5-4 qt'!$B13,Entradas!S:S) -> 4398.3351 | M13: =_xlfn.XLOOKUP($B13,Entradas!$B:$B,Entradas!T:T,,0,1) -> Aéreo | N13: =_xlfn.XLOOKUP($B13,Entradas!$B:$B,Entradas!U:U,,0,1) -> Sim | O13: =_xlfn.XLOOKUP($B13,Entradas!$B:$B,Entradas!V:V,,0,1) -> Realizada | P13: =_xlfn.XLOOKUP($B13,Entradas!$B:$B,Entradas!W:W,,0,1) -> NÃO | Q13: =_xlfn.XLOOKUP($B13,Entradas!$B:$B,Entradas!X:X,,0,1) -> Sem informação | R13: =SUMIF(Entradas!$B:$B,'Entrada Lvl 5-4 qt'!$B13,Entradas!Y:Y) -> 1600.4 | S13: =SUMIF(Entradas!$B:$B,'Entrada Lvl 5-4 qt'!$B13,Entradas!Z:Z) -> 0 | T13: =SUMIF(Entradas!$B:$B,'Entrada Lvl 5-4 qt'!$B13,Entradas!AA:AA) -> 2831.61 | U13: =SUMIF(Entradas!$B:$B,'Entrada Lvl 5-4 qt'!$B13,Entradas!AB:AB) -> 0 | V13: =_xlfn.XLOOKUP($B13,Entradas!$B:$B,Entradas!AC:AC,,0,1) -> 45083 | W13: =J13-I13 -> 5 | X13: Econômica | Y13: =IF(A13<3,0,1) -> 0 | Z13: =IFERROR(SUM(T13:U13),0) -> 2831.61 | AA13: =IFERROR(SUM(R13:S13),0) -> 1600.4 | AB13: Participação em Evento Acadêmico | AC13: Acadêmico | AD13: {=_xlfn.IFS(L13<=Constantes!$G$2,"Muito Curta (evitável)",L13<=Constantes!$H$2,"Curta Distância",L13>Constantes!$H$2,"Longa Distância")} -> Longa Distância | AE13: =IF(P13="SIM",IF(Q13="Sem Informação","SIM","NÃO"),"NÃO") -> NÃO | AF13: =SUMIF(Entradas!$B:$B,'Entrada Lvl 5-4 qt'!$B13,Entradas!$AG:$AG) -> 804.32069
A14: =_xlfn.XLOOKUP(B14,Entradas!B:B,Entradas!A:A,,0,-1) -> 2 | B14: 19040494 | C14: =_xlfn.XLOOKUP($B14,Entradas!$B:$B,Entradas!C:C,,0,1) -> 000477/23 | D14: =_xlfn.XLOOKUP($B14,Entradas!$B:$B,Entradas!D:D,,0,1) -> ***.840.844-** | E14: =_xlfn.XLOOKUP($B14,Entradas!$B:$B,Entradas!E:E,,0,1) -> HEMILIO FERNANDES CAMPOS COELHO | F14: =_xlfn.XLOOKUP($B14,Entradas!$B:$B,Entradas!F:F,,0,1) -> PROFESSOR DO MAGISTERIO SUPERIOR | G14: =_xlfn.XLOOKUP($B14,Entradas!$B:$B,Entradas!G:G,,0,1) -> FG-0001 | H14: =_xlfn.XLOOKUP($B14,Entradas!$B:$B,Entradas!H:H,,0,1) -> FG-0001 | I14: =_xlfn.XLOOKUP($B14,Entradas!$B:$B,Entradas!I:I,,0,1) -> 45130 | J14: =_xlfn.XLOOKUP($B14,Entradas!$B:$B,Entradas!J:J,,0,1) -> 45136 | K14: =_xlfn.XLOOKUP($B14,Entradas!$B:$B,Entradas!K:K,,0,1) -> Participação do evento científico 67ª Reunião Anual da Região Brasileira da Sociedade Internacional de Biometria (RBras) e 20º Simpósio de Estatística Aplicada à Experimentação Agronômica (SEAGRO) que serão realizados no Centro de Eventos e Convenções do Aurora Shopping na cidade de Londrina. | L14: =SUMIF(Entradas!$B:$B,'Entrada Lvl 5-4 qt'!$B14,Entradas!S:S) -> 4992.8231 | M14: =_xlfn.XLOOKUP($B14,Entradas!$B:$B,Entradas!T:T,,0,1) -> Aéreo | N14: =_xlfn.XLOOKUP($B14,Entradas!$B:$B,Entradas!U:U,,0,1) -> Sim | O14: =_xlfn.XLOOKUP($B14,Entradas!$B:$B,Entradas!V:V,,0,1) -> Realizada | P14: =_xlfn.XLOOKUP($B14,Entradas!$B:$B,Entradas!W:W,,0,1) -> NÃO | Q14: =_xlfn.XLOOKUP($B14,Entradas!$B:$B,Entradas!X:X,,0,1) -> Sem informação | R14: =SUMIF(Entradas!$B:$B,'Entrada Lvl 5-4 qt'!$B14,Entradas!Y:Y) -> 1901.3 | S14: =SUMIF(Entradas!$B:$B,'Entrada Lvl 5-4 qt'!$B14,Entradas!Z:Z) -> 0 | T14: =SUMIF(Entradas!$B:$B,'Entrada Lvl 5-4 qt'!$B14,Entradas!AA:AA) -> 3020.87 | U14: =SUMIF(Entradas!$B:$B,'Entrada Lvl 5-4 qt'!$B14,Entradas!AB:AB) -> 0 | V14: =_xlfn.XLOOKUP($B14,Entradas!$B:$B,Entradas!AC:AC,,0,1) -> 45106 | W14: =J14-I14 -> 6 | X14: Econômica | Y14: =IF(A14<3,0,1) -> 0 | Z14: =IFERROR(SUM(T14:U14),0) -> 3020.87 | AA14: =IFERROR(SUM(R14:S14),0) -> 1901.3 | AB14: Participação em Evento Acadêmico | AC14: Acadêmico | AD14: {=_xlfn.IFS(L14<=Constantes!$G$2,"Muito Curta (evitável)",L14<=Constantes!$H$2,"Curta Distância",L14>Constantes!$H$2,"Longa Distância")} -> Longa Distância | AE14: =IF(P14="SIM",IF(Q14="Sem Informação","SIM","NÃO"),"NÃO") -> NÃO | AF14: =SUMIF(Entradas!$B:$B,'Entrada Lvl 5-4 qt'!$B14,Entradas!$AG:$AG) -> 913.03434
... A415: =_xlfn.XLOOKUP(B415,Entradas!B:B,Entradas!A:A,,0,-1) -> 2 | B415: 19432095 | C415: =_xlfn.XLOOKUP($B415,Entradas!$B:$B,Entradas!C:C,,0,1) -> 001571/23 | D415: =_xlfn.XLOOKUP($B415,Entradas!$B:$B,Entradas!D:D,,0,1) -> ***.418.406-** | E415: =_xlfn.XLOOKUP($B415,Entradas!$B:$B,Entradas!E:E,,0,1) -> ALICE MARA SERRA | F415: =_xlfn.XLOOKUP($B415,Entradas!$B:$B,Entradas!F:F,,0,1) -> PROFESSOR DO MAGISTERIO SUPERIOR | G415: =_xlfn.XLOOKUP($B415,Entradas!$B:$B,Entradas!G:G,,0,1) -> -1 | H415: =_xlfn.XLOOKUP($B415,Entradas!$B:$B,Entradas!H:H,,0,1) -> Sem informação | I415: =_xlfn.XLOOKUP($B415,Entradas!$B:$B,Entradas!I:I,,0,1) -> 45277 | J415: =_xlfn.XLOOKUP($B415,Entradas!$B:$B,Entradas!J:J,,0,1) -> 45281 | K415: =_xlfn.XLOOKUP($B415,Entradas!$B:$B,Entradas!K:K,,0,1) -> Participar do evento A Fenomenologia e seus outros, como apresentadora e debatedora. | L415: =SUMIF(Entradas!$B:$B,'Entrada Lvl 5-4 qt'!$B415,Entradas!S:S) -> 3429.6731 | M415: =_xlfn.XLOOKUP($B415,Entradas!$B:$B,Entradas!T:T,,0,1) -> Aéreo | N415: =_xlfn.XLOOKUP($B415,Entradas!$B:$B,Entradas!U:U,,0,1) -> Não | O415: =_xlfn.XLOOKUP($B415,Entradas!$B:$B,Entradas!V:V,,0,1) -> Realizada | P415: =_xlfn.XLOOKUP($B415,Entradas!$B:$B,Entradas!W:W,,0,1) -> NÃO | Q415: =_xlfn.XLOOKUP($B415,Entradas!$B:$B,Entradas!X:X,,0,1) -> Sem informação | R415: =SUMIF(Entradas!$B:$B,'Entrada Lvl 5-4 qt'!$B415,Entradas!Y:Y) -> 887.73 | S415: =SUMIF(Entradas!$B:$B,'Entrada Lvl 5-4 qt'!$B415,Entradas!Z:Z) -> 0 | T415: =SUMIF(Entradas!$B:$B,'Entrada Lvl 5-4 qt'!$B415,Entradas!AA:AA) -> 2647.89 | U415: =SUMIF(Entradas!$B:$B,'Entrada Lvl 5-4 qt'!$B415,Entradas!AB:AB) -> 0 | V415: =_xlfn.XLOOKUP($B415,Entradas!$B:$B,Entradas!AC:AC,,0,1) -> 45225 | W415: =J415-I415 -> 4 | X415: Econômica | Y415: =IF(A415<3,0,1) -> 0 | Z415: =IFERROR(SUM(T415:U415),0) -> 2647.89 | AA415: =IFERROR(SUM(R415:S415),0) -> 887.73 | AB415: Participação em Evento Acadêmico | AC415: Acadêmico | AD415: {=_xlfn.IFS(L415<=Constantes!$G$2,"Muito Curta (evitável)",L415<=Constantes!$H$2,"Curta Distância",L415>Constantes!$H$2,"Longa Distância")} -> Curta Distância | AE415: =IF(P415="SIM",IF(Q415="Sem Informação","SIM","NÃO"),"NÃO") -> NÃO | AF415: =SUMIF(Entradas!$B:$B,'Entrada Lvl 5-4 qt'!$B415,Entradas!$AG:$AG) -> 627.1821

Sheet Entrada Lvl 5-4 ql
A1: Indicador | B1: Descrição | C1: Score
A2: DF1.1 | B2: Contabilização do voo como parte do trabalho | C2: 1
A3: DF1.2 | B3: Intercâmbio sem deslocamento aéreo | C3: 0
A4: DF1.3 | B4: Descrição do motivo do voo | C4: 1
A5: IB1.1 | B5: Uso de classe econômica | C5: 1 | D5: =IF(C5=1,"Atendida","Não Atendida") -> Atendida
A6: IB1.2 | B6: Gerenciamento, priorização e monitoramento de voos | C6: 1 | D6: =IF(C6=1,"Atendida","Não Atendida") -> Atendida
A7: IB1.3 | B7: Programas de mitigação de emissões aéreas | C7: 0 | D7: =IF(C7=1,"Atendida","Não Atendida") -> Não Atendida
A8: IB2.1 | B8: Hibridização de Eventos e Conferências | C8: 0 | D8: =IF(C8=1,"Atendida","Não Atendida") -> Não Atendida
A9: IB2.2 | B9: Acesso a alternativas ao voo | C9: 0 | D9: =IF(C9=1,"Atendida","Não Atendida") -> Não Atendida
A10: IB2.3 | B10: Incentivo a participações remotas | C10: 0 | D10: =IF(C10=1,"Atendida","Não Atendida") -> Não Atendida
A11: IB3.1 | B11: Inventário de viagens aéreas | C11: 1 | D11: =IF(C11=1,"Atendida","Não Atendida") -> Atendida
A12: IB3.2 | B12: Campanhas de conscientização | C12: 0 | D12: =IF(C12=1,"Atendida","Não Atendida") -> Não Atendida
A13: IB3.3 | B13: Viagens aéreas como critério de seleção | C13: 0 | D13: =IF(C13=1,"Atendida","Não Atendida") -> Não Atendida
A14: IB3.4 | B14: Relatório público de emissões | C14: 0 | D14: =IF(C14=1,"Atendida","Não Atendida") -> Não Atendida
A18: Indicador | B18: Descrição | C18: Documentação Relacionada | D18: Transcrição | E18: Considerações sobre a pontuação dada
A19: DF1.1 | B19: Contabilização do voo como parte do trabalho | C19: Instrução Normativa Nº 01, de janeiro de 2020 | D19: Art. 3º Para fins desta Portaria, consideram-se: (...) II - Proposto: aquele que realizará o afastamento a serviço, nacional ou internacional, no interesse da Administração Pública, o qual se responsabiliza pela fidelidade das informações fornecidas; (...)
A20: DF1.2 | B20: Intercâmbio sem deslocamento aéreo
A21: DF1.3 | B21: Descrição do motivo do voo | C21: Instrução Normativa Nº 01, de janeiro de 2020 | D21: Art. 15º O Solicitante de Viagem, ao cadastrar a PCDP no SCDP, deve incluir os dados exigidos e anexar os seguintes documentos: I – Formulário de requisição de diárias e passagens obrigatório devidamente preenchido, conforme modelo constante no endereço eletrônico da Pró-Reitoria de Administração (PRA); II - convite; III - programação da missão; IV - documentação que comprove a participação em atividades que exijam a realização de trechos com embarque e desembarque em locais distintos (quando houver);
A22: IB1.1 | B22: Uso de classe econômica | C22: Instrução Normativa Nº 01, de janeiro de 2020 | D22: V - A escolha da tarifa deve privilegiar o menor preço, identificado entre os voos disponíveis na data de realização da pesquisa de passagens, prevalecendo, sempre que possível, a tarifa em classe econômica
A23: IB1.2 | B23: Gerenciamento, priorização e monitoramento de voos | C23: Instrução Normativa Nº 01, de janeiro de 2020 | D23: Art. 2º Todas as viagens, no interesse da Administração, no âmbito da UFPB, deverão ser registradas no Sistema de Concessão de Diárias e Passagens - SCDP, devendo ser observado o Manual do Usuário do Sistema, desenvolvido pelo Ministério da Economia e disponível na página principal de Acesso ao SCDP.
D24: Art. 21º(...) Parágrafo único. É vedada a emissão de bilhete em data não condizente com a participação do servidor no evento.
A25: IB1.3 | B25: Programas de mitigação de emissões aéreas | C25: Instrução Normativa Nº 01, de janeiro de 2020 | D25: Art. 19º As solicitações de deslocamentos que se iniciarem em sextas-feiras, bem como as que incluam sábados, domingos e feriados deverão ser expressamente justificadas, realizando-se com estrita finalidade pública. Parágrafo único. É vedada a solicitação de viagem em data não condizente com a participação do servidor no evento.
C26: Instrução Normativa Nº 01, de janeiro de 2020 | D26: Art. 21º(...) I - a escolha do voo deve recair prioritariamente em percursos de menor duração, evitando-se, sempre que possível, trechos com escalas e conexões;
C27: Instrução Normativa Nº 01, de janeiro de 2020 | D27: Art. 38º A participação de servidores em feiras, fóruns, seminários, congressos, simpósios, grupos de trabalho e outros eventos será de, no máximo, dois representantes para eventos no país e um representante para eventos no exterior, por unidade ou entidade vinculada.
A28: IB2.1 | B28: Hibridização de Eventos e Conferências
A29: IB2.2 | B29: Acesso a alternativas ao voo
A30: IB2.3 | B30: Incentivo a participações remotas
A31: IB3.1 | B31: Inventário de viagens aéreas | C31: Instrução Normativa Nº 01, de janeiro de 2020 | D31: Art. 3º Para fins desta Portaria, consideram-se: I- Proposta de Concessão de Diárias e Passagens cadastrada - PCDP: proposta cadastrada no SCDP, em que deverão constar os dados do proposto, as informações do deslocamento, as justificativas da missão, os documentos comprobatórios da demanda e os dados financeiros;
A32: IB3.2 | B32: Campanhas de conscientização
A33: IB3.3 | B33: Viagens aéreas como critério de seleção
A34: IB3.4 | B34: Relatório público de emissões

Sheet Agregação Lvl 3-1
A1: Indicadores quantitativos baseados na variação ao longo do tempo
A2: Indicador | B2: Baseline (2019.2-2022.2) | C2: 2023.2 | D2: Variação (baseline-2023.2) | E2: score 2023.2 | F2: Critérios de pontuação | G2: Score (Sd) se o valor desejado é maior | H2: Variação em relação à baseline (Vb) | I2: Score (Sd), se o valor desejado é menor | K2: ED1 | L2: ED2 | M2: ED3 | N2: DF1 | O2: DF2 | P2: IB1 | Q2: IB2 | R2: IB3 | S2: ED | T2: DF | U2: IB | V2: I
A3: ED1.1 | B3: =[2]Baseline!G75 -> 285440.32 | C3: =HLOOKUP('Agregação Lvl 3-1'!A3,'Entrada Lvl 5-4 qt'!$AH$1:$BB$2,2,FALSE) -> 299057.81 | D3: =IFERROR(((C3-B3)/B3)*100,IF(B3=C3,0,100)) -> 4.7706934 | E3: 0.4 | F3: Score (Sd), se o valor desejado é menor | G3: 0 | H3: se Vb < -40 ou é o menor valor possível | I3: 1 | K3: =AVERAGE(E3:E4) -> 0.4 | L3: =AVERAGE(E5:E9) -> 0.68 | M3: =AVERAGE(E10:E12) -> 0.33333333 | N3: =AVERAGE(E17:E19,E13:E14) -> 0.72 | O3: =SUM(E20:E20) -> 1 | P3: =AVERAGE(E21:E23) -> 0.66666667 | Q3: =AVERAGE(E24:E26) -> 0 | R3: =AVERAGE(E27:E30) -> 0.25 | S3: =AVERAGE(K3:M3) -> 0.47111111 | T3: =AVERAGE(N3:O3) -> 0.86 | U3: =AVERAGE(P3:R3) -> 0.30555556 | V3: =SUMPRODUCT(S3:U3,Constantes!N2:P2) -> 0.48555556
A4: ED1.2 | B4: =[2]Baseline!G76 -> 674.23901 | C4: =HLOOKUP('Agregação Lvl 3-1'!A4,'Entrada Lvl 5-4 qt'!$AH$1:$BB$2,2,FALSE) -> 722.36185 | D4: =IFERROR(((C4-B4)/B4)*100,IF(B4=C4,0,100)) -> 7.1373555 | E4: 0.4 | F4: Score (Sd), se o valor desejado é menor | G4: 0.1 | H4: se -40 ≤ Vb < -30 | I4: 0.9
A5: ED2.1 | B5: =[2]Baseline!G77 -> 1738431.2 | C5: =HLOOKUP('Agregação Lvl 3-1'!A5,'Entrada Lvl 5-4 qt'!$AH$1:$BB$2,2,FALSE) -> 1610128.8 | D5: =IFERROR(((C5-B5)/B5)*100,IF(B5=C5,0,100)) -> -7.3803548 | E5: 0.6 | F5: Score (Sd), se o valor desejado é menor | G5: 0.2 | H5: se -30 ≤ Vb < -20 | I5: 0.8
A6: ED2.2 | B6: =[2]Baseline!G78 -> 3947.2025 | C6: =HLOOKUP('Agregação Lvl 3-1'!A6,'Entrada Lvl 5-4 qt'!$AH$1:$BB$2,2,FALSE) -> 3889.1999 | D6: =IFERROR(((C6-B6)/B6)*100,IF(B6=C6,0,100)) -> -1.4694595 | E6: 0.6 | F6: Score (Sd), se o valor desejado é menor | G6: 0.3 | H6: se -20 ≤ Vb < -10 | I6: 0.7
A7: ED2.3 | B7: =[2]Baseline!G79 -> 444 | C7: =HLOOKUP('Agregação Lvl 3-1'!A7,'Entrada Lvl 5-4 qt'!$AH$1:$BB$2,2,FALSE) -> 414 | D7: =IFERROR(((C7-B7)/B7)*100,IF(B7=C7,0,100)) -> -6.7567568 | E7: 0.6 | F7: Score (Sd), se o valor desejado é menor | G7: 0.4 | H7: se -10 ≤ Vb < 0 | I7: 0.6
A8: ED2.4 | B8: =[2]Baseline!G80 -> 0.0074944835 | C8: =HLOOKUP('Agregação Lvl 3-1'!A8,'Entrada Lvl 5-4 qt'!$AH$1:$BB$2,2,FALSE) -> 0.0072463768 | D8: =IFERROR(((C8-B8)/B8)*100,IF(B8=C8,0,100)) -> -3.3105242 | E8: 0.6 | F8: Score (Sd), se o valor desejado é menor | G8: 0.5 | H8: Se Vb = 0 | I8: 0.5
A9: ED2.5 | B9: =[2]Baseline!G81 -> 1 | C9: =HLOOKUP('Agregação Lvl 3-1'!A9,'Entrada Lvl 5-4 qt'!$AH$1:$BB$2,2,FALSE) -> 1 | D9: =IFERROR(((C9-B9)/B9)*100,IF(B9=C9,0,100)) -> 0 | E9: 1 | F9: Score (Sd) se o valor desejado é maior | G9: 0.6 | H9: se 0 < Vb ≤ 10 | I9: 0.4
A10: ED3.1 | B10: =[2]Baseline!G82 -> 1196933.5 | C10: =HLOOKUP('Agregação Lvl 3-1'!A10,'Entrada Lvl 5-4 qt'!$AH$1:$BB$2,2,FALSE) -> 1150238 | D10: =IFERROR(((C10-B10)/B10)*100,IF(B10=C10,0,100)) -> -3.9012626 | E10: 0.3 | F10: Score (Sd), se o valor desejado é menor | G10: 0.7 | H10: se 10 < Vb ≤ 20 | I10: 0.3
A11: ED3.2 | B11: =[2]Baseline!G83 -> 521235.35 | C11: =HLOOKUP('Agregação Lvl 3-1'!A11,'Entrada Lvl 5-4 qt'!$AH$1:$BB$2,2,FALSE) -> 547335.04 | D11: =IFERROR(((C11-B11)/B11)*100,IF(B11=C11,0,100)) -> 5.0072758 | E11: 0.4 | F11: Score (Sd), se o valor desejado é menor | G11: 0.8 | H11: se 20 < Vb ≤ 30 | I11: 0.2
A12: ED3.3 | B12: =[2]Baseline!G84 -> 3454.7583 | C12: =HLOOKUP('Agregação Lvl 3-1'!A12,'Entrada Lvl 5-4 qt'!$AH$1:$BB$2,2,FALSE) -> 4100.418 | D12: =IFERROR(((C12-B12)/B12)*100,IF(B12=C12,0,100)) -> 18.688997 | E12: 0.3 | F12: Score (Sd), se o valor desejado é menor | G12: 0.9 | H12: se 30 < Vb ≤ 40 | I12: 0.1
A13: DF1.4 | B13: =[2]Baseline!G85 -> 0.034715826 | C13: =HLOOKUP('Agregação Lvl 3-1'!A13,'Entrada Lvl 5-4 qt'!$AH$1:$BB$2,2,FALSE) -> 0.031400966 | D13: =IFERROR(((C13-B13)/B13)*100,IF(B13=C13,0,100)) -> -9.5485549 | E13: 0.6 | F13: Score (Sd), se o valor desejado é menor | G13: 1 | H13: se Vb > 40 ou é o maior valor possível | I13: 0
A14: DF1.5 | B14: =[2]Baseline!G86 -> 0 | C14: =HLOOKUP('Agregação Lvl 3-1'!A14,'Entrada Lvl 5-4 qt'!$AH$1:$BB$2,2,FALSE) -> 0 | D14: =IFERROR(((C14-B14)/B14)*100,IF(B14=C14,0,100)) -> 0 | E14: 1 | F14: Score (Sd), se o valor desejado é menor | G14: 0 | H14: Se Vb não está disponível | I14: 0
A16: Indicadores qualitativos
A17: DF1.1 | E17: ='Entrada Lvl 5-4 ql'!C2 -> 1 | F17: Indicador qualitativo (0 = não existe; 1 = existe).
A18: DF1.2 | E18: ='Entrada Lvl 5-4 ql'!C3 -> 0 | F18: Indicador qualitativo (0 = não existe; 1 = existe).
A19: DF1.3 | E19: ='Entrada Lvl 5-4 ql'!C4 -> 1 | F19: Indicador qualitativo (0 = não existe; 1 = existe).
A20: DF2.1 | E20: =SUM('Entrada Lvl 5-4 qt'!AZ2:BC2) -> 1 | F20: Indicador qualitativo (0 = não existe; 1 = existe).
A21: IB1.1 | E21: ='Entrada Lvl 5-4 ql'!C5 -> 1 | F21: Indicador qualitativo (0 = não existe; 1 = existe).
A22: IB1.2 | E22: ='Entrada Lvl 5-4 ql'!C6 -> 1 | F22: Indicador qualitativo (0 = não existe; 1 = existe).
A23: IB1.3 | E23: ='Entrada Lvl 5-4 ql'!C7 -> 0 | F23: Indicador qualitativo (0 = não existe; 1 = existe).
A24: IB2.1 | E24: ='Entrada Lvl 5-4 ql'!C8 -> 0 | F24: Indicador qualitativo (0 = não existe; 1 = existe).
A25: IB2.2 | E25: ='Entrada Lvl 5-4 ql'!C9 -> 0 | F25: Indicador qualitativo (0 = não existe; 1 = existe).
A26: IB2.3 | E26: ='Entrada Lvl 5-4 ql'!C10 -> 0 | F26: Indicador qualitativo (0 = não existe; 1 = existe).
A27: IB3.1 | E27: ='Entrada Lvl 5-4 ql'!C11 -> 1 | F27: Indicador qualitativo (0 = não existe; 1 = existe).
A28: IB3.2 | E28: ='Entrada Lvl 5-4 ql'!C12 -> 0 | F28: Indicador qualitativo (0 = não existe; 1 = existe).
A29: IB3.3 | E29: ='Entrada Lvl 5-4 ql'!C13 -> 0 | F29: Indicador qualitativo (0 = não existe; 1 = existe).
A30: IB3.4 | E30: ='Entrada Lvl 5-4 ql'!C14 -> 0 | F30: Indicador qualitativo (0 = não existe; 1 = existe).

Sheet Overview
K1: Período | L1: Jul 2023 - Dez 2023
B3: Emissões, Deslocamento e Custo | D3: ='Agregação Lvl 3-1'!S3 -> 0.47111111 | F3: Motivações para o voo | H3: ='Agregação Lvl 3-1'!T3 -> 0.86 | J3: Barreiras Institucionais | L3: ='Agregação Lvl 3-1'!U3 -> 0.30555556
B5: Análise de Emissões | C5: Análise do Deslocamento | D5: Análise dos Custos | F5: Incentivo à hipermobilidade | G5: Propósitos do voo | J5: Restrições | K5: Incentivo | L5: Mudança Organizacional
B6: ='Agregação Lvl 3-1'!K3 -> 0.4 | C6: ='Agregação Lvl 3-1'!L3 -> 0.68 | D6: ='Agregação Lvl 3-1'!M3 -> 0.33333333 | F6: ='Agregação Lvl 3-1'!N3 -> 0.72 | G6: ='Agregação Lvl 3-1'!O3 -> 1 | J6: ='Agregação Lvl 3-1'!P3 -> 0.66666667 | K6: ='Agregação Lvl 3-1'!Q3 -> 0 | L6: ='Agregação Lvl 3-1'!R3 -> 0.25

Sheet Constantes
A1: Classe | B1: Econômica | C1: Econômica Plus | D1: Executiva | E1: Primeira | G1: di | H1: ds | M1: Pesos GF | N1: p1 | O1: p2 | P1: p3 | R1: IB - Classificação
A2: Muito Curta (evitável) | B2: 0.27257679 | C2: 0.27257679 | D2: 0.27257679 | E2: 0.27257679 | G2: 600 | H2: 3700 | K2: Domestic haul | M2: =SUM(N2:P2) -> 1 | N2: 0.25 | O2: 0.25 | P2: 0.5 | R2: Ignoradora de viagens | S2: 0
A3: Muito Curta (evitável) | B3: 0.27257679 | C3: 0.27257679 | D3: 0.27257679 | E3: 0.27257679 | K3: Short Haul | R3: Reconhecedora, sem intervenção | S3: IB 3.1
A4: Curta Distância | B4: 0.18286935 | C4: 0.27430288 | D4: 0.27430288 | E4: 0.27430288 | K4: Long Haul | R4: Redutora de viagens aéreas | S4: IB1.1; IB1.2; IB1.3; IB3.3; IB3.4
A5: Longa Distância | B5: 0.20010828 | C5: 0.32015519 | D5: 0.58028693 | E5: 0.80040303 | R5: Substituidora de viagens aéreas | S5: IB2.1; IB2.2; IB2.3; IB3.2
A7: *Os fatores já incluem RF e SF | D7: (Wynes et al, 2019) | R7: IB - Classificação
D8: (DESNZ, 2023) | R8: Substituidora de viagens aéreas | S8: =IF(SUM('Entrada Lvl 5-4 ql'!C8,'Entrada Lvl 5-4 ql'!C9,'Entrada Lvl 5-4 ql'!C10,'Entrada Lvl 5-4 ql'!C12)>1,1,0) -> 0 | T8: Busca substituir viagens aéreas | U8: Não busca substituir viagens aéreas
R9: Redutora de viagens aéreas | S9: =IF(SUM('Entrada Lvl 5-4 ql'!C5,'Entrada Lvl 5-4 ql'!C6,'Entrada Lvl 5-4 ql'!C7,'Entrada Lvl 5-4 ql'!C13,'Entrada Lvl 5-4 ql'!C14)>1,1,0) -> 1 | T9: Busca reduzir viagens aéreas | U9: Não busca reduzir viagens aéreas
R10: Reconhecedora, sem intervenção | S10: =IF(SUM('Entrada Lvl 5-4 ql'!C11,'Entrada Lvl 5-4 ql'!C14)>0,1,0) -> 1 | T10: Faz o levantamento de viagens aéreas | U10: Não faz o levantamento de viagens aéreas
R11: Ignoradora de viagens aéreas | S11: ='Entrada Lvl 5-4 ql'!C11 -> 1
R12: Perfil da IES | S12: =IF(S11=0,R11,(IF(S8=1,R8,IF(S9=1,R9,IF(S10=1,R10,R11))))) -> Redutora de viagens aéreas
R14: Perfil da IES | S14: =IF(S11=0,U10,IF(S10=1,T10,U10)) -> Faz o levantamento de viagens aéreas
S15: =IF(S9=1,T9,U9) -> Busca reduzir viagens aéreas
S16: =IF(S8=1,T8,U8) -> Não busca substituir viagens aéreas

Sheet Dados Dashboard
A1: Rótulos de Linha | B1: Soma de Distância (km) | C1: Soma de Emissões | E1: Rótulos de Linha | F1: Soma de Emissões | H1: Rótulos de Linha | I1: Contagem de Motivo da Viagem | K1: Rótulos de Linha | L1: Contagem de Vínculo Institucional | N1: Rótulos de Linha | O1: Soma de Voo com Escala | Q1: Rótulos de Linha | R1: Soma de Custo da passagem | S1: Soma de Outros custos | U1: Rótulos de Linha | V1: Contagem de Classe | X1: Rótulos de Linha | Y1: Contagem de Dias de viagem | AA1: Rótulos de Linha | AB1: Contagem de Viagem Urgente sem justificativa | AD1: Rótulos de Linha | AE1: Contagem de Distância (km) | AG1: Rótulos de Linha | AH1: Contagem de Situação
A2: Curta Distância | B2: 9474.0458 | C2: 1732.5126 | E2: Servidor | F2: 1344.0608 | H2: Participação em Evento Acadêmico | I2: 4 | K2: Servidor | L2: 2 | N2: Servidor | O2: 0 | Q2: Longa Distância | R2: 6475.92 | S2: 1868.2 | U2: Longa Distância | V2: 3 | X2: Até 1 dia | Y2: 7 | AA2: NÃO | AB2: 7 | AD2: Total Geral | AG2: Curta Distância | AH2: 4
A3: Longa Distância | B3: 12225.952 | C3: 2235.7519 | E3: Acadêmico | F3: 1105.8486 | H3: Representação em Evento Institucional | I3: 2 | K3: Acadêmico | L3: 3 | N3: Acadêmico | O3: 0 | Q3: Curta Distância | R3: 10033.12 | S3: 1951.87 | U3: Curta Distância | V3: 4 | X3: Total Geral | Y3: 7 | AA3: Total Geral | AB3: 7 | AG3: Longa Distância | AH3: 3
A4: Total Geral | B4: 21699.997 | C4: 3968.2645 | E4: Externo | F4: 1518.3551 | H4: Representação em Reunião Institucional | I4: 1 | K4: Externo | L4: 2 | N4: Externo | O4: 0 | Q4: Total Geral | R4: 16509.04 | S4: 3820.07 | U4: Total Geral | V4: 7 | AG4: Total Geral | AH4: 7
E5: Total Geral | F5: 3968.2645 | H5: Total Geral | I5: 7 | K5: Total Geral | L5: 7 | N5: Total Geral | O5: 0
A43: Total de distância percorrida | B43: =GETPIVOTDATA("Distância (km)",$A$1) -> 21699.997 | R43: Custo total com Passagens | S43: =GETPIVOTDATA("Soma de Custo da passagem",$Q$1) -> 16509.04 | U43: Total de Viagens (econômica) | V43: =GETPIVOTDATA("Classe",$U$1) -> 7 | X43: Número de viagens rápidas (até 1 dia) | Y43: =IFERROR(GETPIVOTDATA("Dias de viagem",$X$1,"Dias de viagem2","Até 1 dia"), 0) -> 7 | AA43: Viagens urgentes sem informação | AB43: =IFERROR(GETPIVOTDATA("Viagem Urgente sem justificativa",$AA$1,"Viagem Urgente sem justificativa","SIM"),0) -> 0
A44: Total de emissões (KgCO2e) | B44: =GETPIVOTDATA("Soma de Emissões",$A$1) -> 3968.2645 | E44: Total de emissões (KgCO2e) | F44: =GETPIVOTDATA("Emissões",$E$1) -> 3968.2645 | H44: Total de Viagens | I44: =GETPIVOTDATA("Situação",$AG$1) -> 7 | N44: Total de viagens com escala | O44: =GETPIVOTDATA("Voo com Escala",$N$1) -> 0 | R44: Outros custos | S44: =GETPIVOTDATA("Soma de Outros custos",$Q$1) -> 3820.07 | U44: Taxa de viagens Econômica | V44: =IFERROR(V43/I44,0) -> 1 | X44: Número de viagens curtas (menos de 600 km ida e volta) | Y44: =IFERROR(GETPIVOTDATA("Distância (km)",$AD$1),0) -> 0 | AA44: Taxa de viagens urgentes | AB44: =IFERROR(AB43/V43,0) -> 0
H45: Emissão média por viagem | I45: =IFERROR(B44/I44,0) -> 566.89493 | N45: tx de viagens com escala | O45: =IFERROR(O44/I44,0) -> 0 | R45: Custo médio por viagem | S45: =IFERROR(SUM(S43:S44)/I44,0) -> 2904.1586
H46: Distância média por viagem | I46: =IFERROR(B43/I44,0) -> 3099.9996 | X46: Taxa de viagens curtas (evitáveis) | Y46: =IFERROR(SUM(Y43:Y44)/I44,0) -> 1
